Workbook

Sheet Guide
A1: Guide | B1: Explanation of all sheets
A3: Red sheet | B3: API to the spatial model
A4: Q | B4: Quantities from the spatial model
A6: 1 | B6: City-scale financial models
A7: 1off-site | B7: Off-site costs and revenues, e.g. for trunk infrastructure (costs) and value capture along the trunk line (revenue).
A8: 1site | B8: Optional calculations on landowners and their lands: e.g. for structuring a potential land pooling and land readjustment (LPLR) project
A9: 1db | B9: City Scale Proforma (DashBoard representation)
A11: 2 | B11: Neighborhood-scale financial models
A12: 2neighborhood | B12: Neighborhood scale financial model
A13: 2db | B13: Neighborhood Scale Proforma (DashBoard representation)
A15: 3 | B15: Cluster-scale financial models
A16: 3cluster_artery | B16: Financial model for off-grid clusters along ARTeries
A17: 3cluster_secondary | B17: Financial model for off-grid clusters along SECondaries
A18: 3cluster_local | B18: Financial model for off-grid clusters along local roads that a SINGLE level of clusters
A19: 3cluster_2levels | B19: Financial model for off-grid clusters along local roads that a MULTIPLE level of clusters
A20: 3db | B20: Cluster Scale Proforma (DashBoard representation)
A22: 4 | B22: Building-scale financial models
A23: 4buildings | B23: Building scale financial model
A24: 4db | B24: Building Scale Proforma (DashBoard representation)
A26: 5 | B26: Unit-scale financial models
A27: 5dwellings | B27: Carving out main residential units as well as optional rooms for sublet from the residential area
A28: 5finande | B28: housing finance model, including rental revenue from sublets
A29: 5affordability | B29: Affordability assessment: which households are able to afford main dwellings for ownership and sublet rental rooms?
A30: 5db | B30: Dwelling Scale Proforma (DashBoard representation)
A32: 6 | B32: Demographic projections
A33: 6demographics | B33: Demographic projections, assuming intital and consolidated lot development, number of dwelling units, and household size
A34: 6db | B34: Demographic projection summary
A36: blue sheets | B36: Negotiation and mediation, phasing, and financial efficiency
A37: stakes | B37: allocation of costs and benefits across stakeholders
... A43: Legal information | B43: This spreadsheet is IP of Mat Nohn alias Rapid Urbanism. Contact: nohn@rapidurbanism.com

Sheet Q
A1: Public street network (length)
A2: Public network, by network level (in color code) | C2: 2-sided @100% | D2: 1-sided @50% | E2: zero sided (@tbd) | F2: Subtotal project-borne
B3: Arteries (main roads) | C3: 0 | D3: 0 | E3: 0 | F3: =C3+D3/2 -> 0
B4: Secondaries (distributor roads) | C4: 0 | D4: 0 | E4: 0 | F4: =C4+D4/2 -> 0
B5: Tertiaries (access and local roads) | C5: 0 | D5: 0 | E5: 0 | F5: =C5+D5/2 -> 0
B6: Subtotal project-borne | C6: =SUM(C3:C5) -> 0 | D6: =SUM(D3:D5)/2 -> 0 | E6: =SUM(E3:E5)*0 -> 0 | F6: =SUM(F3:F5) -> 0
A8: Land use (city and neighborhood scale) | X8: Lots and buildings (idealized)
A9: Land uses, by location (in color code) | C9: Environmental reservation | D9: Social reservation | E9: Other non-developable area | F9: Non-developable area | G9: Public streets | H9: City-scale public open spaces, subtotal | I9: City-scale public amenities, subtotal | J9: District-scale public open spaces, subtotal | K9: District-scale public amenities, subtotal | L9: Neighborhood-scale open spaces, subtotal | M9: Neighborhood-scale public amenities, subtotal | N9: Public lands, subtotal | O9: Private lands, subtotals | P9: Developable area, subtotals | Q9: All lands, totals | R9: Distribution (share of total) | X9: Number of lots | Y9: lot d | Z9: lot w | AA9: lot A | AB9: front margin | AC9: back margin | AD9: footprint d | AE9: side margin | AF9: side margin 2 | AG9: footprint w | AH9: footprint A | AI9: floors regular | AJ9: corner bonus | AK9: floors final | AL9: floor area | AM9: max. FAR viable | AO9: starter w | AP9: starter d | AQ9: starter f | AR9: starter w | AS9: starter d | AT9: starter f | AU9: Starter building, average floor area, if any
B10: =C9 -> Environmental reservation | C10: =C60*10000 -> 0 | F10: =SUM(C10:E10) -> 0 | Q10: =F10 -> 0 | R10: =Q10/Q37 -> #DIV/0!
B11: =D9 -> Social reservation | D11: =D60*10000 -> 0 | F11: =SUM(C11:E11) -> 0 | Q11: =F11 -> 0 | R11: =Q11/Q37 -> #DIV/0!
B12: =E9 -> Other non-developable area | E12: 0 | F12: =SUM(C12:E12) -> 0 | Q12: =F12 -> 0 | R12: =Q12/Q37 -> #DIV/0!
B13: Reservations, outside neighborhod | C13: =C10 -> 0 | D13: =D11 -> 0 | E13: =E12 -> 0 | F13: =SUM(F10:F12) -> 0 | Q13: =SUM(Q10:Q12) -> 0 | R13: =Q13/Q37 -> #DIV/0!
B14: Artery x artery (corner) | H14: 0 | I14: 0 | J14: 0 | K14: 0 | L14: 0 | M14: 0 | N14: =SUM(G14:M14) -> 0 | O14: 0 | P14: =SUM(N14:O14) -> 0 | Q14: =P14 -> 0 | R14: =Q14/Q37 -> #DIV/0! | U14: Artery x artery (corner) | X14: 0 | Y14: =Y17 -> 0 | Z14: =Y17 -> 0 | AA14: =Z14*Y14 -> 0 | AB14: =AB17 -> 0 | AC14: =AC17 -> 0 | AD14: =Y14-AB14-AC14 -> 0 | AE14: =AE17 -> 0 | AF14: =AE17 -> 0 | AG14: =Z14-AE14-AF14 -> 0 | AH14: =AG14*AD14 -> 0 | AJ14: 0 | AK14: =ROUND(AI17*(1+AJ14),0) -> 0 | AL14: =AG14*AD14*AK14 -> 0 | AM14: =IF(AA14=0,0,AL14/AA14) -> 0 | AO14: 0 | AP14: 0 | AQ14: 0 | AR14: =AO14*AG14 -> 0 | AS14: =AP14*AD14 -> 0 | AT14: =ROUND(AQ14*AK14,0) -> 0 | AU14: =AL14*AP14*AQ14 -> 0
B15: Artery x secondary (corner) | H15: 0 | I15: 0 | J15: 0 | K15: 0 | L15: 0 | M15: 0 | N15: =SUM(G15:M15) -> 0 | O15: 0 | P15: =SUM(N15:O15) -> 0 | Q15: =P15 -> 0 | R15: =Q15/Q37 -> #DIV/0! | U15: Artery x secondary (corner) | X15: 0 | Y15: =Y17 -> 0 | Z15: =Y21 -> 0 | AA15: =Z15*Y15 -> 0 | AB15: =AB17 -> 0 | AC15: =AC17 -> 0 | AD15: =Y15-AB15-AC15 -> 0 | AE15: =AE17 -> 0 | AF15: =AE21 -> 0 | AG15: =Z15-AE15-AF15 -> 0 | AH15: =AG15*AD15 -> 0 | AJ15: 0 | AK15: =ROUND(AI17*(1+AJ15),0) -> 0 | AL15: =AG15*AD15*AK15 -> 0 | AM15: =IF(AA15=0,0,AL15/AA15) -> 0 | AO15: 0 | AP15: 0 | AQ15: 0 | AR15: =AO15*AG15 -> 0 | AS15: =AP15*AD15 -> 0 | AT15: =ROUND(AQ15*AK15,0) -> 0 | AU15: =AL15*AP15*AQ15 -> 0
B16: Artery x tertiary (corner) | H16: 0 | I16: 0 | J16: 0 | K16: 0 | L16: 0 | M16: 0 | N16: =SUM(G16:M16) -> 0 | O16: 0 | P16: =SUM(N16:O16) -> 0 | Q16: =P16 -> 0 | R16: =Q16/Q37 -> #DIV/0! | U16: Artery x tertiary (corner) | X16: 0 | Y16: =Y17 -> 0 | Z16: =Y24 -> 0 | AA16: =Z16*Y16 -> 0 | AB16: =AB17 -> 0 | AC16: =AC17 -> 0 | AD16: =Y16-AB16-AC16 -> 0 | AE16: =AE17 -> 0 | AF16: =AE24 -> 0 | AG16: =Z16-AE16-AF16 -> 0 | AH16: =AG16*AD16 -> 0 | AJ16: 0 | AK16: =ROUND(AI17*(1+AJ16),0) -> 0 | AL16: =AG16*AD16*AK16 -> 0 | AM16: =IF(AA16=0,0,AL16/AA16) -> 0 | AO16: 0 | AP16: 0 | AQ16: 0 | AR16: =AO16*AG16 -> 0 | AS16: =AP16*AD16 -> 0 | AT16: =ROUND(AQ16*AK16,0) -> 0 | AU16: =AL16*AP16*AQ16 -> 0
B17: Artery (regular) | H17: 0 | I17: 0 | J17: 0 | K17: 0 | L17: 0 | M17: 0 | N17: =SUM(G17:M17) -> 0 | O17: 0 | P17: =SUM(N17:O17) -> 0 | Q17: =P17 -> 0 | R17: =Q17/Q37 -> #DIV/0! | U17: Artery (regular) | X17: 0 | Y17: 0 | Z17: 0 | AA17: =Z17*Y17 -> 0 | AB17: 0 | AC17: 0 | AD17: =Y17-AB17-AC17 -> 0 | AE17: 0 | AF17: =AE17 -> 0 | AG17: =Z17-AE17-AF17 -> 0 | AH17: =AG17*AD17 -> 0 | AI17: 0 | AJ17: 0 | AK17: =ROUND(AI17*(1+AJ17),0) -> 0 | AL17: =AG17*AD17*AK17 -> 0 | AM17: =IF(AA17=0,0,AL17/AA17) -> 0 | AO17: 0 | AP17: 0 | AQ17: 0 | AR17: =AO17*AG17 -> 0 | AS17: =AP17*AD17 -> 0 | AT17: =ROUND(AQ17*AK17,0) -> 0 | AU17: =AL17*AP17*AQ17 -> 0
A18: Land on arteries, subtotal | F18: =SUM(F14:F17) -> 0 | H18: =SUM(H14:H17) -> 0 | I18: =SUM(I14:I17) -> 0 | J18: =SUM(J14:J17) -> 0 | K18: =SUM(K14:K17) -> 0 | L18: =SUM(L14:L17) -> 0 | M18: =SUM(M14:M17) -> 0 | N18: =SUM(N14:N17) -> 0 | O18: =SUM(O14:O17) -> 0 | ... Q18: =SUM(Q14:Q17) -> 0 | R18: =Q18/Q37 -> #DIV/0! | T18: w/path | X18: =C45*2 -> 0 | Y18: =Y17 -> 0 | Z18: =Z17 -> 0 | AA18: =AA17 -> 0 | AB18: =AB17 -> 0 | AC18: =AC17 -> 0 | AD18: =AD17 -> 0 | AE18: =AE17 -> 0 | AF18: =AF17 -> 0 | ... AH18: =AH17 -> 0 | AK18: =AK17 -> 0 | AL18: =AL17 -> 0 | AM18: =IF(AA18=0,0,AL18/AA18) -> 0 | AO18: =AO17 -> 0 | AP18: =AP17 -> 0 | AQ18: =AQ17 -> 0 | AR18: =AO18*AG18 -> 0 | AS18: =AP18*AD18 -> 0 | AT18: =ROUND(AQ18*AK18,0) -> 0 | AU18: =AU17 -> 0
B19: Secondary x secondary (corner) | H19: 0 | I19: 0 | J19: 0 | K19: 0 | L19: 0 | M19: 0 | N19: =SUM(G19:M19) -> 0 | O19: 0 | P19: =SUM(N19:O19) -> 0 | Q19: =P19 -> 0 | R19: =Q19/Q37 -> #DIV/0! | U19: Secondary x secondary (corner) | X19: 0 | Y19: =Y21 -> 0 | Z19: =Y21 -> 0 | AA19: =Z19*Y19 -> 0 | AB19: =AB21 -> 0 | AC19: =AC21 -> 0 | AD19: =Y19-AB19-AC19 -> 0 | AE19: =AE21 -> 0 | AF19: =AE21 -> 0 | AG19: =Z19-AE19-AF19 -> 0 | AH19: =AG19*AD19 -> 0 | AJ19: =AJ15 -> 0 | AK19: =ROUND(AI21*(1+AJ19),0) -> 0 | AL19: =AG19*AD19*AK19 -> 0 | AM19: =IF(AA19=0,0,AL19/AA19) -> 0 | AO19: 0 | AP19: 0 | AQ19: 0 | AR19: =AO19*AG19 -> 0 | AS19: =AP19*AD19 -> 0 | AT19: =ROUND(AQ19*AK19,0) -> 0 | AU19: =AL19*AP19*AQ19 -> 0
B20: Secondary x tertiary (corner) | H20: 0 | I20: 0 | J20: 0 | K20: 0 | L20: 0 | M20: 0 | N20: =SUM(G20:M20) -> 0 | O20: 0 | P20: =SUM(N20:O20) -> 0 | Q20: =P20 -> 0 | R20: =Q20/Q37 -> #DIV/0! | U20: Secondary x tertiary (corner) | X20: 0 | Y20: =Y21 -> 0 | Z20: =Y24 -> 0 | AA20: =Z20*Y20 -> 0 | AB20: =AB21 -> 0 | AC20: =AC21 -> 0 | AD20: =Y20-AB20-AC20 -> 0 | AE20: =AE21 -> 0 | AF20: =AE24 -> 0 | AG20: =Z20-AE20-AF20 -> 0 | AH20: =AG20*AD20 -> 0 | AJ20: =AJ16 -> 0 | AK20: =ROUND(AI21*(1+AJ20),0) -> 0 | AL20: =AG20*AD20*AK20 -> 0 | AM20: =IF(AA20=0,0,AL20/AA20) -> 0 | AO20: 0 | AP20: 0 | AQ20: 0 | AR20: =AO20*AG20 -> 0 | AS20: =AP20*AD20 -> 0 | AT20: =ROUND(AQ20*AK20,0) -> 0 | AU20: =AL20*AP20*AQ20 -> 0
B21: Secondary (regular) | H21: 0 | I21: 0 | J21: 0 | K21: 0 | L21: 0 | M21: 0 | N21: =SUM(G21:M21) -> 0 | O21: 0 | P21: =SUM(N21:O21) -> 0 | Q21: =P21 -> 0 | R21: =Q21/Q37 -> #DIV/0! | U21: Secondary (regular) | X21: 0 | Y21: 0 | Z21: 0 | AA21: =Z21*Y21 -> 0 | AB21: 0 | AC21: 0 | AD21: =Y21-AB21-AC21 -> 0 | AE21: 0 | AF21: =AE21 -> 0 | AG21: =Z21-AE21-AF21 -> 0 | AH21: =AG21*AD21 -> 0 | AI21: 0 | AJ21: 0 | AK21: =ROUND(AI21*(1+AJ21),0) -> 0 | AL21: =AG21*AD21*AK21 -> 0 | AM21: =IF(AA21=0,0,AL21/AA21) -> 0 | AO21: 0 | AP21: 0 | AQ21: 0 | AR21: =AO21*AG21 -> 0 | AS21: =AP21*AD21 -> 0 | AT21: =ROUND(AQ21*AK21,0) -> 0 | AU21: =AL21*AP21*AQ21 -> 0
B22: Land on secondaries, subtotal | F22: =SUM(F19:F21) -> 0 | H22: =SUM(H19:H21) -> 0 | I22: =SUM(I19:I21) -> 0 | J22: =SUM(J19:J21) -> 0 | K22: =SUM(K19:K21) -> 0 | L22: =SUM(L19:L21) -> 0 | M22: =SUM(M19:M21) -> 0 | N22: =SUM(N19:N21) -> 0 | O22: =SUM(O19:O21) -> 0 | ... Q22: =SUM(Q19:Q21) -> 0 | R22: =Q22/Q37 -> #DIV/0! | U22: w/ path | X22: =C46*2 -> 0 | Y22: =Y21 -> 0 | Z22: =Z21 -> 0 | AA22: =AA21 -> 0 | AB22: =AB21 -> 0 | AC22: =AC21 -> 0 | AD22: =AD21 -> 0 | AE22: =AE21 -> 0 | AF22: =AF21 -> 0 | ... AH22: =AH21 -> 0 | AK22: =AK21 -> 0 | AL22: =AL21 -> 0 | AM22: =IF(AA22=0,0,AL22/AA22) -> 0 | AO22: =AO21 -> 0 | AP22: =AP21 -> 0 | AQ22: =AQ21 -> 0 | AR22: =AO22*AG22 -> 0 | AS22: =AP22*AD22 -> 0 | AT22: =ROUND(AQ22*AK22,0) -> 0 | AU22: =AU21 -> 0
B23: Tertiary x tertiary (corner) | H23: 0 | I23: 0 | J23: 0 | K23: 0 | L23: 0 | M23: 0 | N23: =SUM(G23:M23) -> 0 | O23: 0 | P23: =SUM(N23:O23) -> 0 | Q23: =P23 -> 0 | R23: =Q23/Q37 -> #DIV/0! | U23: Tertiary x tertiary (corner) | X23: 0 | Y23: =Y24 -> 0 | Z23: =Y24 -> 0 | AA23: =Z23*Y23 -> 0 | AB23: =AB24 -> 0 | AC23: =AC24 -> 0 | AD23: =Y23-AB23-AC23 -> 0 | AE23: =AE24 -> 0 | AF23: =AE24 -> 0 | AG23: =Z23-AE23-AF23 -> 0 | AH23: =AG23*AD23 -> 0 | AJ23: =AJ16 -> 0 | AK23: =ROUND(AI24*(1+AJ23),0) -> 0 | AL23: =AG23*AD23*AK23 -> 0 | AM23: =IF(AA23=0,0,AL23/AA23) -> 0 | AO23: 0 | AP23: 0 | AQ23: 0 | AR23: =AO23*AG23 -> 0 | AS23: =AP23*AD23 -> 0 | AT23: =ROUND(AQ23*AK23,0) -> 0 | AU23: =AL23*AP23*AQ23 -> 0
B24: Tertiary (regular) | H24: 0 | I24: 0 | J24: 0 | K24: 0 | L24: 0 | M24: 0 | N24: =SUM(G24:M24) -> 0 | O24: 0 | P24: =SUM(N24:O24) -> 0 | Q24: =P24 -> 0 | R24: =Q24/Q37 -> #DIV/0! | U24: Tertiary (regular) | X24: 0 | Y24: 0 | Z24: 0 | AA24: =Z24*Y24 -> 0 | AB24: 0 | AC24: 0 | AD24: =Y24-AB24-AC24 -> 0 | AE24: 0 | AF24: =AE24 -> 0 | AG24: =Z24-AE24-AF24 -> 0 | AH24: =AG24*AD24 -> 0 | AI24: 0 | AJ24: 0 | AK24: =ROUND(AI24*(1+AJ24),0) -> 0 | AL24: =AG24*AD24*AK24 -> 0 | AM24: =IF(AA24=0,0,AL24/AA24) -> 0 | AO24: 0 | AP24: 0 | AQ24: 0 | AR24: =AO24*AG24 -> 0 | AS24: =AP24*AD24 -> 0 | AT24: =ROUND(AQ24*AK24,0) -> 0 | AU24: =AL24*AP24*AQ24 -> 0
B25: Land on local roads, subtotal | F25: =SUM(F23:F24) -> 0 | H25: =SUM(H23:H24) -> 0 | I25: =SUM(I23:I24) -> 0 | J25: =SUM(J23:J24) -> 0 | K25: =SUM(K23:K24) -> 0 | L25: =SUM(L23:L24) -> 0 | M25: =SUM(M23:M24) -> 0 | N25: =SUM(N23:N24) -> 0 | O25: =SUM(O23:O24) -> 0 | ... Q25: =SUM(Q23:Q24) -> 0 | R25: =Q25/Q37 -> #DIV/0! | U25: w/path | V25: cluster w | W25: int. path w | X25: =SUM(C47:C48)*2 -> 0 | Y25: =Y24 -> 0 | Z25: =Z24 -> 0 | AA25: =AA24 -> 0 | AB25: =AB24 -> 0 | AC25: =AC24 -> 0 | AD25: =AD24 -> 0 | AE25: =AE24 -> 0 | AF25: =AF24 -> 0 | ... AH25: =AH24 -> 0 | AK25: =AK24 -> 0 | AL25: =AL24 -> 0 | AM25: =IF(AA25=0,0,AL25/AA25) -> 0 | AO25: =AO24 -> 0 | AP25: =AP24 -> 0 | AQ25: =AQ24 -> 0 | AR25: =AO25*AG25 -> 0 | AS25: =AP25*AD25 -> 0 | AT25: =ROUND(AQ25*AK25,0) -> 0 | AU25: =AU24 -> 0
A26: Off-grid clusters | B26: on arteries | H26: 0 | I26: 0 | J26: 0 | K26: 0 | L26: 0 | M26: 0 | N26: =SUM(G26:M26) -> 0 | O26: 0 | P26: =SUM(N26:O26) -> 0 | Q26: =P26 -> 0 | R26: =Q26/Q37 -> #DIV/0! | T26: Off-grid clusters | U26: on arteries | V26: 0 | W26: 0 | X26: 0 | Y26: =(V26-W26)/2 -> 0 | Z26: 0 | AA26: =Z26*Y26 -> 0 | AB26: 0 | AC26: 0 | AD26: =Y26-AB26-AC26 -> 0 | AE26: 0 | AF26: =AE26 -> 0 | AG26: =Z26-2*AE26 -> 0 | AH26: =AG26*AD26 -> 0 | AI26: 0 | AJ26: 0 | AK26: =ROUND(AI26*(1+AJ26),0) -> 0 | AL26: =AG26*AD26*AK26 -> 0 | AM26: =IF(AA26=0,0,AL26/AA26) -> 0 | AO26: 0 | AP26: 0 | AQ26: 0 | AR26: =AO26*AG26 -> 0 | AS26: =AP26*AD26 -> 0 | AT26: =ROUND(AQ26*AK26,0) -> 0 | AU26: =AL26*AP26*AQ26 -> 0
A27: Off-grid clusters | B27: on secondaries | H27: 0 | I27: 0 | J27: 0 | K27: 0 | L27: 0 | M27: 0 | N27: =SUM(G27:M27) -> 0 | O27: 0 | P27: =SUM(N27:O27) -> 0 | Q27: =P27 -> 0 | R27: =Q27/Q37 -> #DIV/0! | T27: Off-grid clusters | U27: on secondaries | V27: =V28 -> 0 | W27: =W28 -> 0 | X27: 0 | Y27: =(V27-W27)/2 -> 0 | Z27: 0 | AA27: =Z27*Y27 -> 0 | AB27: 0 | AC27: 0 | AD27: =Y27-AB27-AC27 -> 0 | AE27: 0 | AF27: =AE27 -> 0 | AG27: =Z27-2*AE27 -> 0 | AH27: =AG27*AD27 -> 0 | AI27: =AI28 -> 0 | AJ27: 0 | AK27: =ROUND(AI27*(1+AJ27),0) -> 0 | AL27: =AG27*AD27*AK27 -> 0 | AM27: =IF(AA27=0,0,AL27/AA27) -> 0 | AO27: =AO28 -> 0 | AP27: =AP28 -> 0 | AQ27: =AQ28 -> 0 | AR27: =AO27*AG27 -> 0 | AS27: =AP27*AD27 -> 0 | AT27: =ROUND(AQ27*AK27,0) -> 0 | AU27: =AL27*AP27*AQ27 -> 0
A28: Simple off-grid clusters | B28: on locals | H28: 0 | I28: 0 | J28: 0 | K28: 0 | L28: 0 | M28: 0 | N28: =SUM(G28:M28) -> 0 | O28: 0 | P28: =SUM(N28:O28) -> 0 | Q28: =P28 -> 0 | R28: =Q28/Q37 -> #DIV/0! | T28: Simple off-grid clusters | U28: on locals | V28: 0 | W28: 0 | X28: 0 | Y28: =(V28-W28)/2 -> 0 | Z28: 0 | AA28: =Z28*Y28 -> 0 | AB28: 0 | AC28: 0 | AD28: =Y28-AB28-AC28 -> 0 | AE28: 0 | AF28: =AE28 -> 0 | AG28: =Z28-2*AE28 -> 0 | AH28: =AG28*AD28 -> 0 | AI28: 0 | AJ28: 0 | AK28: =ROUND(AI28*(1+AJ28),0) -> 0 | AL28: =AG28*AD28*AK28 -> 0 | AM28: =IF(AA28=0,0,AL28/AA28) -> 0 | AO28: 0 | AP28: 0 | AQ28: 0 | AR28: =AO28*AG28 -> 0 | AS28: =AP28*AD28 -> 0 | AT28: =ROUND(AQ28*AK28,0) -> 0 | AU28: =AL28*AP28*AQ28 -> 0
A29: 2-level off-grid clusters, 1st level | B29: on locals | H29: 0 | I29: 0 | J29: 0 | K29: 0 | L29: 0 | M29: 0 | N29: =SUM(G29:M29) -> 0 | O29: 0 | P29: =SUM(N29:O29) -> 0 | Q29: =P29 -> 0 | R29: =Q29/Q37 -> #DIV/0! | T29: 2-level off-grid clusters, 1st level | U29: on locals | V29: =V28 -> 0 | W29: =W28 -> 0 | X29: 0 | Y29: =Y28 -> 0 | Z29: =Z28 -> 0 | AA29: =AA28 -> 0 | AB29: =AB28 -> 0 | AC29: =AC28 -> 0 | AD29: =AD28 -> 0 | AE29: =AE28 -> 0 | AF29: =AF28 -> 0 | ... AH29: =AH28 -> 0 | AK29: =AK28 -> 0 | AL29: =AL28 -> 0 | AM29: =IF(AA29=0,0,AL29/AA29) -> 0 | AO29: =AO28 -> 0 | AP29: =AP28 -> 0 | AQ29: =AQ28 -> 0 | AR29: =AO29*AG29 -> 0 | AS29: =AP29*AD29 -> 0 | AT29: =ROUND(AQ29*AK29,0) -> 0 | AU29: =AU28 -> 0
A30: 2nd level | B30: from 1st | H30: 0 | I30: 0 | J30: 0 | K30: 0 | L30: 0 | M30: 0 | N30: =SUM(G30:M30) -> 0 | O30: 0 | P30: =SUM(N30:O30) -> 0 | Q30: =P30 -> 0 | R30: =Q30/Q37 -> #DIV/0! | T30: 2nd level | U30: from 1st | V30: =V28 -> 0 | W30: 0 | X30: 0 | Y30: =(V30-W30)/2 -> 0 | Z30: 0 | AA30: =Z30*Y30 -> 0 | AB30: =AB28 -> 0 | AC30: =AC28 -> 0 | AD30: =Y30-AB30-AC30 -> 0 | AE30: =AE28 -> 0 | AF30: =AE30 -> 0 | AG30: =Z30-2*AE30 -> 0 | AH30: =AG30*AD30 -> 0 | AI30: =AI28 -> 0 | AJ30: 0 | AK30: =ROUND(AI30*(1+AJ30),0) -> 0 | AL30: =AG30*AD30*AK30 -> 0 | AM30: =IF(AA30=0,0,AL30/AA30) -> 0 | AO30: 0 | AP30: 0 | AQ30: 0 | AR30: =AO30*AG30 -> 0 | AS30: =AP30*AD30 -> 0 | AT30: =ROUND(AQ30*AK30,0) -> 0 | AU30: =AL30*AP30*AQ30 -> 0
B31: Off-grid partitions, subtotal | H31: =SUM(H26:H30) -> 0 | I31: =SUM(I26:I30) -> 0 | J31: =SUM(J26:J30) -> 0 | K31: =SUM(K26:K30) -> 0 | L31: =SUM(L26:L30) -> 0 | M31: =SUM(M26:M30) -> 0 | N31: =SUM(N26:N30) -> 0 | O31: =SUM(O26:O30) -> 0 | ... Q31: =SUM(Q26:Q30) -> 0 | R31: =Q31/Q37 -> #DIV/0!
B32: Land in urban blocks, subtotal | C32: 0 | D32: 0 | E32: 0 | F32: 0 | G32: 0 | H32: =H31+H25+H22+H18 -> 0 | I32: =I31+I25+I22+I18 -> 0 | J32: =J31+J25+J22+J18 -> 0 | K32: =K31+K25+K22+K18 -> 0 | L32: =L31+L25+L22+L18 -> 0 | M32: =M31+M25+M22+M18 -> 0 | N32: =N31+N25+N22+N18 -> 0 | O32: =O31+O25+O22+O18 -> 0 | ... Q32: =Q31+Q25+Q22+Q18 -> 0 | R32: =Q32/Q37 -> #DIV/0!
B33: Arteries (main roads) | C33: 0 | D33: 0 | E33: 0 | F33: =SUM(C33:E33) -> 0 | G33: 0 | N33: =G33 -> 0 | P33: =SUM(N33:O33) -> 0 | Q33: =P33+F33 -> 0 | R33: =Q33/Q37 -> #DIV/0!
B34: Secondaries (distributor roads) | C34: 0 | D34: 0 | E34: 0 | F34: =SUM(C34:E34) -> 0 | G34: 0 | N34: =G34 -> 0 | P34: =SUM(N34:O34) -> 0 | Q34: =P34+F34 -> 0 | R34: =Q34/Q37 -> #DIV/0!
B35: Tertiaries (access and local roads) | C35: 0 | D35: 0 | E35: 0 | F35: =SUM(C35:E35) -> 0 | G35: 0 | N35: =G35 -> 0 | P35: =SUM(N35:O35) -> 0 | Q35: =P35+F35 -> 0 | R35: =Q35/Q37 -> #DIV/0!
B36: Land in public streets, subtotal | C36: =SUM(C33:C35) -> 0 | D36: =SUM(D33:D35) -> 0 | E36: =SUM(E33:E35) -> 0 | F36: =SUM(F33:F35) -> 0 | G36: =SUM(G33:G35) -> 0 | N36: =SUM(N33:N35) -> 0 | P36: =SUM(P33:P35) -> 0 | Q36: =SUM(Q33:Q35) -> 0 | R36: =Q36/Q37 -> #DIV/0!
B37: Totals | C37: =C36+C13 -> 0 | D37: =D36+D13 -> 0 | E37: =E36+E13 -> 0 | F37: =F36+F13 -> 0 | G37: =G32 -> 0 | H37: =H32 -> 0 | I37: =I32 -> 0 | J37: =J32 -> 0 | K37: =K32 -> 0 | L37: =L32 -> 0 | M37: =M32 -> 0 | N37: =N36+N32 -> 0 | O37: =O36+O32 -> 0 | P37: =P36+P32 -> 0 | Q37: =Q36+Q32+Q13 -> 0 | R37: =Q37/Q37 -> #DIV/0!
B38: Distribution (share of total) | C38: =C37/Q37 -> #DIV/0! | D38: =D37/Q37 -> #DIV/0! | E38: =E37/Q37 -> #DIV/0! | F38: =F37/Q37 -> #DIV/0! | G38: =G37/Q37 -> #DIV/0! | H38: =H37/Q37 -> #DIV/0! | I38: =I37/Q37 -> #DIV/0! | J38: =J37/Q37 -> #DIV/0! | K38: =K37/Q37 -> #DIV/0! | L38: =L37/Q37 -> #DIV/0! | M38: =M37/Q37 -> #DIV/0! | N38: =N37/Q37 -> #DIV/0! | O38: =O37/Q37 -> #DIV/0! | P38: =P37/Q37 -> #DIV/0! | Q38: =Q37/Q37 -> #DIV/0!
A43: Clusters
B44: Area | C44: Connections from public network | D44: Semi-private / collective infra | G44: access areas on on-grid partitions | H44: semi-private collective circulation | I44: semi-private collective green space
A45: Off-grid clusters | B45: on arteries | C45: 0 | D45: 0 | G45: 0 | H45: 0 | I45: 0
A46: Off-grid clusters | B46: on secondaries | C46: 0 | D46: 0 | G46: 0 | H46: 0 | I46: 0
A47: Simple off-grid clusters | B47: on locals | C47: 0 | D47: 0 | G47: 0 | H47: 0 | I47: 0
A48: 2-level off-grid clusters, 1st level | B48: on locals | C48: 0 | D48: 0 | G48: 0 | H48: 0 | I48: 0
A49: 2nd level | B49: from 1st | C49: 0 | D49: 0 | H49: 0 | I49: 0
A51: Prior Landownership | B51: dummy values
A52: Land areas | B52: public roads, existing | C52: environmental reservation | D52: social reservation | E52: agricultural land | F52: urban land | G52: subtotals | H52: %shares
A53: existing public roads | B53: =H53*Q37/10000 -> 0 | G53: =B53 -> 0 | H53: 0.0625
A54: Landowner 1 | C54: 0 | D54: 0 | E54: =H54*Q37/10000 -> 0 | F54: 0 | G54: =SUM(C54:F54) -> 0 | H54: 0.076875
A55: Landowner 2 | C55: 0 | D55: 0 | E55: =H55*Q37/10000 -> 0 | F55: 0 | G55: =SUM(C55:F55) -> 0 | H55: 0.225
A56: Landowner 3 | C56: 0 | D56: 0 | E56: =H56*Q37/10000 -> 0 | F56: 0 | G56: =SUM(C56:F56) -> 0 | H56: 0.03625
A57: Landowner 4 | C57: 0 | D57: 0 | E57: =H57*Q37/10000 -> 0 | F57: 0 | G57: =SUM(C57:F57) -> 0 | H57: 0.389375
A58: Landowner 5 | C58: 0 | D58: 0 | E58: =H58*Q37/10000 -> 0 | F58: 0 | G58: =SUM(C58:F58) -> 0 | H58: 0.125
A59: Landowner 6 | C59: 0 | D59: 0 | E59: =H59*Q37/10000 -> 0 | F59: 0 | G59: =SUM(C59:F59) -> 0 | H59: =1-SUM(H53:H58) -> 0.085
A60: subtotals | B60: =SUM(B53:B59) -> 0 | C60: =SUM(C53:C59) -> 0 | D60: =SUM(D53:D59) -> 0 | E60: =SUM(E53:E59) -> 0 | F60: =SUM(F53:F59) -> 0 | G60: =SUM(G53:G59) -> 0 | H60: =SUM(H53:H59) -> 1
A62: precision check, comparing areas
A63: area | B63: area size | C63: deviation
A64: site, defined by external boundary | B64: 0
A65: individual land owners' contribution | B65: =G60*10000 -> 0 | C65: =(B65-B64)/B65 -> #DIV/0!
A66: serviced lands (project) | B66: =Q37 -> 0 | C66: =(B66-B64)/B66 -> #DIV/0!
A68: Notes
A69: All quantities from the spatial model
A70: All quantities from the spatial model - NOT YET EXISTING/MODELLED

Sheet 1db
A1: Site mobilization proforma
A3: Trunk infrastructure items | B3: Base-year amount
A4: Off-site costs | B4: =-'1off-site'!G6 -> 0
A5: Off-site revenues | B5: ='1off-site'!G12 -> 0
A6: Off-site surplus (loss) | B6: ='1off-site'!G14 -> 0 | D6: formatting in case of surplus
A7: Off-site costs, project-borne | B7: ='1off-site'!G16 -> 0 | D7: =D6 -> formatting in case of surplus
A8: Site mobilization items | B8: Base-year amount
A9: ='1site'!B10 -> 0 | B9: =-'1site'!B30 -> 0
A10: ='1site'!C10 -> 0 | B10: =-'1site'!C30 -> 0
A11: ='1site'!D10 -> 0 | B11: =-'1site'!D30 -> 0
A12: ='1site'!E10 -> 0 | B12: =-'1site'!E30 -> 0
A13: ='1site'!F10 -> 0 | B13: =-'1site'!F30 -> 0
A14: Land costs, subtotal | B14: =-'1site'!G30 -> 0
A16: Site-related costs, total | B16: =B14+B7 -> 0 | D16: =D15 -> 0

Sheet 2db
A1: Neighborhood scale proforma
A3: Item | B3: Base-year amount | C3: quantity
A4: Land and site-related costs | B4: =-'2neighborhood'!L6 -> 0 | C4: ='2neighborhood'!D4 -> 0
A5: Arteries (main roads) | B5: =-'2neighborhood'!L11 -> 0 | C5: ='2neighborhood'!D8 -> 0
A6: Secondaries (distributor roads) | B6: =-'2neighborhood'!L15 -> 0 | C6: ='2neighborhood'!D12 -> 0
A7: Tertiaries (access and local roads) | B7: =-'2neighborhood'!L19 -> 0 | C7: ='2neighborhood'!D16 -> 0
A8: Public Spaces | B8: =-'2neighborhood'!L29 -> 0 | C8: =SUM('2neighborhood'!D26:D27)/10000 -> 0
A9: Costs, total | B9: =SUM(B4:B8) -> 0 | C9: =C4 -> 0
A10: Revenues from private lands on arteries | B10: ='2neighborhood'!L56 -> 0 | C10: ='2neighborhood'!K56/10000 -> 0
A11: ...on secondaries | B11: ='2neighborhood'!L60 -> 0 | C11: ='2neighborhood'!K60/10000 -> 0
A12: ...on tertiaries | B12: ='2neighborhood'!L63 -> 0 | C12: ='2neighborhood'!K63/10000 -> 0
A13: ...in off-grid clusters | B13: ='2neighborhood'!L71 -> 0 | C13: ='2neighborhood'!K71/10000 -> 0
A14: Revenues from private lands | B14: =SUM(B10:B13) -> 0 | C14: ='2neighborhood'!K76/10000 -> 0
A15: Revenue from public uses | B15: ='2neighborhood'!J82 -> 0 | C15: =C8 -> 0
A16: Revenues, total | B16: =SUM(B14:B15) -> 0 | C16: =SUM(C14:C15) -> 0
A18: Project surplus (loss) | B18: =B9+B16 -> 0 | C18: =C4 -> 0 | E18: formatting in case of loss
A19: Financial efficiency (surplus/costs) | B19: =-B18/B9 -> #DIV/0! | E19: formatting in case of loss
B22: differentiate social and private surplus?

Sheet 3db
A1: Off-grid Clusters Proforma
A3: Off-grid cluster category | B3: on arteries | C3: on secondaries | D3: on locals, single | E3: on locals, multiple | F3: total
A4: Number of clusters | B4: ='3cluster_artery'!B3 -> 0 | C4: ='3cluster_secondary'!B3 -> 0 | D4: ='3lcluster_local'!B3 -> 0 | E4: ='3lcluster_local_2level'!B3 -> 0 | F4: =SUM(B4:E4) -> 0
A5: Costs and revenues, all clusters | B5: Base-year amount | C5: Base-year amount | D5: Base-year amount | E5: Base-year amount | F5: Base-year amount
A6: Serviced land, all clusters | B6: =-'3cluster_artery'!I10 -> 0 | C6: =-'3cluster_secondary'!I10 -> 0 | D6: =-'3lcluster_local'!I10 -> 0 | E6: =-('3lcluster_local_2level'!I10+'3lcluster_local_2level'!I22) -> 0 | F6: =SUM(B6:E6) -> 0
A7: Semi-private (collective) space, all clusters | B7: =-'3cluster_artery'!I16 -> 0 | C7: =-'3cluster_secondary'!I16 -> 0 | D7: =-'3lcluster_local'!I16 -> 0 | E7: =-('3lcluster_local_2level'!I16+'3lcluster_local_2level'!I28) -> 0 | F7: =SUM(B7:E7) -> 0
A8: Total costs, all clusters | B8: =-'3cluster_artery'!I17 -> 0 | C8: =-'3cluster_secondary'!I17 -> 0 | D8: =-'3lcluster_local'!I17 -> 0 | E8: =-'3lcluster_local_2level'!I17-'3lcluster_local_2level'!I29 -> 0 | F8: =SUM(B8:E8) -> 0
A9: Revenues from private lots, all clusters | B9: ='3cluster_artery'!I23 -> 0 | C9: ='3cluster_secondary'!I23 -> 0 | D9: ='3lcluster_local'!I23 -> 0 | E9: ='3lcluster_local_2level'!I44+'3lcluster_local_2level'!I37 -> 0 | F9: =SUM(B9:E9) -> 0
A10: Other revenues, all clusters | B10: =SUM('3cluster_artery'!I24:I25) -> 0 | C10: =SUM('3cluster_secondary'!I24:I25) -> 0 | D10: =SUM('3lcluster_local'!I24:I25) -> 0 | E10: =SUM('3lcluster_local_2level'!I38:I39)+SUM('3lcluster_local_2level'!I45:I46) -> 0 | F10: =SUM(B10:E10) -> 0
A11: Total revenue, all clusters | B11: ='3cluster_artery'!I26 -> 0 | C11: ='3cluster_secondary'!I26 -> 0 | D11: ='3lcluster_local'!I26 -> 0 | E11: ='3lcluster_local_2level'!I47 -> 0 | F11: =SUM(B11:E11) -> 0
A13: Total surplus (loss), all clusters | B13: =B11+B8 -> 0 | C13: =C11+C8 -> 0 | D13: =D11+D8 -> 0 | E13: =E11+E8 -> 0 | F13: =F11+F8 -> 0 | H13: formatting in case of loss
A14: Financial efficiency (surplus/costs) | B14: =IF(B8=0,0,-B13/B8) -> 0 | C14: =IF(C8=0,0,-C13/C8) -> 0 | D14: =IF(D8=0,0,-D13/D8) -> 0 | E14: =IF(E8=0,0,-E13/E8) -> 0 | F14: =IF(F8=0,0,-F13/F8) -> 0 | H14: formatting in case of loss
A16: Off-grid cluster category | B16: on arteries | C16: on secondaries | D16: on locals, single | E16: on locals, multiple | F16: average
A17: Number of clusters | B17: =B4 -> 0 | C17: =C4 -> 0 | D17: =D4 -> 0 | E17: =E4 -> 0 | F17: =F4 -> 0
A18: Costs and revenues, individual cluster | B18: Base-year amount | C18: Base-year amount | D18: Base-year amount | E18: Base-year amount | F18: Base-year amount
A19: Serviced land | B19: =IF(B4=0,0,'3db'!B6/B4) -> 0 | C19: =IF(C4=0,0,'3db'!C6/C4) -> 0 | D19: =IF(D4=0,0,'3db'!D6/D4) -> 0 | E19: =IF(E4=0,0,'3db'!E6/E4) -> 0 | F19: =IF(F4=0,0,'3db'!F6/F4) -> 0
A20: Semi-private (collective) space | B20: =IF(B4=0,0,'3db'!B7/B4) -> 0 | C20: =IF(C4=0,0,'3db'!C7/C4) -> 0 | D20: =IF(D4=0,0,'3db'!D7/D4) -> 0 | E20: =IF(E4=0,0,'3db'!E7/E4) -> 0 | F20: =IF(F4=0,0,'3db'!F7/F4) -> 0
A21: Costs, total | B21: =IF(B4=0,0,'3db'!B8/B4) -> 0 | C21: =IF(C4=0,0,'3db'!C8/C4) -> 0 | D21: =IF(D4=0,0,'3db'!D8/D4) -> 0 | E21: =IF(E4=0,0,'3db'!E8/E4) -> 0 | F21: =IF(F4=0,0,'3db'!F8/F4) -> 0
A22: Revenues from private lots | B22: =IF(B4=0,0,'3db'!B9/B4) -> 0 | C22: =IF(C4=0,0,'3db'!C9/C4) -> 0 | D22: =IF(D4=0,0,'3db'!D9/D4) -> 0 | E22: =IF(E4=0,0,'3db'!E9/E4) -> 0 | F22: =IF(F4=0,0,'3db'!F9/F4) -> 0
A23: Other revenues | B23: =IF(B4=0,0,'3db'!B10/B4) -> 0 | C23: =IF(C4=0,0,'3db'!C10/C4) -> 0 | D23: =IF(D4=0,0,'3db'!D10/D4) -> 0 | E23: =IF(E4=0,0,'3db'!E10/E4) -> 0 | F23: =IF(F4=0,0,'3db'!F10/F4) -> 0
A24: Revenues, total | B24: =IF(B4=0,0,'3db'!B11/B4) -> 0 | C24: =IF(C4=0,0,'3db'!C11/C4) -> 0 | D24: =IF(D4=0,0,'3db'!D11/D4) -> 0 | E24: =IF(E4=0,0,'3db'!E11/E4) -> 0 | F24: =IF(F4=0,0,'3db'!F11/F4) -> 0
A26: Project surplus (loss) | B26: =IF(B4=0,0,'3db'!B13/B4) -> 0 | C26: =IF(C4=0,0,'3db'!C13/C4) -> 0 | D26: =IF(D4=0,0,'3db'!D13/D4) -> 0 | E26: =IF(E4=0,0,'3db'!E13/E4) -> 0 | F26: =IF(F4=0,0,'3db'!F13/F4) -> 0 | H26: formatting in case of loss
A27: Financial efficiency (surplus/costs) | B27: =IF(B21=0,0,-B26/B21) -> 0 | C27: =IF(C21=0,0,-C26/C21) -> 0 | D27: =IF(D21=0,0,-D26/D21) -> 0 | E27: =IF(E21=0,0,-E26/E21) -> 0 | F27: =IF(F21=0,0,-F26/F21) -> 0 | H27: formatting in case of loss

Sheet 4db
A1: Starter Buildings Proforma
A2: Location, by color code | B2: Artery x artery (corner) | C2: Artery x secondary (corner) | D2: Artery x tertiary (corner) | E2: Artery (regular) | F2: Artery (cluster access) | G2: Off-grid cluster (on arteries) | H2: Secondary x secondary (corner) | I2: Secondary x tertiary (corner) | J2: Secondary (regular) | K2: Secondary (cluster access) | L2: Off-grid cluster (secondaries) | M2: Tertiary x tertiary (corner) | N2: Tertiary (regular) | O2: Tertiary (cluster access) | P2: Off-grid cluster (simple) | Q2: 2-level cluster (1st level) | R2: 2-level cluster (2nd level) | S2: Total
A3: Serviced lots, withOUT construction | B3: =IF('4buildings'!B29=0,'4buildings'!B10,0) -> 0 | C3: =IF('4buildings'!C29=0,'4buildings'!C10,0) -> 0 | D3: =IF('4buildings'!D29=0,'4buildings'!D10,0) -> 0 | E3: =IF('4buildings'!E29=0,'4buildings'!E10,0) -> 0 | F3: =IF('4buildings'!F29=0,'4buildings'!F10,0) -> 0 | G3: =IF('4buildings'!G29=0,'4buildings'!G10,0) -> 0 | H3: =IF('4buildings'!H29=0,'4buildings'!H10,0) -> 0 | I3: =IF('4buildings'!I29=0,'4buildings'!I10,0) -> 0 | ... R3: =IF('4buildings'!R29=0,'4buildings'!R10,0) -> 0 | S3: =SUM(B3:R3) -> 0
A4: Costs and revenues | B4: Base-year amount | C4: Base-year amount | D4: Base-year amount | E4: Base-year amount | F4: Base-year amount | G4: Base-year amount | H4: Base-year amount | I4: Base-year amount | J4: Base-year amount | K4: Base-year amount | L4: Base-year amount | M4: Base-year amount | N4: Base-year amount | O4: Base-year amount | P4: Base-year amount | Q4: Base-year amount | R4: Base-year amount | S4: Base-year amount
A5: Serviced lots, on arteries | B5: =B3*'4buildings'!B35 -> 0 | C5: =C3*'4buildings'!C35 -> 0 | D5: =D3*'4buildings'!D35 -> 0 | E5: =E3*'4buildings'!E35 -> 0 | F5: =F3*'4buildings'!F35 -> 0 | S5: =SUM(B5:R5) -> 0
A6: …in off-grid clusters, from arteries | G6: =G3*'4buildings'!G35 -> 0 | S6: =SUM(B6:R6) -> 0
A7: Serviced lots, on secondaries | H7: =H3*'4buildings'!H35 -> 0 | I7: =I3*'4buildings'!I35 -> 0 | J7: =J3*'4buildings'!J35 -> 0 | K7: =K3*'4buildings'!K35 -> 0 | S7: =SUM(B7:R7) -> 0
A8: …in off-grid clusters, from secondaries | L8: =L3*'4buildings'!L35 -> 0 | S8: =SUM(B8:R8) -> 0
A9: Serviced lots, on locals | M9: =M3*'4buildings'!M35 -> 0 | N9: =N3*'4buildings'!N35 -> 0 | O9: =O3*'4buildings'!O35 -> 0 | S9: =SUM(B9:R9) -> 0
A10: …in off-grid clusters, from locals | P10: =P3*'4buildings'!P35 -> 0 | Q10: =Q3*'4buildings'!Q35 -> 0 | R10: =R3*'4buildings'!R35 -> 0 | S10: =SUM(B10:R10) -> 0
A11: Sales of serviced lots, subtotal | B11: =B5 -> 0 | C11: =C5 -> 0 | D11: =D5 -> 0 | E11: =E5 -> 0 | F11: =F5 -> 0 | G11: =G6 -> 0 | H11: =H7 -> 0 | I11: =I7 -> 0 | J11: =J7 -> 0 | K11: =K7 -> 0 | L11: =L8 -> 0 | M11: =M9 -> 0 | N11: =N9 -> 0 | O11: =O9 -> 0 | P11: =P10 -> 0 | Q11: =Q10 -> 0 | R11: =R10 -> 0 | S11: =SUM(B11:R11) -> 0
A13: Serviced lots, WITH starters | B13: =IF('4buildings'!B29=0,0,'4buildings'!B10) -> 0 | C13: =IF('4buildings'!C29=0,0,'4buildings'!C10) -> 0 | D13: =IF('4buildings'!D29=0,0,'4buildings'!D10) -> 0 | E13: =IF('4buildings'!E29=0,0,'4buildings'!E10) -> 0 | F13: =IF('4buildings'!F29=0,0,'4buildings'!F10) -> 0 | G13: =IF('4buildings'!G29=0,0,'4buildings'!G10) -> 0 | H13: =IF('4buildings'!H29=0,0,'4buildings'!H10) -> 0 | I13: =IF('4buildings'!I29=0,0,'4buildings'!I10) -> 0 | ... R13: =IF('4buildings'!R29=0,0,'4buildings'!R10) -> 0 | S13: =SUM(B13:R13) -> 0
A14: Costs and revenues | B14: Base-year amount | C14: Base-year amount | D14: Base-year amount | E14: Base-year amount | F14: Base-year amount | G14: Base-year amount | H14: Base-year amount | I14: Base-year amount | J14: Base-year amount | K14: Base-year amount | L14: Base-year amount | M14: Base-year amount | N14: Base-year amount | O14: Base-year amount | P14: Base-year amount | Q14: Base-year amount | R14: Base-year amount | S14: Base-year amount
A15: Serviced lot | B15: =-B13*'4buildings'!B17 -> 0 | C15: =-C13*'4buildings'!C17 -> 0 | D15: =-D13*'4buildings'!D17 -> 0 | E15: =-E13*'4buildings'!E17 -> 0 | F15: =-F13*'4buildings'!F17 -> 0 | G15: =-G13*'4buildings'!G17 -> 0 | H15: =-H13*'4buildings'!H17 -> 0 | I15: =-I13*'4buildings'!I17 -> 0 | ... R15: =-R13*'4buildings'!R17 -> 0 | S15: =SUM(B15:R15) -> 0
A16: Construction | B16: =-B13*'4buildings'!B29 -> 0 | C16: =-C13*'4buildings'!C29 -> 0 | D16: =-D13*'4buildings'!D29 -> 0 | E16: =-E13*'4buildings'!E29 -> 0 | F16: =-F13*'4buildings'!F29 -> 0 | G16: =-G13*'4buildings'!G29 -> 0 | H16: =-H13*'4buildings'!H29 -> 0 | I16: =-I13*'4buildings'!I29 -> 0 | ... R16: =-R13*'4buildings'!R29 -> 0 | S16: =SUM(B16:R16) -> 0
A17: Interest | B17: =B13*('4buildings'!B31-'4buildings'!B33) -> 0 | C17: =C13*('4buildings'!C31-'4buildings'!C33) -> 0 | D17: =D13*('4buildings'!D31-'4buildings'!D33) -> 0 | E17: =E13*('4buildings'!E31-'4buildings'!E33) -> 0 | F17: =F13*('4buildings'!F31-'4buildings'!F33) -> 0 | G17: =G13*('4buildings'!G31-'4buildings'!G33) -> 0 | H17: =H13*('4buildings'!H31-'4buildings'!H33) -> 0 | I17: =I13*('4buildings'!I31-'4buildings'!I33) -> 0 | ... R17: =R13*('4buildings'!R31-'4buildings'!R33) -> 0 | S17: =SUM(B17:R17) -> 0
A18: Costs, total | B18: =SUM(B15:B17) -> 0 | C18: =SUM(C15:C17) -> 0 | D18: =SUM(D15:D17) -> 0 | E18: =SUM(E15:E17) -> 0 | F18: =SUM(F15:F17) -> 0 | G18: =SUM(G15:G17) -> 0 | H18: =SUM(H15:H17) -> 0 | I18: =SUM(I15:I17) -> 0 | ... R18: =SUM(R15:R17) -> 0 | S18: =SUM(B18:R18) -> 0
A19: Revenues (sales), commercial floor area | B19: =B13*'4buildings'!B46 -> 0 | C19: =C13*'4buildings'!C46 -> 0 | D19: =D13*'4buildings'!D46 -> 0 | E19: =E13*'4buildings'!E46 -> 0 | F19: =F13*'4buildings'!F46 -> 0 | G19: =G13*'4buildings'!G46 -> 0 | H19: =H13*'4buildings'!H46 -> 0 | I19: =I13*'4buildings'!I46 -> 0 | ... R19: =R13*'4buildings'!R46 -> 0 | S19: =SUM(B19:R19) -> 0
A20: Revenues (sales), residential floor area | B20: =B13*'4buildings'!B48 -> 0 | C20: =C13*'4buildings'!C48 -> 0 | D20: =D13*'4buildings'!D48 -> 0 | E20: =E13*'4buildings'!E48 -> 0 | F20: =F13*'4buildings'!F48 -> 0 | G20: =G13*'4buildings'!G48 -> 0 | H20: =H13*'4buildings'!H48 -> 0 | I20: =I13*'4buildings'!I48 -> 0 | ... R20: =R13*'4buildings'!R48 -> 0 | S20: =SUM(B20:R20) -> 0
A21: Revenues, total | B21: =B13*'4buildings'!B35 -> 0 | C21: =C13*'4buildings'!C35 -> 0 | D21: =D13*'4buildings'!D35 -> 0 | E21: =E13*'4buildings'!E35 -> 0 | F21: =F13*'4buildings'!F35 -> 0 | G21: =G13*'4buildings'!G35 -> 0 | H21: =H13*'4buildings'!H35 -> 0 | I21: =I13*'4buildings'!I35 -> 0 | ... R21: =R13*'4buildings'!R35 -> 0 | S21: =SUM(B21:R21) -> 0
A22: Project surplus (loss), per lot | B22: =B21+B18 -> 0 | C22: =C21+C18 -> 0 | D22: =D21+D18 -> 0 | E22: =E21+E18 -> 0 | F22: =F21+F18 -> 0 | G22: =G21+G18 -> 0 | H22: =H21+H18 -> 0 | I22: =I21+I18 -> 0 | ... R22: =R21+R18 -> 0 | S22: =SUM(B22:R22) -> 0 | U22: formatting in case of loss
A23: Financial efficiency (surplus/costs) | B23: =IF(B18=0,0,-B22/B18) -> 0 | C23: =IF(C18=0,0,-C22/C18) -> 0 | D23: =IF(D18=0,0,-D22/D18) -> 0 | E23: =IF(E18=0,0,-E22/E18) -> 0 | F23: =IF(F18=0,0,-F22/F18) -> 0 | G23: =IF(G18=0,0,-G22/G18) -> 0 | H23: =IF(H18=0,0,-H22/H18) -> 0 | I23: =IF(I18=0,0,-I22/I18) -> 0 | ... S23: =IF(S18=0,0,-S22/S18) -> 0 | U23: formatting in case of loss
A25: ="@Daniel, in the standard dashboard view only show the last column with totals, please." -> @Daniel, in the standard dashboard view only show the last column with totals, please.

Sheet 5db
A1: Dwellings Proforma & Affordability
A3: Location, by color code | B3: Artery x artery (corner) | C3: Artery x secondary (corner) | D3: Artery x tertiary (corner) | E3: Artery (regular) | F3: Artery (cluster access) | G3: Off-grid cluster (on arteries) | H3: Secondary x secondary (corner) | I3: Secondary x tertiary (corner) | J3: Secondary (regular) | K3: Secondary (cluster access) | L3: Off-grid cluster (secondaries) | M3: Tertiary x tertiary (corner) | N3: Tertiary (regular) | O3: Tertiary (cluster access) | P3: Off-grid cluster (simple) | Q3: 2-level cluster (1st level) | R3: 2-level cluster (2nd level) | S3: Total OR min. to max.
A4: Serviced lots WITH starters | B4: =IF('4buildings'!B29=0,0,'4buildings'!B10) -> 0 | C4: =IF('4buildings'!C29=0,0,'4buildings'!C10) -> 0 | D4: =IF('4buildings'!D29=0,0,'4buildings'!D10) -> 0 | E4: =IF('4buildings'!E29=0,0,'4buildings'!E10) -> 0 | F4: =IF('4buildings'!F29=0,0,'4buildings'!F10) -> 0 | G4: =IF('4buildings'!G29=0,0,'4buildings'!G10) -> 0 | H4: =IF('4buildings'!H29=0,0,'4buildings'!H10) -> 0 | I4: =IF('4buildings'!I29=0,0,'4buildings'!I10) -> 0 | ... R4: =IF('4buildings'!R29=0,0,'4buildings'!R10) -> 0 | S4: =SUM(B4:R4) -> 0
A5: Starter units (incl. sublets), project-built | B5: =IF(B4=0,0,B4*'5dwellings'!B20) -> 0 | C5: =IF(C4=0,0,C4*'5dwellings'!C20) -> 0 | D5: =IF(D4=0,0,D4*'5dwellings'!D20) -> 0 | E5: =IF(E4=0,0,E4*'5dwellings'!E20) -> 0 | F5: =IF(F4=0,0,F4*'5dwellings'!F20) -> 0 | G5: =IF(G4=0,0,G4*'5dwellings'!G20) -> 0 | H5: =IF(H4=0,0,H4*'5dwellings'!H20) -> 0 | I5: =IF(I4=0,0,I4*'5dwellings'!I20) -> 0 | ... R5: =IF(R4=0,0,R4*'5dwellings'!R20) -> 0 | S5: =SUM(B5:R5) -> 0
A6: ='5finance'!A3 -> Starter type | B6: ='5finance'!B3 -> lot only | C6: ='5finance'!C3 -> lot only | D6: ='5finance'!D3 -> lot only | E6: ='5finance'!E3 -> mixed-use building | F6: ='5finance'!F3 -> mixed-use building | G6: ='5finance'!G3 -> lot only | H6: ='5finance'!H3 -> lot only | ... R6: ='5finance'!R3 -> roof
A7: ='5finance'!A4 -> starter dwelling main units (owned), average gross area | B7: ='5finance'!B4 -> 0 | C7: ='5finance'!C4 -> 0 | D7: ='5finance'!D4 -> 0 | E7: ='5finance'!E4 -> 0 | F7: ='5finance'!F4 -> 0 | G7: ='5finance'!G4 -> 0 | H7: ='5finance'!H4 -> 0 | ... R7: ='5finance'!R4 -> 0 | S7: =MIN(B27:R27) -> 0 | T7: to | U7: =ROUND(MAX(B7:R7),0) -> 0
A8: Costs | B8: Base-year amount | C8: Base-year amount | D8: Base-year amount | E8: Base-year amount | F8: Base-year amount | G8: Base-year amount | H8: Base-year amount | I8: Base-year amount | J8: Base-year amount | K8: Base-year amount | L8: Base-year amount | M8: Base-year amount | N8: Base-year amount | O8: Base-year amount | P8: Base-year amount | Q8: Base-year amount | R8: Base-year amount | S8: min | T8: to | U8: max
A9: ='5finance'!A5 -> Land cost, attributed to 1 main dwelling unit | B9: ='5finance'!B5 -> 0 | C9: ='5finance'!C5 -> 0 | D9: ='5finance'!D5 -> 0 | E9: ='5finance'!E5 -> 0 | F9: ='5finance'!F5 -> 0 | G9: ='5finance'!G5 -> 0 | H9: ='5finance'!H5 -> 0 | ... R9: ='5finance'!R5 -> 0 | S9: =MIN(B29:R29) -> 0 | T9: to | U9: =ROUND(MAX(B9:R9),0) -> 0
A10: ='5finance'!A6 -> Starter unit cost, attributed to 1 main dwelling unit | B10: ='5finance'!B6 -> 0 | C10: ='5finance'!C6 -> 0 | D10: ='5finance'!D6 -> 0 | E10: ='5finance'!E6 -> 0 | F10: ='5finance'!F6 -> 0 | G10: ='5finance'!G6 -> 0 | H10: ='5finance'!H6 -> 0 | ... R10: ='5finance'!R6 -> 0 | S10: =MIN(B30:R30) -> 0 | T10: to | U10: =ROUND(MAX(B10:R10),0) -> 0
A11: ='5finance'!A7 -> Additional household investment, before move in (if any) | B11: =IF(B7=0,0,'5finance'!B7) -> 0 | C11: =IF(C7=0,0,'5finance'!C7) -> 0 | D11: =IF(D7=0,0,'5finance'!D7) -> 0 | E11: =IF(E7=0,0,'5finance'!E7) -> 0 | F11: =IF(F7=0,0,'5finance'!F7) -> 0 | G11: =IF(G7=0,0,'5finance'!G7) -> 0 | H11: =IF(H7=0,0,'5finance'!H7) -> 0 | I11: =IF(I7=0,0,'5finance'!I7) -> 0 | ... R11: =IF(R7=0,0,'5finance'!R7) -> 0 | S11: =MIN(B31:R31) -> 0 | T11: to | U11: =ROUND(MAX(B11:R11),0) -> 0
A12: ='5finance'!A8 -> Total cost, to be financed | B12: ='5finance'!B8 -> 0 | C12: ='5finance'!C8 -> 0 | D12: ='5finance'!D8 -> 0 | E12: ='5finance'!E8 -> 0 | F12: ='5finance'!F8 -> 0 | G12: ='5finance'!G8 -> 0 | H12: ='5finance'!H8 -> 0 | ... R12: ='5finance'!R8 -> 0 | S12: =MIN(B32:R32) -> 0 | T12: to | U12: =ROUND(MAX(B12:R12),0) -> 0
A14: Required monthly payments | B14: Monthly payments | C14: Monthly payments | D14: Monthly payments | E14: Monthly payments | F14: Monthly payments | G14: Monthly payments | H14: Monthly payments | I14: Monthly payments | J14: Monthly payments | K14: Monthly payments | L14: Monthly payments | M14: Monthly payments | N14: Monthly payments | O14: Monthly payments | P14: Monthly payments | Q14: Monthly payments | R14: Monthly payments | S14: min | T14: to | U14: max
A15: Payments for land, if separate | B15: ='5finance'!B57 -> 0 | C15: ='5finance'!C57 -> 0 | D15: ='5finance'!D57 -> 0 | E15: ='5finance'!E57 -> 0 | F15: ='5finance'!F57 -> 0 | G15: ='5finance'!G57 -> 0 | H15: ='5finance'!H57 -> 0 | I15: ='5finance'!I57 -> 0 | ... R15: ='5finance'!R57 -> 0 | S15: =MIN(B35:R35) -> 0 | T15: to | U15: =ROUND(MAX(B15:R15),0) -> 0
A16: Payments for starter, if separate | B16: ='5finance'!B58 -> 0 | C16: ='5finance'!C58 -> 0 | D16: ='5finance'!D58 -> 0 | E16: ='5finance'!E58 -> 0 | F16: ='5finance'!F58 -> 0 | G16: ='5finance'!G58 -> 0 | H16: ='5finance'!H58 -> 0 | I16: ='5finance'!I58 -> 0 | ... R16: ='5finance'!R58 -> 0 | S16: =MIN(B36:R36) -> 0 | T16: to | U16: =ROUND(MAX(B16:R16),0) -> 0
A17: Payments, remaining | B17: ='5finance'!B59 -> 0 | C17: ='5finance'!C59 -> 0 | D17: ='5finance'!D59 -> 0 | E17: ='5finance'!E59 -> 0 | F17: ='5finance'!F59 -> 0 | G17: ='5finance'!G59 -> 0 | H17: ='5finance'!H59 -> 0 | I17: ='5finance'!I59 -> 0 | ... R17: ='5finance'!R59 -> 0 | S17: =MIN(B37:R37) -> 0 | T17: to | U17: =ROUND(MAX(B17:R17),0) -> 0
A18: Payments, total | B18: =SUM(B15:B16) -> 0 | C18: =SUM(C15:C16) -> 0 | D18: =SUM(D15:D16) -> 0 | E18: =SUM(E15:E16) -> 0 | F18: =SUM(F15:F16) -> 0 | G18: =SUM(G15:G16) -> 0 | H18: =SUM(H15:H16) -> 0 | I18: =SUM(I15:I16) -> 0 | ... L18: =SUM(L15:L16) -> 0 | M18: ='5finance'!M60 -> 0 | N18: ='5finance'!N60 -> 0 | O18: ='5finance'!O60 -> 0 | P18: ='5finance'!P60 -> 0 | Q18: ='5finance'!Q60 -> 0 | R18: ='5finance'!R60 -> 0 | S18: =MIN(B38:R38) -> 0 | T18: to | U18: =ROUND(MAX(B18:R18),0) -> 0
A20: Affordability of ownership | B20: ='5affordability'!H21 -> 0 | C20: ='5affordability'!I21 -> 0 | D20: ='5affordability'!J21 -> 0 | E20: ='5affordability'!K21 -> 0 | F20: ='5affordability'!L21 -> 0 | G20: ='5affordability'!M21 -> 0 | H20: ='5affordability'!N21 -> 0 | I20: ='5affordability'!O21 -> 0 | ... S20: ='5affordability'!Y21 -> 0
A21: Affordability of rental sublets | B21: ='5affordability'!H38 -> 0 | C21: ='5affordability'!I38 -> 0 | D21: ='5affordability'!J38 -> 0 | E21: ='5affordability'!K38 -> 0 | F21: ='5affordability'!L38 -> 0 | G21: ='5affordability'!M38 -> 0 | H21: ='5affordability'!N38 -> 0 | I21: ='5affordability'!O38 -> 0 | ... S21: ='5affordability'!Y38 -> 0
A23: ="@Daniel, in the standard dashboard view only show the last column with totals. Beyond that, could we construct a dropdown menu, with the column headers, in order to display different columns?" -> @Daniel, in the standard dashboard view only show the last column with totals. Beyond that, could we construct a dropdown menu, with the column headers, in order to display different columns?
A24: ="@Daniel, if the CONCATE formula in the final column does not work for Lucky Sheets, this can be hardcoded for RUE?" -> @Daniel, if the CONCATE formula in the final column does not work for Lucky Sheets, this can be hardcoded for RUE?
A26: Workaround area for minimum calculation, excluding cells, of which the value is zero…
A27: ='5finance'!A30 -> Downpayment, share | B27: =IF(B7=0,U7,B7) -> 0 | C27: =IF(C7=0,U7,C7) -> 0 | D27: =IF(D7=0,U7,D7) -> 0 | E27: =IF(E7=0,U7,E7) -> 0 | F27: =IF(F7=0,U7,F7) -> 0 | G27: =IF(G7=0,U7,G7) -> 0 | H27: =IF(H7=0,U7,H7) -> 0 | I27: =IF(I7=0,U7,I7) -> 0 | J27: =IF(J7=0,U7,J7) -> 0 | K27: =IF(K7=0,U7,K7) -> 0 | L27: =IF(L7=0,U7,L7) -> 0 | M27: =IF(M7=0,U7,M7) -> 0 | N27: =IF(N7=0,U7,N7) -> 0 | O27: =IF(O7=0,U7,O7) -> 0 | P27: =IF(P7=0,U7,P7) -> 0 | Q27: =IF(Q7=0,U7,Q7) -> 0 | R27: =IF(R7=0,U7,R7) -> 0
A28: Costs and revenues
A29: ='5finance'!A31 -> …, amount | B29: =IF(B9=0,U9,B9) -> 0 | C29: =IF(C9=0,U9,C9) -> 0 | D29: =IF(D9=0,U9,D9) -> 0 | E29: =IF(E9=0,U9,E9) -> 0 | F29: =IF(F9=0,U9,F9) -> 0 | G29: =IF(G9=0,U9,G9) -> 0 | H29: =IF(H9=0,U9,H9) -> 0 | I29: =IF(I9=0,U9,I9) -> 0 | J29: =IF(J9=0,U9,J9) -> 0 | K29: =IF(K9=0,U9,K9) -> 0 | L29: =IF(L9=0,U9,L9) -> 0 | M29: =IF(M9=0,U9,M9) -> 0 | N29: =IF(N9=0,U9,N9) -> 0 | O29: =IF(O9=0,U9,O9) -> 0 | P29: =IF(P9=0,U9,P9) -> 0 | Q29: =IF(Q9=0,U9,Q9) -> 0 | R29: =IF(R9=0,U9,R9) -> 0
A30: ='5finance'!A32 -> Downpayment/cash subsidy | B30: =IF(B10=0,U10,B10) -> 0 | C30: =IF(C10=0,U10,C10) -> 0 | D30: =IF(D10=0,U10,D10) -> 0 | E30: =IF(E10=0,U10,E10) -> 0 | F30: =IF(F10=0,U10,F10) -> 0 | G30: =IF(G10=0,U10,G10) -> 0 | H30: =IF(H10=0,U10,H10) -> 0 | I30: =IF(I10=0,U10,I10) -> 0 | J30: =IF(J10=0,U10,J10) -> 0 | K30: =IF(K10=0,U10,K10) -> 0 | L30: =IF(L10=0,U10,L10) -> 0 | M30: =IF(M10=0,U10,M10) -> 0 | N30: =IF(N10=0,U10,N10) -> 0 | O30: =IF(O10=0,U10,O10) -> 0 | P30: =IF(P10=0,U10,P10) -> 0 | Q30: =IF(Q10=0,U10,Q10) -> 0 | R30: =IF(R10=0,U10,R10) -> 0
A31: ='5finance'!A33 -> Amount to be financed | B31: =IF(B11=0,U11,B11) -> 0 | C31: =IF(C11=0,U11,C11) -> 0 | D31: =IF(D11=0,U11,D11) -> 0 | E31: =IF(E11=0,U11,E11) -> 0 | F31: =IF(F11=0,U11,F11) -> 0 | G31: =IF(G11=0,U11,G11) -> 0 | H31: =IF(H11=0,U11,H11) -> 0 | I31: =IF(I11=0,U11,I11) -> 0 | J31: =IF(J11=0,U11,J11) -> 0 | K31: =IF(K11=0,U11,K11) -> 0 | L31: =IF(L11=0,U11,L11) -> 0 | M31: =IF(M11=0,U11,M11) -> 0 | N31: =IF(N11=0,U11,N11) -> 0 | O31: =IF(O11=0,U11,O11) -> 0 | P31: =IF(P11=0,U11,P11) -> 0 | Q31: =IF(Q11=0,U11,Q11) -> 0 | R31: =IF(R11=0,U11,R11) -> 0
A32: ='5finance'!A34 -> Financing period, months | B32: =IF(B12=0,U12,B12) -> 0 | C32: =IF(C12=0,U12,C12) -> 0 | D32: =IF(D12=0,U12,D12) -> 0 | E32: =IF(E12=0,U12,E12) -> 0 | F32: =IF(F12=0,U12,F12) -> 0 | G32: =IF(G12=0,U12,G12) -> 0 | H32: =IF(H12=0,U12,H12) -> 0 | I32: =IF(I12=0,U12,I12) -> 0 | J32: =IF(J12=0,U12,J12) -> 0 | K32: =IF(K12=0,U12,K12) -> 0 | L32: =IF(L12=0,U12,L12) -> 0 | M32: =IF(M12=0,U12,M12) -> 0 | N32: =IF(N12=0,U12,N12) -> 0 | O32: =IF(O12=0,U12,O12) -> 0 | P32: =IF(P12=0,U12,P12) -> 0 | Q32: =IF(Q12=0,U12,Q12) -> 0 | R32: =IF(R12=0,U12,R12) -> 0
A34: Monthly payments
A35: Payments for land, if separate | B35: =IF(B15=0,U15,B15) -> 0 | C35: =IF(C15=0,U15,C15) -> 0 | D35: =IF(D15=0,U15,D15) -> 0 | E35: =IF(E15=0,U15,E15) -> 0 | F35: =IF(F15=0,U15,F15) -> 0 | G35: =IF(G15=0,U15,G15) -> 0 | H35: =IF(H15=0,U15,H15) -> 0 | I35: =IF(I15=0,U15,I15) -> 0 | J35: =IF(J15=0,U15,J15) -> 0 | K35: =IF(K15=0,U15,K15) -> 0 | L35: =IF(L15=0,U15,L15) -> 0 | M35: =IF(M15=0,U15,M15) -> 0 | N35: =IF(N15=0,U15,N15) -> 0 | O35: =IF(O15=0,U15,O15) -> 0 | P35: =IF(P15=0,U15,P15) -> 0 | Q35: =IF(Q15=0,U15,Q15) -> 0 | R35: =IF(R15=0,U15,R15) -> 0
A36: Payments for starter, if separate | B36: =IF(B16=0,U16,B16) -> 0 | C36: =IF(C16=0,U16,C16) -> 0 | D36: =IF(D16=0,U16,D16) -> 0 | E36: =IF(E16=0,U16,E16) -> 0 | F36: =IF(F16=0,U16,F16) -> 0 | G36: =IF(G16=0,U16,G16) -> 0 | H36: =IF(H16=0,U16,H16) -> 0 | I36: =IF(I16=0,U16,I16) -> 0 | J36: =IF(J16=0,U16,J16) -> 0 | K36: =IF(K16=0,U16,K16) -> 0 | L36: =IF(L16=0,U16,L16) -> 0 | M36: =IF(M16=0,U16,M16) -> 0 | N36: =IF(N16=0,U16,N16) -> 0 | O36: =IF(O16=0,U16,O16) -> 0 | P36: =IF(P16=0,U16,P16) -> 0 | Q36: =IF(Q16=0,U16,Q16) -> 0 | R36: =IF(R16=0,U16,R16) -> 0
A37: Payments, remaining | B37: =IF(B17=0,U17,B17) -> 0 | C37: =IF(C17=0,U17,C17) -> 0 | D37: =IF(D17=0,U17,D17) -> 0 | E37: =IF(E17=0,U17,E17) -> 0 | F37: =IF(F17=0,U17,F17) -> 0 | G37: =IF(G17=0,U17,G17) -> 0 | H37: =IF(H17=0,U17,H17) -> 0 | I37: =IF(I17=0,U17,I17) -> 0 | J37: =IF(J17=0,U17,J17) -> 0 | K37: =IF(K17=0,U17,K17) -> 0 | L37: =IF(L17=0,U17,L17) -> 0 | M37: =IF(M17=0,U17,M17) -> 0 | N37: =IF(N17=0,U17,N17) -> 0 | O37: =IF(O17=0,U17,O17) -> 0 | P37: =IF(P17=0,U17,P17) -> 0 | Q37: =IF(Q17=0,U17,Q17) -> 0 | R37: =IF(R17=0,U17,R17) -> 0
A38: Payments, total | B38: =IF(B18=0,U18,B18) -> 0 | C38: =IF(C18=0,U18,C18) -> 0 | D38: =IF(D18=0,U18,D18) -> 0 | E38: =IF(E18=0,U18,E18) -> 0 | F38: =IF(F18=0,U18,F18) -> 0 | G38: =IF(G18=0,U18,G18) -> 0 | H38: =IF(H18=0,U18,H18) -> 0 | I38: =IF(I18=0,U18,I18) -> 0 | J38: =IF(J18=0,U18,J18) -> 0 | K38: =IF(K18=0,U18,K18) -> 0 | L38: =IF(L18=0,U18,L18) -> 0 | M38: =IF(M18=0,U18,M18) -> 0 | N38: =IF(N18=0,U18,N18) -> 0 | O38: =IF(O18=0,U18,O18) -> 0 | P38: =IF(P18=0,U18,P18) -> 0 | Q38: =IF(Q18=0,U18,Q18) -> 0 | R38: =IF(R18=0,U18,R18) -> 0

Sheet 6db
A1: Demographic forecast
A3: Initial dwellings | B3: ='6demographics'!S5 -> 0
A4: ...population | B4: ='6demographics'!S8 -> 0
A5: ...density, gross (all site) | B5: ='6demographics'!S9 -> 0
A6: ...density, net (private land) | B6: ='6demographics'!S10 -> 0
A8: Consolidated dwellings | B8: ='6demographics'!T6 -> 0
A9: ...population | B9: ='6demographics'!T8 -> 0
A10: ...density, gross (all site) | B10: ='6demographics'!T9 -> 0
A11: ...density, net (private land) | B11: ='6demographics'!T10 -> 0

Sheet spider
A1: Spider
A3: category | B3: key value | C3: objective (10 points) | D3: score (out of 10) | E3: Comment
A4: Sustainability:
A5: Land consumption | B5: =10000/'6db'!B10 -> #DIV/0! | C5: =10000/C8 -> 12.5 | D5: =C5/B5*10 -> #DIV/0! | E5: gross ratio for consolidated settlement
A6: Livability
A7: Density, initial | B7: ='6db'!B5 -> 0 | C7: 400 | D7: =B7/C7*10 -> 0 | E7: initial density for gross area
A8: Density, consolidated | B8: ='6db'!B10 -> 0 | C8: 800 | D8: =B8/C8*10 -> 0
A9: Public space (streets, open space & amenities), consolidated | B9: =Q!N38*B5 -> #DIV/0! | C9: =IF(B8>O30,P36,IF(B8>N30,O36,IF(B8>M30,N36,IF(B8>L30,M36,IF(B8>K30,L36,IF(B8>J30,K36,IF(B8>I30,J36,IF(B8>H30,I36,H36)))))))) -> 13 | D9: =B9/C9*10 -> #DIV/0!
A10: Public and community space | B10: =(Q!N37+SUM(Q!G45:I49))/Q!Q37*B5 -> #DIV/0! | C10: =C9 -> 13 | D10: =B10/C10*10 -> #DIV/0! | E10: streets, public open spaces, amenities; collective spaces in clusters per capita for consolidated (fully populated) settlement; for moving targets see below.
A11: Financial viability:
A12: Financial efficiency, neighborhood scale | B12: ='2db'!B19 -> #DIV/0! | C12: 0.15 | D12: =B12/C12*10 -> #DIV/0! | E12: (revenues-cost)/cost
A13: Financial efficiency, cluster scale | B13: ='3db'!F14 -> 0 | C13: 0.15 | D13: =B13/C13*10 -> 0 | E13: (revenues-cost)/cost
A14: Financial efficiency, building scale | B14: ='4db'!S23 -> 0 | C14: 0.15 | D14: =B14/C14*10 -> 0 | E14: (revenues-cost)/cost
A15: Inclusion:
A16: Affordability of ownership | B16: ='5affordability'!Y21 -> 0 | C16: 1 | D16: =B16/C16*10 -> 0 | E16: affordability of monthly payment (loan installment) and downpayment (first installment)
A17: Affordability of small-scale private rental | B17: ='5affordability'!Y38 -> 0 | C17: 1 | D17: =B17/C17*10 -> 0 | E17: affordability of monthly payment (rent) for sublets
A19: Fiscal cost
A20: Economic viability, IRR total project | B20: =#REF! -> #REF! | C20: 0.15 | D20: =B20/C20*10 -> #REF!
A21: Commercial viability, IRR private sector | B21: =#REF! -> #REF! | C21: 0.25 | D21: =B21/C21*10 -> #REF!
A23: Fiscal viability, public sector project NPV | B23: =#REF! -> #REF!
A24: less supply-side in-kind capture (e.g. value of public lands), NPV | B24: =-#REF! -> #REF! | C24: not yet adjusted for inflation
A25: less demand-side subsidies, NPV | B25: -2000000 | C25: tbd
A26: Balance | B26: =SUM(B23:B25) -> #REF!
A27: Fiscal viability | B27: =B26/Q!Q37 -> #REF!
E28: moving public space targets, by pop density
F29: marginal change
E30: pop density (gross) | F30: below 500 | G30: above 500 | H30: 200 | I30: 300 | J30: 400 | K30: 500 | L30: 600 | M30: 700 | N30: 800 | O30: 900 | P30: 1000
E31: open space / parks target | F31: 0.005 | G31: 0.0025 | H31: =K31+(H30-K30)/100*F31 -> 0.035 | I31: =K31+(I30-K30)/100*F31 -> 0.04 | J31: =K31+(J30-K30)/100*F31 -> 0.045 | K31: 0.05 | L31: =K31+(L30-K30)/100*G31 -> 0.0525 | M31: =K31+(M30-K30)/100*G31 -> 0.055 | N31: =K31+(N30-K30)/100*G31 -> 0.0575 | O31: =K31+(O30-K30)/100*G31 -> 0.06 | P31: =K31+(P30-K30)/100*G31 -> 0.0625
E32: amenities target | F32: 0.01 | G32: 0.005 | H32: =K32+(H30-K30)/100*F32 -> 0.07 | I32: =K32+(I30-K30)/100*F32 -> 0.08 | J32: =K32+(J30-K30)/100*F32 -> 0.09 | K32: 0.1 | L32: =K32+(L30-K30)/100*G32 -> 0.105 | M32: =K32+(M30-K30)/100*G32 -> 0.11 | N32: =K32+(N30-K30)/100*G32 -> 0.115 | O32: =K32+(O30-K30)/100*G32 -> 0.12 | P32: =K32+(P30-K30)/100*G32 -> 0.125
E33: street space target | F33: 0.015 | G33: 0.0075 | H33: =K33+(H30-K30)/100*F33 -> 0.155 | I33: =K33+(I30-K30)/100*F33 -> 0.17 | J33: =K33+(J30-K30)/100*F33 -> 0.185 | K33: 0.2 | L33: =K33+(L30-K30)/100*G33 -> 0.2075 | M33: =K33+(M30-K30)/100*G33 -> 0.215 | N33: =K33+(N30-K30)/100*G33 -> 0.2225 | O33: =K33+(O30-K30)/100*G33 -> 0.23 | P33: =K33+(P30-K30)/100*G33 -> 0.2375
E34: public space target | F34: =SUM(F31:F33) -> 0.03 | G34: =SUM(G31:G33) -> 0.015 | H34: =SUM(H31:H33) -> 0.26 | I34: =SUM(I31:I33) -> 0.29 | J34: =SUM(J31:J33) -> 0.32 | K34: =SUM(K31:K33) -> 0.35 | L34: =SUM(L31:L33) -> 0.365 | M34: =SUM(M31:M33) -> 0.38 | ... P34: =SUM(P31:P33) -> 0.425
G35: public space | H35: =H34*10000 -> 2600 | I35: =I34*10000 -> 2900 | J35: =J34*10000 -> 3200 | K35: =K34*10000 -> 3500 | L35: =L34*10000 -> 3650 | M35: =M34*10000 -> 3800 | N35: =N34*10000 -> 3950 | O35: =O34*10000 -> 4100 | P35: =P34*10000 -> 4250
G36: public space p.c. | H36: =H35/H30 -> 13 | I36: =I35/I30 -> 9.6666667 | J36: =J35/J30 -> 8 | K36: =K35/K30 -> 7 | L36: =L35/L30 -> 6.0833333 | M36: =M35/M30 -> 5.4285714 | N36: =N35/N30 -> 4.9375 | O36: =O35/O30 -> 4.5555556 | P36: =P35/P30 -> 4.25

Sheet Q_zeroed
A1: Public street network (length)
A2: Public network, by network level (in color code) | C2: 2-sided @100% | D2: 1-sided @50% | E2: zero sided (@tbd) | F2: Subtotal project-borne
B3: Arteries (main roads) | C3: 0 | D3: 0 | E3: 0 | F3: =C3+D3/2 -> 0
B4: Secondaries (distributor roads) | C4: 0 | D4: 0 | E4: 0 | F4: =C4+D4/2 -> 0
B5: Tertiaries (access and local roads) | C5: 0 | D5: 0 | E5: 0 | F5: =C5+D5/2 -> 0
B6: Subtotal project-borne | C6: =SUM(C3:C5) -> 0 | D6: =SUM(D3:D5)/2 -> 0 | E6: =SUM(E3:E5)*0 -> 0 | F6: =SUM(F3:F5) -> 0
A8: Land use (city and neighborhood scale) | X8: Lots and buildings (idealized)
A9: Land uses, by location (in color code) | C9: Environmental reservation | D9: Social reservation | E9: Other non-developable area | F9: Non-developable area | G9: Public streets | H9: City-scale public open spaces, subtotal | I9: City-scale public amenities, subtotal | J9: District-scale public open spaces, subtotal | K9: District-scale public amenities, subtotal | L9: Neighborhood-scale open spaces, subtotal | M9: Neighborhood-scale public amenities, subtotal | N9: Public lands, subtotal | O9: Private lands, subtotals | P9: Developable area, subtotals | Q9: All lands, totals | R9: Distribution (share of total) | X9: Number of lots | Y9: lot d | Z9: lot w | AA9: lot A | AB9: front margin | AC9: back margin | AD9: footprint d | AE9: side margin | AF9: side margin 2 | AG9: footprint w | AH9: footprint A | AI9: floors regular | AJ9: corner bonus | AK9: floors final | AL9: floor area | AM9: max. FAR viable | AO9: starter w | AP9: starter d | AQ9: starter f | AR9: starter w | AS9: starter d | AT9: starter f | AU9: Starter building, average floor area, if any
B10: =C9 -> Environmental reservation | C10: =C60*10000 -> 0 | F10: =SUM(C10:E10) -> 0 | Q10: =F10 -> 0 | R10: =Q10/Q37 -> #DIV/0!
B11: =D9 -> Social reservation | D11: =D60*10000 -> 0 | F11: =SUM(C11:E11) -> 0 | Q11: =F11 -> 0 | R11: =Q11/Q37 -> #DIV/0!
B12: =E9 -> Other non-developable area | E12: 0 | F12: =SUM(C12:E12) -> 0 | Q12: =F12 -> 0 | R12: =Q12/Q37 -> #DIV/0!
B13: Reservations, outside neighborhod | C13: =C10 -> 0 | D13: =D11 -> 0 | E13: =E12 -> 0 | F13: =SUM(F10:F12) -> 0 | Q13: =SUM(Q10:Q12) -> 0 | R13: =Q13/Q37 -> #DIV/0!
B14: Artery x artery (corner) | H14: 0 | I14: 0 | J14: 0 | K14: 0 | L14: 0 | M14: 0 | N14: =SUM(G14:M14) -> 0 | O14: 0 | P14: =SUM(N14:O14) -> 0 | Q14: =P14 -> 0 | R14: =Q14/Q37 -> #DIV/0! | U14: Artery x artery (corner) | X14: 0 | Y14: =Y17 -> 0 | Z14: =Y17 -> 0 | AA14: =Z14*Y14 -> 0 | AB14: =AB17 -> 0 | AC14: =AC17 -> 0 | AD14: =Y14-AB14-AC14 -> 0 | AE14: =AE17 -> 0 | AF14: =AE17 -> 0 | AG14: =Z14-AE14-AF14 -> 0 | AH14: =AG14*AD14 -> 0 | AJ14: 0 | AK14: =ROUND(AI17*(1+AJ14),0) -> 0 | AL14: =AG14*AD14*AK14 -> 0 | AM14: =IF(AA14=0,0,AL14/AA14) -> 0 | AO14: 0 | AP14: 0 | AQ14: 0 | AR14: =AO14*AG14 -> 0 | AS14: =AP14*AD14 -> 0 | AT14: =ROUND(AQ14*AK14,0) -> 0 | AU14: =AL14*AP14*AQ14 -> 0
B15: Artery x secondary (corner) | H15: 0 | I15: 0 | J15: 0 | K15: 0 | L15: 0 | M15: 0 | N15: =SUM(G15:M15) -> 0 | O15: 0 | P15: =SUM(N15:O15) -> 0 | Q15: =P15 -> 0 | R15: =Q15/Q37 -> #DIV/0! | U15: Artery x secondary (corner) | X15: 0 | Y15: =Y17 -> 0 | Z15: =Y21 -> 0 | AA15: =Z15*Y15 -> 0 | AB15: =AB17 -> 0 | AC15: =AC17 -> 0 | AD15: =Y15-AB15-AC15 -> 0 | AE15: =AE17 -> 0 | AF15: =AE21 -> 0 | AG15: =Z15-AE15-AF15 -> 0 | AH15: =AG15*AD15 -> 0 | AJ15: 0 | AK15: =ROUND(AI17*(1+AJ15),0) -> 0 | AL15: =AG15*AD15*AK15 -> 0 | AM15: =IF(AA15=0,0,AL15/AA15) -> 0 | AO15: 0 | AP15: 0 | AQ15: 0 | AR15: =AO15*AG15 -> 0 | AS15: =AP15*AD15 -> 0 | AT15: =ROUND(AQ15*AK15,0) -> 0 | AU15: =AL15*AP15*AQ15 -> 0
B16: Artery x tertiary (corner) | H16: 0 | I16: 0 | J16: 0 | K16: 0 | L16: 0 | M16: 0 | N16: =SUM(G16:M16) -> 0 | O16: 0 | P16: =SUM(N16:O16) -> 0 | Q16: =P16 -> 0 | R16: =Q16/Q37 -> #DIV/0! | U16: Artery x tertiary (corner) | X16: 0 | Y16: =Y17 -> 0 | Z16: =Y24 -> 0 | AA16: =Z16*Y16 -> 0 | AB16: =AB17 -> 0 | AC16: =AC17 -> 0 | AD16: =Y16-AB16-AC16 -> 0 | AE16: =AE17 -> 0 | AF16: =AE24 -> 0 | AG16: =Z16-AE16-AF16 -> 0 | AH16: =AG16*AD16 -> 0 | AJ16: 0 | AK16: =ROUND(AI17*(1+AJ16),0) -> 0 | AL16: =AG16*AD16*AK16 -> 0 | AM16: =IF(AA16=0,0,AL16/AA16) -> 0 | AO16: 0 | AP16: 0 | AQ16: 0 | AR16: =AO16*AG16 -> 0 | AS16: =AP16*AD16 -> 0 | AT16: =ROUND(AQ16*AK16,0) -> 0 | AU16: =AL16*AP16*AQ16 -> 0
B17: Artery (regular) | H17: 0 | I17: 0 | J17: 0 | K17: 0 | L17: 0 | M17: 0 | N17: =SUM(G17:M17) -> 0 | O17: 0 | P17: =SUM(N17:O17) -> 0 | Q17: =P17 -> 0 | R17: =Q17/Q37 -> #DIV/0! | U17: Artery (regular) | X17: 0 | Y17: 0 | Z17: 0 | AA17: =Z17*Y17 -> 0 | AB17: 0 | AC17: 0 | AD17: =Y17-AB17-AC17 -> 0 | AE17: 0 | AF17: =AE17 -> 0 | AG17: =Z17-AE17-AF17 -> 0 | AH17: =AG17*AD17 -> 0 | AI17: 0 | AJ17: 0 | AK17: =ROUND(AI17*(1+AJ17),0) -> 0 | AL17: =AG17*AD17*AK17 -> 0 | AM17: =IF(AA17=0,0,AL17/AA17) -> 0 | AO17: 0 | AP17: 0 | AQ17: 0 | AR17: =AO17*AG17 -> 0 | AS17: =AP17*AD17 -> 0 | AT17: =ROUND(AQ17*AK17,0) -> 0 | AU17: =AL17*AP17*AQ17 -> 0
A18: Land on arteries, subtotal | F18: =SUM(F14:F17) -> 0 | H18: =SUM(H14:H17) -> 0 | I18: =SUM(I14:I17) -> 0 | J18: =SUM(J14:J17) -> 0 | K18: =SUM(K14:K17) -> 0 | L18: =SUM(L14:L17) -> 0 | M18: =SUM(M14:M17) -> 0 | N18: =SUM(N14:N17) -> 0 | O18: =SUM(O14:O17) -> 0 | ... Q18: =SUM(Q14:Q17) -> 0 | R18: =Q18/Q37 -> #DIV/0! | T18: w/path | X18: =C45*2 -> 0 | Y18: =Y17 -> 0 | Z18: =Z17 -> 0 | AA18: =AA17 -> 0 | AB18: =AB17 -> 0 | AC18: =AC17 -> 0 | AD18: =AD17 -> 0 | AE18: =AE17 -> 0 | AF18: =AF17 -> 0 | ... AH18: =AH17 -> 0 | AK18: =AK17 -> 0 | AL18: =AL17 -> 0 | AM18: =IF(AA18=0,0,AL18/AA18) -> 0 | AO18: =AO17 -> 0 | AP18: =AP17 -> 0 | AQ18: =AQ17 -> 0 | AR18: =AO18*AG18 -> 0 | AS18: =AP18*AD18 -> 0 | AT18: =ROUND(AQ18*AK18,0) -> 0 | AU18: =AU17 -> 0
B19: Secondary x secondary (corner) | H19: 0 | I19: 0 | J19: 0 | K19: 0 | L19: 0 | M19: 0 | N19: =SUM(G19:M19) -> 0 | O19: 0 | P19: =SUM(N19:O19) -> 0 | Q19: =P19 -> 0 | R19: =Q19/Q37 -> #DIV/0! | U19: Secondary x secondary (corner) | X19: 0 | Y19: =Y21 -> 0 | Z19: =Y21 -> 0 | AA19: =Z19*Y19 -> 0 | AB19: =AB21 -> 0 | AC19: =AC21 -> 0 | AD19: =Y19-AB19-AC19 -> 0 | AE19: =AE21 -> 0 | AF19: =AE21 -> 0 | AG19: =Z19-AE19-AF19 -> 0 | AH19: =AG19*AD19 -> 0 | AJ19: =AJ15 -> 0 | AK19: =ROUND(AI21*(1+AJ19),0) -> 0 | AL19: =AG19*AD19*AK19 -> 0 | AM19: =IF(AA19=0,0,AL19/AA19) -> 0 | AO19: 0 | AP19: 0 | AQ19: 0 | AR19: =AO19*AG19 -> 0 | AS19: =AP19*AD19 -> 0 | AT19: =ROUND(AQ19*AK19,0) -> 0 | AU19: =AL19*AP19*AQ19 -> 0
B20: Secondary x tertiary (corner) | H20: 0 | I20: 0 | J20: 0 | K20: 0 | L20: 0 | M20: 0 | N20: =SUM(G20:M20) -> 0 | O20: 0 | P20: =SUM(N20:O20) -> 0 | Q20: =P20 -> 0 | R20: =Q20/Q37 -> #DIV/0! | U20: Secondary x tertiary (corner) | X20: 0 | Y20: =Y21 -> 0 | Z20: =Y24 -> 0 | AA20: =Z20*Y20 -> 0 | AB20: =AB21 -> 0 | AC20: =AC21 -> 0 | AD20: =Y20-AB20-AC20 -> 0 | AE20: =AE21 -> 0 | AF20: =AE24 -> 0 | AG20: =Z20-AE20-AF20 -> 0 | AH20: =AG20*AD20 -> 0 | AJ20: =AJ16 -> 0 | AK20: =ROUND(AI21*(1+AJ20),0) -> 0 | AL20: =AG20*AD20*AK20 -> 0 | AM20: =IF(AA20=0,0,AL20/AA20) -> 0 | AO20: 0 | AP20: 0 | AQ20: 0 | AR20: =AO20*AG20 -> 0 | AS20: =AP20*AD20 -> 0 | AT20: =ROUND(AQ20*AK20,0) -> 0 | AU20: =AL20*AP20*AQ20 -> 0
B21: Secondary (regular) | H21: 0 | I21: 0 | J21: 0 | K21: 0 | L21: 0 | M21: 0 | N21: =SUM(G21:M21) -> 0 | O21: 0 | P21: =SUM(N21:O21) -> 0 | Q21: =P21 -> 0 | R21: =Q21/Q37 -> #DIV/0! | U21: Secondary (regular) | X21: 0 | Y21: 0 | Z21: 0 | AA21: =Z21*Y21 -> 0 | AB21: 0 | AC21: 0 | AD21: =Y21-AB21-AC21 -> 0 | AE21: 0 | AF21: =AE21 -> 0 | AG21: =Z21-AE21-AF21 -> 0 | AH21: =AG21*AD21 -> 0 | AI21: 0 | AJ21: 0 | AK21: =ROUND(AI21*(1+AJ21),0) -> 0 | AL21: =AG21*AD21*AK21 -> 0 | AM21: =IF(AA21=0,0,AL21/AA21) -> 0 | AO21: 0 | AP21: 0 | AQ21: 0 | AR21: =AO21*AG21 -> 0 | AS21: =AP21*AD21 -> 0 | AT21: =ROUND(AQ21*AK21,0) -> 0 | AU21: =AL21*AP21*AQ21 -> 0
B22: Land on secondaries, subtotal | F22: =SUM(F19:F21) -> 0 | H22: =SUM(H19:H21) -> 0 | I22: =SUM(I19:I21) -> 0 | J22: =SUM(J19:J21) -> 0 | K22: =SUM(K19:K21) -> 0 | L22: =SUM(L19:L21) -> 0 | M22: =SUM(M19:M21) -> 0 | N22: =SUM(N19:N21) -> 0 | O22: =SUM(O19:O21) -> 0 | ... Q22: =SUM(Q19:Q21) -> 0 | R22: =Q22/Q37 -> #DIV/0! | U22: w/ path | X22: =C46*2 -> 0 | Y22: =Y21 -> 0 | Z22: =Z21 -> 0 | AA22: =AA21 -> 0 | AB22: =AB21 -> 0 | AC22: =AC21 -> 0 | AD22: =AD21 -> 0 | AE22: =AE21 -> 0 | AF22: =AF21 -> 0 | ... AH22: =AH21 -> 0 | AK22: =AK21 -> 0 | AL22: =AL21 -> 0 | AM22: =IF(AA22=0,0,AL22/AA22) -> 0 | AO22: =AO21 -> 0 | AP22: =AP21 -> 0 | AQ22: =AQ21 -> 0 | AR22: =AO22*AG22 -> 0 | AS22: =AP22*AD22 -> 0 | AT22: =ROUND(AQ22*AK22,0) -> 0 | AU22: =AU21 -> 0
B23: Tertiary x tertiary (corner) | H23: 0 | I23: 0 | J23: 0 | K23: 0 | L23: 0 | M23: 0 | N23: =SUM(G23:M23) -> 0 | O23: 0 | P23: =SUM(N23:O23) -> 0 | Q23: =P23 -> 0 | R23: =Q23/Q37 -> #DIV/0! | U23: Tertiary x tertiary (corner) | X23: 0 | Y23: =Y24 -> 0 | Z23: =Y24 -> 0 | AA23: =Z23*Y23 -> 0 | AB23: =AB24 -> 0 | AC23: =AC24 -> 0 | AD23: =Y23-AB23-AC23 -> 0 | AE23: =AE24 -> 0 | AF23: =AE24 -> 0 | AG23: =Z23-AE23-AF23 -> 0 | AH23: =AG23*AD23 -> 0 | AJ23: =AJ16 -> 0 | AK23: =ROUND(AI24*(1+AJ23),0) -> 0 | AL23: =AG23*AD23*AK23 -> 0 | AM23: =IF(AA23=0,0,AL23/AA23) -> 0 | AO23: 0 | AP23: 0 | AQ23: 0 | AR23: =AO23*AG23 -> 0 | AS23: =AP23*AD23 -> 0 | AT23: =ROUND(AQ23*AK23,0) -> 0 | AU23: =AL23*AP23*AQ23 -> 0
B24: Tertiary (regular) | H24: 0 | I24: 0 | J24: 0 | K24: 0 | L24: 0 | M24: 0 | N24: =SUM(G24:M24) -> 0 | O24: 0 | P24: =SUM(N24:O24) -> 0 | Q24: =P24 -> 0 | R24: =Q24/Q37 -> #DIV/0! | U24: Tertiary (regular) | X24: 0 | Y24: 0 | Z24: 0 | AA24: =Z24*Y24 -> 0 | AB24: 0 | AC24: 0 | AD24: =Y24-AB24-AC24 -> 0 | AE24: 0 | AF24: =AE24 -> 0 | AG24: =Z24-AE24-AF24 -> 0 | AH24: =AG24*AD24 -> 0 | AI24: 0 | AJ24: 0 | AK24: =ROUND(AI24*(1+AJ24),0) -> 0 | AL24: =AG24*AD24*AK24 -> 0 | AM24: =IF(AA24=0,0,AL24/AA24) -> 0 | AO24: 0 | AP24: 0 | AQ24: 0 | AR24: =AO24*AG24 -> 0 | AS24: =AP24*AD24 -> 0 | AT24: =ROUND(AQ24*AK24,0) -> 0 | AU24: =AL24*AP24*AQ24 -> 0
B25: Land on local roads, subtotal | F25: =SUM(F23:F24) -> 0 | H25: =SUM(H23:H24) -> 0 | I25: =SUM(I23:I24) -> 0 | J25: =SUM(J23:J24) -> 0 | K25: =SUM(K23:K24) -> 0 | L25: =SUM(L23:L24) -> 0 | M25: =SUM(M23:M24) -> 0 | N25: =SUM(N23:N24) -> 0 | O25: =SUM(O23:O24) -> 0 | ... Q25: =SUM(Q23:Q24) -> 0 | R25: =Q25/Q37 -> #DIV/0! | U25: w/path | V25: cluster w | W25: int. path w | X25: =SUM(C47:C48)*2 -> 0 | Y25: =Y24 -> 0 | Z25: =Z24 -> 0 | AA25: =AA24 -> 0 | AB25: =AB24 -> 0 | AC25: =AC24 -> 0 | AD25: =AD24 -> 0 | AE25: =AE24 -> 0 | AF25: =AF24 -> 0 | ... AH25: =AH24 -> 0 | AK25: =AK24 -> 0 | AL25: =AL24 -> 0 | AM25: =IF(AA25=0,0,AL25/AA25) -> 0 | AO25: =AO24 -> 0 | AP25: =AP24 -> 0 | AQ25: =AQ24 -> 0 | AR25: =AO25*AG25 -> 0 | AS25: =AP25*AD25 -> 0 | AT25: =ROUND(AQ25*AK25,0) -> 0 | AU25: =AU24 -> 0
A26: Off-grid clusters | B26: on arteries | H26: 0 | I26: 0 | J26: 0 | K26: 0 | L26: 0 | M26: 0 | N26: =SUM(G26:M26) -> 0 | O26: 0 | P26: =SUM(N26:O26) -> 0 | Q26: =P26 -> 0 | R26: =Q26/Q37 -> #DIV/0! | T26: Off-grid clusters | U26: on arteries | V26: 0 | W26: 0 | X26: 0 | Y26: =(V26-W26)/2 -> 0 | Z26: 0 | AA26: =Z26*Y26 -> 0 | AB26: 0 | AC26: 0 | AD26: =Y26-AB26-AC26 -> 0 | AE26: 0 | AF26: =AE26 -> 0 | AG26: =Z26-2*AE26 -> 0 | AH26: =AG26*AD26 -> 0 | AI26: 0 | AJ26: 0 | AK26: =ROUND(AI26*(1+AJ26),0) -> 0 | AL26: =AG26*AD26*AK26 -> 0 | AM26: =IF(AA26=0,0,AL26/AA26) -> 0 | AO26: 0 | AP26: 0 | AQ26: 0 | AR26: =AO26*AG26 -> 0 | AS26: =AP26*AD26 -> 0 | AT26: =ROUND(AQ26*AK26,0) -> 0 | AU26: =AL26*AP26*AQ26 -> 0
A27: Off-grid clusters | B27: on secondaries | H27: 0 | I27: 0 | J27: 0 | K27: 0 | L27: 0 | M27: 0 | N27: =SUM(G27:M27) -> 0 | O27: 0 | P27: =SUM(N27:O27) -> 0 | Q27: =P27 -> 0 | R27: =Q27/Q37 -> #DIV/0! | T27: Off-grid clusters | U27: on secondaries | V27: =V28 -> 0 | W27: =W28 -> 0 | X27: 0 | Y27: =(V27-W27)/2 -> 0 | Z27: 0 | AA27: =Z27*Y27 -> 0 | AB27: 0 | AC27: 0 | AD27: =Y27-AB27-AC27 -> 0 | AE27: 0 | AF27: =AE27 -> 0 | AG27: =Z27-2*AE27 -> 0 | AH27: =AG27*AD27 -> 0 | AI27: =AI28 -> 0 | AJ27: 0 | AK27: =ROUND(AI27*(1+AJ27),0) -> 0 | AL27: =AG27*AD27*AK27 -> 0 | AM27: =IF(AA27=0,0,AL27/AA27) -> 0 | AO27: =AO28 -> 0 | AP27: =AP28 -> 0 | AQ27: =AQ28 -> 0 | AR27: =AO27*AG27 -> 0 | AS27: =AP27*AD27 -> 0 | AT27: =ROUND(AQ27*AK27,0) -> 0 | AU27: =AL27*AP27*AQ27 -> 0
A28: Simple off-grid clusters | B28: on locals | H28: 0 | I28: 0 | J28: 0 | K28: 0 | L28: 0 | M28: 0 | N28: =SUM(G28:M28) -> 0 | O28: 0 | P28: =SUM(N28:O28) -> 0 | Q28: =P28 -> 0 | R28: =Q28/Q37 -> #DIV/0! | T28: Simple off-grid clusters | U28: on locals | V28: 0 | W28: 0 | X28: 0 | Y28: =(V28-W28)/2 -> 0 | Z28: 0 | AA28: =Z28*Y28 -> 0 | AB28: 0 | AC28: 0 | AD28: =Y28-AB28-AC28 -> 0 | AE28: 0 | AF28: =AE28 -> 0 | AG28: =Z28-2*AE28 -> 0 | AH28: =AG28*AD28 -> 0 | AI28: 0 | AJ28: 0 | AK28: =ROUND(AI28*(1+AJ28),0) -> 0 | AL28: =AG28*AD28*AK28 -> 0 | AM28: =IF(AA28=0,0,AL28/AA28) -> 0 | AO28: 0 | AP28: 0 | AQ28: 0 | AR28: =AO28*AG28 -> 0 | AS28: =AP28*AD28 -> 0 | AT28: =ROUND(AQ28*AK28,0) -> 0 | AU28: =AL28*AP28*AQ28 -> 0
A29: 2-level off-grid clusters, 1st level | B29: on locals | H29: 0 | I29: 0 | J29: 0 | K29: 0 | L29: 0 | M29: 0 | N29: =SUM(G29:M29) -> 0 | O29: 0 | P29: =SUM(N29:O29) -> 0 | Q29: =P29 -> 0 | R29: =Q29/Q37 -> #DIV/0! | T29: 2-level off-grid clusters, 1st level | U29: on locals | V29: =V28 -> 0 | W29: =W28 -> 0 | X29: 0 | Y29: =Y28 -> 0 | Z29: =Z28 -> 0 | AA29: =AA28 -> 0 | AB29: =AB28 -> 0 | AC29: =AC28 -> 0 | AD29: =AD28 -> 0 | AE29: =AE28 -> 0 | AF29: =AF28 -> 0 | ... AH29: =AH28 -> 0 | AK29: =AK28 -> 0 | AL29: =AL28 -> 0 | AM29: =IF(AA29=0,0,AL29/AA29) -> 0 | AO29: =AO28 -> 0 | AP29: =AP28 -> 0 | AQ29: =AQ28 -> 0 | AR29: =AO29*AG29 -> 0 | AS29: =AP29*AD29 -> 0 | AT29: =ROUND(AQ29*AK29,0) -> 0 | AU29: =AU28 -> 0
A30: 2nd level | B30: from 1st | H30: 0 | I30: 0 | J30: 0 | K30: 0 | L30: 0 | M30: 0 | N30: =SUM(G30:M30) -> 0 | O30: 0 | P30: =SUM(N30:O30) -> 0 | Q30: =P30 -> 0 | R30: =Q30/Q37 -> #DIV/0! | T30: 2nd level | U30: from 1st | V30: =V28 -> 0 | W30: 0 | X30: 0 | Y30: =(V30-W30)/2 -> 0 | Z30: 0 | AA30: =Z30*Y30 -> 0 | AB30: =AB28 -> 0 | AC30: =AC28 -> 0 | AD30: =Y30-AB30-AC30 -> 0 | AE30: =AE28 -> 0 | AF30: =AE30 -> 0 | AG30: =Z30-2*AE30 -> 0 | AH30: =AG30*AD30 -> 0 | AI30: =AI28 -> 0 | AJ30: 0 | AK30: =ROUND(AI30*(1+AJ30),0) -> 0 | AL30: =AG30*AD30*AK30 -> 0 | AM30: =IF(AA30=0,0,AL30/AA30) -> 0 | AO30: 0 | AP30: 0 | AQ30: 0 | AR30: =AO30*AG30 -> 0 | AS30: =AP30*AD30 -> 0 | AT30: =ROUND(AQ30*AK30,0) -> 0 | AU30: =AL30*AP30*AQ30 -> 0
B31: Off-grid partitions, subtotal | H31: =SUM(H26:H30) -> 0 | I31: =SUM(I26:I30) -> 0 | J31: =SUM(J26:J30) -> 0 | K31: =SUM(K26:K30) -> 0 | L31: =SUM(L26:L30) -> 0 | M31: =SUM(M26:M30) -> 0 | N31: =SUM(N26:N30) -> 0 | O31: =SUM(O26:O30) -> 0 | ... Q31: =SUM(Q26:Q30) -> 0 | R31: =Q31/Q37 -> #DIV/0!
B32: Land in urban blocks, subtotal | C32: 0 | D32: 0 | E32: 0 | F32: 0 | G32: 0 | H32: =H31+H25+H22+H18 -> 0 | I32: =I31+I25+I22+I18 -> 0 | J32: =J31+J25+J22+J18 -> 0 | K32: =K31+K25+K22+K18 -> 0 | L32: =L31+L25+L22+L18 -> 0 | M32: =M31+M25+M22+M18 -> 0 | N32: =N31+N25+N22+N18 -> 0 | O32: =O31+O25+O22+O18 -> 0 | ... Q32: =Q31+Q25+Q22+Q18 -> 0 | R32: =Q32/Q37 -> #DIV/0!
B33: Arteries (main roads) | C33: 0 | D33: 0 | E33: 0 | F33: =SUM(C33:E33) -> 0 | G33: 0 | N33: =G33 -> 0 | P33: =SUM(N33:O33) -> 0 | Q33: =P33+F33 -> 0 | R33: =Q33/Q37 -> #DIV/0!
B34: Secondaries (distributor roads) | C34: 0 | D34: 0 | E34: 0 | F34: =SUM(C34:E34) -> 0 | G34: 0 | N34: =G34 -> 0 | P34: =SUM(N34:O34) -> 0 | Q34: =P34+F34 -> 0 | R34: =Q34/Q37 -> #DIV/0!
B35: Tertiaries (access and local roads) | C35: 0 | D35: 0 | E35: 0 | F35: =SUM(C35:E35) -> 0 | G35: 0 | N35: =G35 -> 0 | P35: =SUM(N35:O35) -> 0 | Q35: =P35+F35 -> 0 | R35: =Q35/Q37 -> #DIV/0!
B36: Land in public streets, subtotal | C36: =SUM(C33:C35) -> 0 | D36: =SUM(D33:D35) -> 0 | E36: =SUM(E33:E35) -> 0 | F36: =SUM(F33:F35) -> 0 | G36: =SUM(G33:G35) -> 0 | N36: =SUM(N33:N35) -> 0 | P36: =SUM(P33:P35) -> 0 | Q36: =SUM(Q33:Q35) -> 0 | R36: =Q36/Q37 -> #DIV/0!
B37: Totals | C37: =C36+C13 -> 0 | D37: =D36+D13 -> 0 | E37: =E36+E13 -> 0 | F37: =F36+F13 -> 0 | G37: =G32 -> 0 | H37: =H32 -> 0 | I37: =I32 -> 0 | J37: =J32 -> 0 | K37: =K32 -> 0 | L37: =L32 -> 0 | M37: =M32 -> 0 | N37: =N36+N32 -> 0 | O37: =O36+O32 -> 0 | P37: =P36+P32 -> 0 | Q37: =Q36+Q32+Q13 -> 0 | R37: =Q37/Q37 -> #DIV/0!
B38: Distribution (share of total) | C38: =C37/Q37 -> #DIV/0! | D38: =D37/Q37 -> #DIV/0! | E38: =E37/Q37 -> #DIV/0! | F38: =F37/Q37 -> #DIV/0! | G38: =G37/Q37 -> #DIV/0! | H38: =H37/Q37 -> #DIV/0! | I38: =I37/Q37 -> #DIV/0! | J38: =J37/Q37 -> #DIV/0! | K38: =K37/Q37 -> #DIV/0! | L38: =L37/Q37 -> #DIV/0! | M38: =M37/Q37 -> #DIV/0! | N38: =N37/Q37 -> #DIV/0! | O38: =O37/Q37 -> #DIV/0! | P38: =P37/Q37 -> #DIV/0! | Q38: =Q37/Q37 -> #DIV/0!
A43: Clusters
B44: Area | C44: Connections from public network | D44: Semi-private / collective infra | G44: access areas on on-grid partitions | H44: semi-private collective circulation | I44: semi-private collective green space
A45: Off-grid clusters | B45: on arteries | C45: 0 | D45: 0 | G45: 0 | H45: 0 | I45: 0
A46: Off-grid clusters | B46: on secondaries | C46: 0 | D46: 0 | G46: 0 | H46: 0 | I46: 0
A47: Simple off-grid clusters | B47: on locals | C47: 0 | D47: 0 | G47: 0 | H47: 0 | I47: 0
A48: 2-level off-grid clusters, 1st level | B48: on locals | C48: 0 | D48: 0 | G48: 0 | H48: 0 | I48: 0
A49: 2nd level | B49: from 1st | C49: 0 | D49: 0 | H49: 0 | I49: 0
A51: Prior Landownership | B51: dummy values
A52: Land areas | B52: public roads, existing | C52: environmental reservation | D52: social reservation | E52: agricultural land | F52: urban land | G52: subtotals | H52: %shares
A53: existing public roads | B53: =H53*Q37/10000 -> 0 | G53: =B53 -> 0 | H53: 0.0625
A54: Landowner 1 | C54: 0 | D54: 0 | E54: =H54*Q37/10000 -> 0 | F54: 0 | G54: =SUM(C54:F54) -> 0 | H54: 0.076875
A55: Landowner 2 | C55: 0 | D55: 0 | E55: =H55*Q37/10000 -> 0 | F55: 0 | G55: =SUM(C55:F55) -> 0 | H55: 0.225
A56: Landowner 3 | C56: 0 | D56: 0 | E56: =H56*Q37/10000 -> 0 | F56: 0 | G56: =SUM(C56:F56) -> 0 | H56: 0.03625
A57: Landowner 4 | C57: 0 | D57: 0 | E57: =H57*Q37/10000 -> 0 | F57: 0 | G57: =SUM(C57:F57) -> 0 | H57: 0.389375
A58: Landowner 5 | C58: 0 | D58: 0 | E58: =H58*Q37/10000 -> 0 | F58: 0 | G58: =SUM(C58:F58) -> 0 | H58: 0.125
A59: Landowner 6 | C59: 0 | D59: 0 | E59: =H59*Q37/10000 -> 0 | F59: 0 | G59: =SUM(C59:F59) -> 0 | H59: =1-SUM(H53:H58) -> 0.085
A60: subtotals | B60: =SUM(B53:B59) -> 0 | C60: =SUM(C53:C59) -> 0 | D60: =SUM(D53:D59) -> 0 | E60: =SUM(E53:E59) -> 0 | F60: =SUM(F53:F59) -> 0 | G60: =SUM(G53:G59) -> 0 | H60: =SUM(H53:H59) -> 1
A62: precision check, comparing areas
A63: area | B63: area size | C63: deviation
A64: site, defined by external boundary | B64: 0
A65: individual land owners' contribution | B65: =G60*10000 -> 0 | C65: =(B65-B64)/B65 -> #DIV/0!
A66: serviced lands (project) | B66: =Q37 -> 0 | C66: =(B66-B64)/B66 -> #DIV/0!
A68: Notes
A69: All quantities from the spatial model
A70: All quantities from the spatial model - NOT YET EXISTING/MODELLED

Sheet 1off-site
A1: City-scale budget: off-site costs and revenues (e.g. related to trunk infrastructure)
A2: Off-site costs | B2: hard cost | C2: physical contingency | D2: design & management | E2: base-year cost before interest | F2: interest cost | G2: total cost (base year)
A3: Off-site costs (e.g. trunk infra, if project borne) | C3: 0.1 | D3: 0.12 | E3: =B3*(1+C3)*(1+D3) -> 0 | F3: 0.09 | G3: =E3*(1+F3) -> 0
A4: Other costs, if any | C4: 0.1 | D4: 0.12 | E4: =B4*(1+C4)*(1+D4) -> 0 | F4: =F3 -> 0.09 | G4: =E4*(1+F4) -> 0
A5: Other costs, if any | C5: 0.1 | D5: 0.12 | E5: =B5*(1+C5)*(1+D5) -> 0 | F5: =F3 -> 0.09 | G5: =E5*(1+F5) -> 0
A6: Total off-site costs, base year | E6: =SUM(E3:E5) -> 0 | G6: =SUM(G3:G5) -> 0
A8: Off-site revenues (benefits) | B8: base-year revenue | G8: total revenue (base year)
A9: Off-site revenues (e.g. value capture along trunk infra) | G9: =B9 -> 0
A10: Other revenues/benefits, if any | G10: =B10 -> 0
A11: Other revenues/benefits, if any | G11: =B11 -> 0
A12: Total off-site revenues/benefits, base year | E12: =SUM(E9:E11) -> 0 | G12: =SUM(G9:G11) -> 0
A14: Off-site surplus (loss), base year | E14: =E6-E12 -> 0 | G14: =G12-G6 -> 0
F15: share of loss that is project-borne, if applicable
F16: off-site costs, project-borne | G16: =IF(G14<0,G14*G15,0) -> 0
A18: Notes
A19: user input in the financial model
A20: (a) from the spatial model
A21: (b) per total area
A23: ="@Matt, glimpse of value capture for trunk infrastructure, can be hidden or excluded" -> @Matt, glimpse of value capture for trunk infrastructure, can be hidden or excluded

Sheet 1site
A1: Land acquisition and landowners
A2: Land areas | B2: public roads, existing | C2: environmental reservation | D2: social reservation | E2: agricultural land | F2: urban land | G2: subtotals
A3: existing public roads | B3: =Q!B53 -> 0 | G3: =B3 -> 0
A4: Landowner 1 | C4: =Q!C54 -> 0 | D4: =Q!D54 -> 0 | E4: =Q!E54 -> 0 | F4: =Q!F54 -> 0 | G4: =SUM(C4:F4) -> 0
A5: Landowner 2 | C5: =Q!C55 -> 0 | D5: =Q!D55 -> 0 | E5: =Q!E55 -> 0 | F5: =Q!F55 -> 0 | G5: =SUM(C5:F5) -> 0
A6: Landowner 3 | C6: =Q!C56 -> 0 | D6: =Q!D56 -> 0 | E6: =Q!E56 -> 0 | F6: =Q!F56 -> 0 | G6: =SUM(C6:F6) -> 0
A7: Landowner 4 | C7: =Q!C57 -> 0 | D7: =Q!D57 -> 0 | E7: =Q!E57 -> 0 | F7: =Q!F57 -> 0 | G7: =SUM(C7:F7) -> 0
A8: Landowner 5 | C8: =Q!C58 -> 0 | D8: =Q!D58 -> 0 | E8: =Q!E58 -> 0 | F8: =Q!F58 -> 0 | G8: =SUM(C8:F8) -> 0
A9: Landowner 6 | C9: =Q!C59 -> 0 | D9: =Q!D59 -> 0 | E9: =Q!E59 -> 0 | F9: =Q!F59 -> 0 | G9: =SUM(C9:F9) -> 0
A10: subtotals | B10: =SUM(B3:B9) -> 0 | C10: =SUM(C3:C9) -> 0 | D10: =SUM(D3:D9) -> 0 | E10: =SUM(E3:E9) -> 0 | F10: =SUM(F3:F9) -> 0 | G10: =SUM(G3:G9) -> 0
A12: Land prices / values | B12: =B2 -> public roads, existing | C12: =C2 -> environmental reservation | D12: =D2 -> social reservation | E12: =E2 -> agricultural land | F12: =F2 -> urban land | G12: average
A13: existing public roads | B13: 0 | G13: =G23/G3/10000 -> #DIV/0!
A14: Landowner 1 | C14: 0 | D14: 0 | E14: 10.26 | F14: 0 | G14: =G24/G4/10000 -> #DIV/0!
A15: Landowner 2 | C15: 0 | D15: 0 | E15: 10.75 | F15: 0 | G15: =G25/G5/10000 -> #DIV/0!
A16: Landowner 3 | C16: 0 | D16: 0 | E16: 11.55 | F16: 0 | G16: =G26/G6/10000 -> #DIV/0!
A17: Landowner 4 | C17: 0 | D17: 0 | E17: 11.79 | F17: 0 | G17: =G27/G7/10000 -> #DIV/0!
A18: Landowner 5 | C18: 0 | D18: 0 | E18: 8.5 | F18: 0 | G18: =G28/G8/10000 -> #DIV/0!
A19: Landowner 6 | C19: 0 | D19: 0 | E19: 9 | F19: 0 | G19: =G29/G9/10000 -> #DIV/0!
A20: average | B20: =B30/B10/10000 -> #DIV/0! | C20: =C30/C10/10000 -> #DIV/0! | D20: =D30/D10/10000 -> #DIV/0! | E20: =E30/E10/10000 -> #DIV/0! | F20: =F30/F10/10000 -> #DIV/0! | G20: =G30/G10/10000 -> #DIV/0!
A22: Land prices / values | B22: =B12 -> public roads, existing | C22: =C12 -> environmental reservation | D22: =D12 -> social reservation | E22: =E12 -> agricultural land | F22: =F12 -> urban land | G22: subtotal
A23: existing public roads | B23: =B13*B3*10000 -> 0 | G23: =B23 -> 0
A24: Landowner 1 | C24: =C14*C4*10000 -> 0 | D24: =D14*D4*10000 -> 0 | E24: =E14*E4*10000 -> 0 | F24: =F14*F4*10000 -> 0 | G24: =SUM(C24:F24) -> 0
A25: Landowner 2 | C25: =C15*C5*10000 -> 0 | D25: =D15*D5*10000 -> 0 | E25: =E15*E5*10000 -> 0 | F25: =F15*F5*10000 -> 0 | G25: =SUM(C25:F25) -> 0
A26: Landowner 3 | C26: =C16*C6*10000 -> 0 | D26: =D16*D6*10000 -> 0 | E26: =E16*E6*10000 -> 0 | F26: =F16*F6*10000 -> 0 | G26: =SUM(C26:F26) -> 0
A27: Landowner 4 | C27: =C17*C7*10000 -> 0 | D27: =D17*D7*10000 -> 0 | E27: =E17*E7*10000 -> 0 | F27: =F17*F7*10000 -> 0 | G27: =SUM(C27:F27) -> 0
A28: Landowner 5 | C28: =C18*C8*10000 -> 0 | D28: =D18*D8*10000 -> 0 | E28: =E18*E8*10000 -> 0 | F28: =F18*F8*10000 -> 0 | G28: =SUM(C28:F28) -> 0
A29: Landowner 5 | C29: =C19*C9*10000 -> 0 | D29: =D19*D9*10000 -> 0 | E29: =E19*E9*10000 -> 0 | F29: =F19*F9*10000 -> 0 | G29: =SUM(C29:F29) -> 0
A30: average | B30: =B23 -> 0 | C30: =SUM(C24:C29) -> 0 | D30: =SUM(D24:D29) -> 0 | E30: =SUM(E24:E29) -> 0 | F30: =SUM(F24:F29) -> 0 | G30: =SUM(G23:G29) -> 0
A32: Notes:
A33: quantity from the spatial model, OR manual user input in the financial model
A34: user input in the financial model

Sheet 2neighborhood
A1: Costs of adequate land development
B2: Cost item | C2: unit cost | D2: quantity (a) | E2: hard cost | G2: physical contingency | I2: design & management | J2: base-year cost before interest | K2: interest cost | L2: total cost (base year)
B3: Off-site costs, project-borne share (1) | C3: ='1off-site'!G14 -> 0 | D3: ='1off-site'!G15 -> 0 | E3: =C3*D3 -> 0 | G3: 0 | I3: 0.02 | J3: =E3*(1+G3)*(1+I3) -> 0 | K3: =K6 -> 0.1 | L3: =J3*(1+K3) -> 0
B4: Land costs (0) | C4: 10 | D4: =Q!Q37/10000 -> 0 | E4: =C4*D4*10000 -> 0 | G4: 0 | I4: 0.03 | J4: =E4*(1+G4)*(1+I4) -> 0 | K4: =K6 -> 0.1 | L4: =J4*(1+K4) -> 0
B5: Site preparation | C5: 2.5 | D5: =Q!Q37/10000 -> 0 | E5: =C5*D5*10000 -> 0 | G5: 0.05 | I5: 0.1 | J5: =E5*(1+G5)*(1+I5) -> 0 | K5: =K6 -> 0.1 | L5: =J5*(1+K5) -> 0
B6: Land-related costs, subtotal | E6: =SUM(E3:F5) -> 0 | J6: =SUM(J3:J5) -> 0 | K6: 0.1 | L6: =J6*(1+K6) -> 0 | P6: =L6/D4 -> #DIV/0!
B8: Arteries (main roads), higher standard | C8: 1200 | D8: =Q!F3 -> 0 | E8: =C8*D8 -> 0 | G8: =G11 -> 0.1 | I8: =I11 -> 0.12 | J8: =E8*(1+G8)*(1+I8) -> 0 | K8: =K6 -> 0.1 | L8: =J8*(1+K8) -> 0
B9: Connections to lots on arteries | C9: 500 | D9: =SUM(Q!X14:X18) -> 0 | E9: =C9*D9 -> 0 | G9: =G11 -> 0.1 | I9: =I11 -> 0.12 | J9: =E9*(1+G9)*(1+I9) -> 0 | K9: =K6 -> 0.1 | L9: =J9*(1+K9) -> 0
A10: Connections to off-grid clusters | B10: on arteries | C10: 500 | D10: =Q!C45 -> 0 | E10: =C10*D10 -> 0 | G10: =G11 -> 0.1 | I10: =I11 -> 0.12 | J10: =E10*(1+G10)*(1+I10) -> 0 | K10: =K6 -> 0.1 | L10: =J10*(1+K10) -> 0
B11: Arteries (main roads), subtotal | E11: =SUM(E8:F10) -> 0 | G11: 0.1 | I11: 0.12 | J11: =E11*(1+G11)*(1+I11) -> 0 | K11: =K6 -> 0.1 | L11: =J11*(1+K11) -> 0
B12: Secondaries (distributor roads), medium standard | C12: 600 | D12: =Q!F4 -> 0 | E12: =C12*D12 -> 0 | G12: =G15 -> 0.1 | I12: =I15 -> 0.12 | J12: =E12*(1+G12)*(1+I12) -> 0 | K12: =K6 -> 0.1 | L12: =J12*(1+K12) -> 0
B13: Connections to lots on secondaries | C13: 400 | D13: =SUM(Q!X19:X22) -> 0 | E13: =C13*D13 -> 0 | G13: =G15 -> 0.1 | I13: =I15 -> 0.12 | J13: =E13*(1+G13)*(1+I13) -> 0 | K13: =K6 -> 0.1 | L13: =J13*(1+K13) -> 0
A14: Connections to off-grid clusters | B14: on secondaries | C14: 500 | D14: =Q!C46 -> 0 | E14: =C14*D14 -> 0 | G14: =G15 -> 0.1 | I14: =I15 -> 0.12 | J14: =E14*(1+G14)*(1+I14) -> 0 | K14: =K6 -> 0.1 | L14: =J14*(1+K14) -> 0
B15: Secondaries (distributor roads), subtotal | E15: =SUM(E12:F14) -> 0 | G15: 0.1 | I15: 0.12 | J15: =E15*(1+G15)*(1+I15) -> 0 | K15: =K6 -> 0.1 | L15: =J15*(1+K15) -> 0
B16: Tertiaries (access and local roads), basic standard | C16: 200 | D16: =Q!F5 -> 0 | E16: =C16*D16 -> 0 | G16: =G19 -> 0.1 | I16: =I19 -> 0.12 | J16: =E16*(1+G16)*(1+I16) -> 0 | K16: =K6 -> 0.1 | L16: =J16*(1+K16) -> 0
B17: Connections to lots on tertiaries | C17: 350 | D17: =SUM(Q!X23:X25) -> 0 | E17: =C17*D17 -> 0 | G17: =G19 -> 0.1 | I17: =I19 -> 0.12 | J17: =E17*(1+G17)*(1+I17) -> 0 | K17: =K6 -> 0.1 | L17: =J17*(1+K17) -> 0
A18: Connections to off-grid clusters, 1st | B18: on tertiaries | C18: 500 | D18: =Q!C47 -> 0 | E18: =C18*D18 -> 0 | G18: =G19 -> 0.1 | I18: =I19 -> 0.12 | J18: =E18*(1+G18)*(1+I18) -> 0 | K18: =K6 -> 0.1 | L18: =J18*(1+K18) -> 0
B19: Tertiaries (access and local roads), subtotal | E19: =SUM(E16:F18) -> 0 | G19: 0.1 | I19: 0.12 | J19: =E19*(1+G19)*(1+I19) -> 0 | K19: =K6 -> 0.1 | L19: =J19*(1+K19) -> 0
B20: Public network costs (w/o connections), subtotal | E20: =E11+E15+E19 -> 0 | J20: =J11+J15+J19 -> 0 | K20: =K6 -> 0.1 | L20: =J20*(1+K20) -> 0 | P20: =L20/D4 -> #DIV/0!
B22: City-scale public open spaces | D22: =Q!H37 -> 0 | E22: =C22*D22 -> 0
B23: City-scale amenities | D23: =Q!I37 -> 0 | E23: =C23*D23 -> 0
B24: District-scale public open spaces | D24: =Q!J37 -> 0 | E24: =C24*D24 -> 0
B25: District-scale amenities | D25: =Q!K37 -> 0 | E25: =C25*D25 -> 0
B26: Neighborhood-scale public open spaces | C26: 50 | D26: =Q!L32 -> 0 | E26: =C26*D26 -> 0 | G26: =G29 -> 0.1 | I26: =I29 -> 0.12 | J26: =E26*(1+G26)*(1+I26) -> 0 | K26: =K6 -> 0.1 | L26: =J26*(1+K26) -> 0
B27: Neighborhood-scale public amenities | C27: total lot area: | D27: =Q!M32 -> 0 | E27: =D4*25000 -> 0 | G27: =G29 -> 0.1 | I27: =I29 -> 0.12 | J27: =E27*(1+G27)*(1+I27) -> 0 | K27: =K6 -> 0.1 | L27: =J27*(1+K27) -> 0
B28: Other public items, if any | E28: 0 | G28: =G29 -> 0.1 | I28: =I29 -> 0.12 | J28: =E28*(1+G28)*(1+I28) -> 0 | K28: =K6 -> 0.1 | L28: =J28*(1+K28) -> 0
B29: Public spaces costs, subtotal | E29: =SUM(E22:F28) -> 0 | G29: 0.1 | I29: 0.12 | J29: =E29*(1+G29)*(1+I29) -> 0 | K29: =K6 -> 0.1 | L29: =J29*(1+K29) -> 0 | P29: =L29/D4 -> #DIV/0!
B31: Total cost (base year) | E31: =E6+E20+E29 -> 0 | J31: =J6+J20+J29 -> 0 | K31: =L31/J31-1 -> #DIV/0! | L31: =L6+L20+L29 -> 0 | P31: =L31/D4 -> #DIV/0!
A33: Spot costing | L33: these rows can be hidden
A34: Spot costing is applicable to all lands: i.e. both private and public lands.
B35: by location (in color code) | C35: net area (a) (partitions only) | D35: public area (a) (partitions only) | E35: land costs | G35: public network costs | I35: public space costs | J35: total costs
B36: Total cost to be recovered (amount) | E36: ='2neighborhood'!L6 -> 0 | G36: ='2neighborhood'!L20 -> 0 | I36: ='2neighborhood'!L29 -> 0 | J36: =SUM(E36:I36) -> 0
B37: ...per gross area | C37: =SUM(C42:D42) -> 0 | E37: =E36/C37 -> #DIV/0! | G37: =G36/C37 -> #DIV/0! | I37: =I36/C37 -> #DIV/0! | J37: =J36/C37 -> #DIV/0!
B38: Land on arteries | C38: =Q!Q18 -> 0 | D38: =Q!Q33 -> 0 | E38: =(C38+D38)*E37/C38 -> #DIV/0! | G38: ='2neighborhood'!L11/C38 -> #DIV/0! | I38: =(C38+D38)*I37/C38 -> #DIV/0! | J38: =SUM(E38:I38) -> #DIV/0!
B39: Land on secondaries | C39: =Q!Q22 -> 0 | D39: =Q!Q34 -> 0 | E39: =(C39+D39)*E37/C39 -> #DIV/0! | G39: ='2neighborhood'!L15/C39 -> #DIV/0! | I39: =(C39+D39)*I37/C39 -> #DIV/0! | J39: =SUM(E39:I39) -> #DIV/0!
B40: Land on local roads | C40: =Q!Q25 -> 0 | D40: =Q!Q35 -> 0 | E40: =(C40+D40)*E37/C40 -> #DIV/0! | G40: ='2neighborhood'!L19/C40 -> #DIV/0! | I40: =(C40+D40)*I37/C40 -> #DIV/0! | J40: =SUM(E40:I40) -> #DIV/0!
B41: Land in off-grid clusters | C41: =Q!Q31 -> 0 | E41: =(C41+D41)*E37/C41 -> #DIV/0! | I41: =(C41+D41)*I37/C41 -> #DIV/0! | J41: =SUM(E41:I41) -> #DIV/0!
B42: Subtotal or average | C42: =SUM(C38:C41) -> 0 | D42: =SUM(D38:D41) -> 0 | E42: =(E38*C38+E39*C39+E40*C40+E41*C41)/C42 -> #DIV/0! | G42: =(G38*C38+G39*C39+G40*C40+G41*C41)/C42 -> #DIV/0! | I42: =(I38*C38+I39*C39+I40*C40+I41*C41)/C42 -> #DIV/0! | J42: =(J38*C38+J39*C39+J40*C40+J41*C41)/C42 -> #DIV/0!
B43: Cost recovered (amount) | E43: =E42*C42 -> #DIV/0! | G43: =G42*C42 -> #DIV/0! | I43: =I42*C42 -> #DIV/0! | J43: =J42*C42 -> #DIV/0!
A44: ="@Matt: for spot costing - possible to allocate higher share of city/district/local public spaces to different locations" -> @Matt: for spot costing - possible to allocate higher share of city/district/local public spaces to different locations
A46: Revenues from serviced land, after differential pricing by location, permitted use and density
A47: In this section, please estimate the market value of lands, depending on location, public infrastructure standard, and access
A48: Please note, this section does not categorize how much the government needs to pay for public lands; instead it quantifies the value (or opportunity cost) of lands carved out for public use.
A49: (Whether or not (and, if so, how much) is to be paid for public lands is decided in the stakeholder spreadsheet, distributing costs and benefits of the projects amongst stakeholders equitably.)
B50: Private land by location (in color code) | C50: typical land uses | E50: FAR | F50: differential pricing of private land | H50: value- over- cost ratio | I50: public lands carved out area (a) | J50: public lands carved out value ≠ revenue | K50: private lands area (a) | L50: private land value ≈ revenue | N50: Land area as share of total serviced area | O50: Land value or revenue as share of total revenue
A51: First, please determine the market value of all on-grid lots on public roads…
B52: Artery x artery (corner) | C52: XL offices | E52: =Q!AM14 -> 0 | F52: 125 | H52: =F52/J38-1 -> #DIV/0! | I52: =Q!N14 -> 0 | J52: =F52*I52 -> 0 | K52: =Q!O14 -> 0 | L52: =F52*K52 -> 0 | N52: =K52/K85 -> #DIV/0! | O52: =L52/L85 -> #DIV/0!
B53: Artery x secondary (corner) | C53: L offices | E53: =Q!AM15 -> 0 | F53: 110 | H53: =F53/J38-1 -> #DIV/0! | I53: =Q!N15 -> 0 | J53: =F53*I53 -> 0 | K53: =Q!O15 -> 0 | L53: =F53*K53 -> 0 | N53: =K53/K85 -> #DIV/0! | O53: =L53/L85 -> #DIV/0!
B54: Artery x tertiary (corner) | C54: M retail, offices, residential | E54: =Q!AM16 -> 0 | F54: 100 | H54: =F54/J38-1 -> #DIV/0! | I54: =Q!N16 -> 0 | J54: =F54*I54 -> 0 | K54: =Q!O16 -> 0 | L54: =F54*K54 -> 0 | N54: =K54/K85 -> #DIV/0! | O54: =L54/L85 -> #DIV/0!
B55: Artery (regular) | C55: M retail, offices, residential | E55: =Q!AM17 -> 0 | F55: 90 | H55: =F55/J38-1 -> #DIV/0! | I55: =Q!N17 -> 0 | J55: =F55*I55 -> 0 | K55: =Q!O17 -> 0 | L55: =F55*K55 -> 0 | N55: =K55/K85 -> #DIV/0! | O55: =L55/L85 -> #DIV/0!
B56: Land on arteries, average/subtotal | E56: =(E52*SUM(K52,I52)+E53*SUM(K53,I53)+E54*SUM(K54,I54)+E55*SUM(K55,I55))/SUM(K56,I56) -> #DIV/0! | F56: =L56/K56 -> #DIV/0! | H56: =F56/J38-1 -> #DIV/0! | I56: =Q!N18 -> 0 | J56: =SUM(J52:J55) -> 0 | K56: =Q!O18 -> 0 | L56: =SUM(L52:L55) -> 0 | N56: =K56/K85 -> #DIV/0! | O56: =L56/L85 -> #DIV/0!
B57: Secondary x secondary (corner) | C57: L retail, offices, residential | E57: =Q!AM19 -> 0 | F57: 85 | H57: =F57/J39-1 -> #DIV/0! | I57: =Q!N19 -> 0 | J57: =F57*I57 -> 0 | K57: =Q!O19 -> 0 | L57: =F57*K57 -> 0 | N57: =K57/K85 -> #DIV/0! | O57: =L57/L85 -> #DIV/0!
B58: Secondary x tertiary (corner) | C58: M retail, offices, residential | E58: =Q!AM20 -> 0 | F58: 75 | H58: =F58/J39-1 -> #DIV/0! | I58: =Q!N20 -> 0 | J58: =F58*I58 -> 0 | K58: =Q!O20 -> 0 | L58: =F58*K58 -> 0 | N58: =K58/K85 -> #DIV/0! | O58: =L58/L85 -> #DIV/0!
B59: Secondary (regular) | C59: SM retail, offices, residential | E59: =Q!AM21 -> 0 | F59: 65 | H59: =F59/J39-1 -> #DIV/0! | I59: =Q!N21 -> 0 | J59: =F59*I59 -> 0 | K59: =Q!O21 -> 0 | L59: =F59*K59 -> 0 | N59: =K59/K85 -> #DIV/0! | O59: =L59/L85 -> #DIV/0!
B60: Land on secondaries, average/subtotal | E60: =(E57*SUM(K57,I57)+E58*SUM(K58,I58)+E59*SUM(K59,I59))/SUM(K60,I60) -> #DIV/0! | F60: =L60/K60 -> #DIV/0! | H60: =F60/J39-1 -> #DIV/0! | I60: =Q!N22 -> 0 | J60: =SUM(J57:J59) -> 0 | K60: =Q!O22 -> 0 | L60: =SUM(L57:L59) -> 0 | N60: =K60/K85 -> #DIV/0! | O60: =L60/L85 -> #DIV/0!
B61: Tertiary x tertiary (corner) | C61: S commercial, manufacturing, residential | E61: =Q!AM23 -> 0 | F61: 60 | H61: =F61/J40-1 -> #DIV/0! | I61: =Q!N23 -> 0 | J61: =F61*I61 -> 0 | K61: =Q!O23 -> 0 | L61: =F61*K61 -> 0 | N61: =K61/K85 -> #DIV/0! | O61: =L61/L85 -> #DIV/0!
B62: Tertiary (regular) | C62: M commercial, manufacturing, residential | E62: =Q!AM24 -> 0 | F62: 50 | H62: =F62/J40-1 -> #DIV/0! | I62: =Q!N24 -> 0 | J62: =F62*I62 -> 0 | K62: =Q!O24 -> 0 | L62: =F62*K62 -> 0 | N62: =K62/K85 -> #DIV/0! | O62: =L62/L85 -> #DIV/0!
B63: Land on local roads, average/subtotal | E63: =(E61*SUM(K61,I61)+E62*SUM(K62,I62))/SUM(K63,I63) -> #DIV/0! | F63: =L63/K63 -> #DIV/0! | H63: =F63/J40-1 -> #DIV/0! | I63: =Q!N25 -> 0 | J63: =SUM(J61:J62) -> 0 | K63: =Q!O25 -> 0 | L63: =SUM(L61:L62) -> 0 | N63: =K63/K85 -> #DIV/0! | O63: =L63/L85 -> #DIV/0!
A64: Second, please determine the market value of lots in off-grid clusters. Off-grid clusters are areas in-side urban blocks, requiring private services that connect to public roads… | P64: preview, for calibration: | R64: forecast for off-grid lots with collective (semi-private) services. (Final prices should be lower than that of on-grid lots above…)
A65: ='2neighborhood'!J41 -> #DIV/0! | F65: non-serviced price | P65: serviced cluster price | Q65: fin. efficiency (c)
A66: 1st level off-grid cluster, connecting to: | B66: arteries | C66: MSME services | E66: =Q!AM26 -> 0 | F66: 30 | H66: =F66/J41-1 -> #DIV/0! | I66: =Q!N26 -> 0 | J66: =F66*I66 -> 0 | K66: =Q!O26 -> 0 | L66: =F66*K66 -> 0 | N66: =K66/K85 -> #DIV/0! | O66: =L66/L85 -> #DIV/0! | P66: =IF('3cluster_artery'!B3=0,"n/a",'3cluster_artery'!G23) -> n/a | Q66: =IF('3cluster_artery'!B3=0,"n/a",'3cluster_artery'!H23) -> n/a
A67: 1st level off-grid cluster, connecting to: | B67: secondaries | C67: MSME manufacturing | E67: =Q!AM27 -> 0 | F67: 20 | H67: =F67/J41-1 -> #DIV/0! | I67: =Q!N27 -> 0 | J67: =F67*I67 -> 0 | K67: =Q!O27 -> 0 | L67: =F67*K67 -> 0 | N67: =K67/K85 -> #DIV/0! | O67: =L67/L85 -> #DIV/0! | P67: =IF('3cluster_secondary'!B3=0,"n/a",'3cluster_secondary'!G23) -> n/a | Q67: =IF('3cluster_secondary'!B3=0,"n/a",'3cluster_secondary'!H23) -> n/a
B68: 1st level off-grid cluster, connecting to local roads | C68: Small-scale livelihoods, residential | E68: =Q!AM28 -> 0 | F68: 15 | H68: =F68/J41-1 -> #DIV/0! | I68: =Q!N28+Q!N29 -> 0 | J68: =F68*I68 -> 0 | K68: =Q!O28+Q!O29 -> 0 | L68: =F68*K68 -> 0 | N68: =K68/K85 -> #DIV/0! | O68: =L68/L85 -> #DIV/0! | P68: =IF('3lcluster_local'!B3=0,"n/a",'3lcluster_local'!G23) -> n/a | Q68: =IF('3lcluster_local'!B3=0,"n/a",'3lcluster_local'!H23) -> n/a
A69: Third, please determine the market value of lots in 2nd-level off-grid clusters. These are clusters that are accessible only through other off-grid clusters (i.e. without direct connection to a public road)…
B70: 2nd-level off-grid cluster, connected through 1st level | C70: Small-scale livelihoods, residential | E70: =Q!AM30 -> 0 | F70: 10 | H70: =F70/J41-1 -> #DIV/0! | I70: =Q!N30 -> 0 | J70: =F70*I70 -> 0 | K70: =Q!O30 -> 0 | L70: =F70*K70 -> 0 | N70: =K70/K85 -> #DIV/0! | O70: =L70/L85 -> #DIV/0! | P70: =IF('3lcluster_local_2level'!B3=0,"n/a",'3lcluster_local_2level'!G44) -> n/a | Q70: =IF('3lcluster_local_2level'!B3=0,"n/a",'3lcluster_local_2level'!H44) -> n/a
B71: Off-grid partitions, average/subtotal | E71: =(E66*SUM(K66,I66)+E67*SUM(K67,I67)+E68*SUM(K68,I68)+E70*SUM(K70,I70))/SUM(K71,I71) -> #DIV/0! | F71: =L71/K71 -> #DIV/0! | H71: =F71/J41-1 -> #DIV/0! | I71: =Q!N31 -> 0 | J71: =SUM(J66:J70) -> 0 | K71: =Q!O31 -> 0 | L71: =SUM(L66:L70) -> 0 | N71: =K71/K85 -> #DIV/0! | O71: =L71/L85 -> #DIV/0!
B73: Private lands, value ≈ revenue | E73: =(E52*K52+E56*K56+E59*K59+E67*K67)/K73 -> #DIV/0! | F73: =L73/K73 -> #DIV/0! | K73: =SUM(K51:K72)/2 -> 0 | L73: =SUM(L51:L72)/2 -> 0 | N73: =K73/K85 -> #DIV/0! | O73: =L73/L85 -> #DIV/0!
A75: Now, determine the collectable revenue from private lands, optionally budgeting a contingency to hedge against market risks (if not priced in above)… | J75: contingency buffer, if any: | K75: 0.05 | L75: =-K75*L73 -> 0
B76: Private lands, revenue | L76: =SUM(L73,L75) -> 0 | N76: =N73 -> #DIV/0! | O76: =L76/L85 -> #DIV/0!
B78: Public lands, value ≠ revenue | E78: =(E56*I56+E60*I60+E63*I63+E71*I71)/I78 -> #DIV/0! | F78: =J78/I78 -> #DIV/0! | I78: =SUM(I51:I72)/2 -> 0 | J78: =SUM(J51:J72)/2 -> 0 | N78: =I78/K85 -> #DIV/0! | O78: =J78/L85 -> #DIV/0!
A79: Finally, determine the collectable revenue from public lands, if any, considering land value sharing…
B80: Neighborhood-scale public open spaces | F80: 10 | I80: =Q!L32 -> 0 | J80: =F80*I80 -> 0 | N80: =I80/K85 -> #DIV/0! | O80: =J80/L85 -> #DIV/0!
B81: Neighborhood-scale public amenities | F81: 10 | I81: =Q!M32 -> 0 | J81: =F81*I81 -> 0 | N81: =I81/K85 -> #DIV/0! | O81: =J81/L85 -> #DIV/0!
B82: Public lands, revenue | I82: =J82/J78 -> #DIV/0! | J82: =SUM(J80:J81) -> 0 | L82: =J82 -> 0 | N82: =N78 -> #DIV/0! | O82: =J82/L85 -> #DIV/0!
H83: opportunity cost of public lands (foregone revenue = land value sharing): | I83: =-J83/J78 -> #DIV/0! | J83: =J82-J78 -> 0
B85: Serviced land, average/total | K85: =K73+I78 -> 0 | L85: =SUM(J82,L76) -> 0 | N85: =K85/K85 -> #DIV/0! | O85: =L85/L85 -> #DIV/0! | P85: =L85/D4 -> #DIV/0!
B87: Base-year surplus (loss) | L87: =L85-L31 -> 0 | P87: =L87/D4 -> #DIV/0!
B88: Financial efficiency | L88: =L87/L31 -> #DIV/0!
A91: Notes:
A92: user input in the financial model
A93: (0) aggregates for all landowners (allows manual input or data transfer from the '1site' sheet)
A94: (1) from the city scale model
A95: (a) from the spatial model
A96: (b) the spot costing model considers location specific infrastructure and land costs. Particularly, it considers that off-grid areas do not consume public networks (while they share costs for public open spaces and amenities).
A97: (c) profit margin: market value relative to base year cost
C101: entries for land use zoning dropdown menu
C102: XXL offices
C103: XL offices
C104: L retail, offices, residential
C105: M retail, offices, residential
C106: SM retail, offices, residential
C107: S commercial, manufacturing, residential
C108: M commercial, manufacturing, residential
C109: MSME services
C110: MSME manufacturing
C111: =C112 -> Small-scale livelihoods, residential
C112: Small-scale livelihoods, residential
C113: Other
B115: street-based revenues (e.g. natural markets)
B116: other

Sheet 3cluster_artery
A1: Off-grid clusters on arteries: development of semi-private / collective lands
A3: Off-grid clusters on arteries… | B3: =Q!C45 -> 0 | C3: hide sheet if value is zero
A5: Costs, land & site development | B5: unit cost | C5: quantity (a) | D5: hard cost | E5: physical contingency | F5: design & management | G5: base-year cost before interest | H5: interest cost | I5: total cost (base year)
A6: Single-level cluster…
A7: On-grid frontage/access path (2) | B7: ='2neighborhood'!F55 -> 90 | C7: =Q!G45 -> 0 | D7: =B7*C7 -> 0 | E7: =E8 -> 0 | F7: =F8 -> 0.05 | G7: =D7*(1+E7)*(1+F7) -> 0 | H7: =H10 -> 0.1 | I7: =G7*(1+H7) -> 0
A8: less cost shared with on-grid lots (x) | B8: 0.5 | D8: =-D7*B8 -> 0 | E8: =E9 -> 0 | F8: =F9 -> 0.05 | G8: =D8*(1+E8)*(1+F8) -> 0 | H8: =H10 -> 0.1 | I8: =G8*(1+H8) -> 0
A9: Off-grid partitions (2) | B9: ='2neighborhood'!F66 -> 30 | C9: =Q!O26 -> 0 | D9: =B9*C9 -> 0 | E9: =E10 -> 0 | F9: =F10 -> 0.05 | G9: =D9*(1+E9)*(1+F9) -> 0 | H9: =H10 -> 0.1 | I9: =G9*(1+H9) -> 0
A10: Land-related costs, subtotal | D10: =SUM(D7:D9) -> 0 | E10: 0 | F10: 0.05 | G10: =D10*(1+E10)*(1+F10) -> 0 | H10: 0.1 | I10: =G10*(1+H10) -> 0 | K10: =I10/SUM(C6:C10)*10000 -> #DIV/0!
A11: Semi-private (collective) network | B11: 500 | C11: =Q!D45 -> 0 | D11: =B11*C11 -> 0 | E11: =E12 -> 0.1 | F11: =F12 -> 0.12 | G11: =D11*(1+E11)*(1+F11) -> 0 | H11: =H10 -> 0.1 | I11: =G11*(1+H11) -> 0
A12: Connections to individual subpartitions (lots) | B12: 200 | C12: =Q!X26 -> 0 | D12: =B12*C12 -> 0 | E12: =E13 -> 0.1 | F12: =F13 -> 0.12 | G12: =D12*(1+E12)*(1+F12) -> 0 | H12: =H10 -> 0.1 | I12: =G12*(1+H12) -> 0
A13: Semi-private (collective) open spaces | B13: 20 | C13: =Q!I45 -> 0 | D13: =B13*C13 -> 0 | E13: =E14 -> 0.1 | F13: =F14 -> 0.12 | G13: =D13*(1+E13)*(1+F13) -> 0 | H13: =H10 -> 0.1 | I13: =G13*(1+H13) -> 0
A14: Semi-private (collective) amenities | C14: e.g. community hall | D14: 0 | E14: =E15 -> 0.1 | F14: =F15 -> 0.12 | G14: =D14*(1+E14)*(1+F14) -> 0 | H14: =H10 -> 0.1 | I14: =G14*(1+H14) -> 0
A15: Other semi-private (collective) items, if any | D15: 0 | E15: =E16 -> 0.1 | F15: =F16 -> 0.12 | G15: =D15*(1+E15)*(1+F15) -> 0 | H15: =H10 -> 0.1 | I15: =G15*(1+H15) -> 0
A16: Semi-private (collective) development, subtotal | D16: =SUM(D11:D15) -> 0 | E16: 0.1 | F16: 0.12 | G16: =D16*(1+E16)*(1+F16) -> 0 | H16: =H10 -> 0.1 | I16: =G16*(1+H16) -> 0 | K16: =I16/SUM(C6:C10)*10000 -> #DIV/0!
A17: Cost, total | D17: =D16+D10 -> 0 | G17: =G16+G10 -> 0 | I17: =I16+I10 -> 0 | K17: =I17/SUM(C6:C10)*10000 -> #DIV/0!
A19: Revenues, by location (in color code) | B19: area (a) | C19: typical land uses | F19: FAR | G19: differential price | H19: profit (c) | I19: revenue
A20: Single-level cluster…
A21: semi-private (collective) spaces (a) | B21: =Q!H45+Q!I45 -> 0 | C21: shared circulation, open spaces, and amenities
A22: =IF(B23=0,0,I17/B23) -> 0
A23: revenue generating private lots (a) | B23: =C9-B21 -> 0 | C23: ='2neighborhood'!C66 -> MSME services | F23: =Q!AM26 -> 0 | G23: 60 | H23: =IF(B23=0,0,IF(I17=0,0,G23/(I17/B23)-1)) -> 0 | I23: =G23*B23 -> 0 | K23: =I23/SUM(C6:C10)*10000 -> #DIV/0!
A24: Semi-private (collective) amenities | C24: e.g. from community facilities | I24: 0
A25: Other, if any | C25: e.g. from community facilities | I25: 0 | K25: =I25/SUM(C6:C10)*10000 -> #DIV/0!
A26: Revenue, total | D26: =D23+D15 -> 0 | H26: =H23 -> 0 | I26: =SUM(I21:I25) -> 0 | K26: =I26/SUM(C6:C10)*10000 -> #DIV/0!
A28: Base-year surplus (loss) | H28: revenues from (or 'value of') serviced land less cost for land, infrastructure and services | I28: =I26-I17 -> 0 | K28: =I28/SUM(C6:C10)*10000 -> #DIV/0!
H29: Financial efficiency | I29: =IF(I17=0,0,I28/I17) -> 0
A33: Notes
A34: user input in the financial model
A35: (2) pricing from the neighborhood scale model
A36: (a) from the spatial model
A37: (c) profit margin over base year cost
A38: (x) costs may be shared with on-grid lots in case of duplicate use, such as entrances that also serve the back of the on-grid lot or that allow a bridge building on top of a gate, or access paths that only consume setbacks / side margins between on-grid buildings.
A40: ="@Matt, question is whether the access area of the on-grid partition needs to be charged to the off-grid. Presumably not (fully) if it also services the backside of the on-grid and/or serves as distance between on-grid buildings..." -> @Matt, question is whether the access area of the on-grid partition needs to be charged to the off-grid. Presumably not (fully) if it also services the backside of the on-grid and/or serves as distance between on-grid buildings...
A41: ="@Daniel, Hide sheet if value in B3 is zero." -> @Daniel, Hide sheet if value in B3 is zero.

Sheet 3cluster_secondary
A1: Off-grid clusters on secondaries: development of semi-private / collective lands
A3: Off-grid clusters on secondaries… | B3: =Q!C46 -> 0
A5: Costs, land & site development | B5: unit cost | C5: quantity (a) | D5: hard cost | E5: physical contingency | F5: design & management | G5: base-year cost before interest | H5: interest cost | I5: total cost (base year)
A6: Single-level cluster…
A7: On-grid frontage/access path (2) | B7: ='2neighborhood'!F59 -> 65 | C7: =Q!G46 -> 0 | D7: =B7*C7 -> 0 | E7: =E8 -> 0 | F7: =F8 -> 0.05 | G7: =D7*(1+E7)*(1+F7) -> 0 | H7: =H10 -> 0.1 | I7: =G7*(1+H7) -> 0
A8: less cost shared with on-grid lots (x) | B8: 0.5 | D8: =-D7*B8 -> 0 | E8: =E9 -> 0 | F8: =F9 -> 0.05 | G8: =D8*(1+E8)*(1+F8) -> 0 | H8: =H10 -> 0.1 | I8: =G8*(1+H8) -> 0
A9: Off-grid partitions (2) | B9: ='2neighborhood'!F67 -> 20 | C9: =Q!O27 -> 0 | D9: =B9*C9 -> 0 | E9: =E10 -> 0 | F9: =F10 -> 0.05 | G9: =D9*(1+E9)*(1+F9) -> 0 | H9: =H10 -> 0.1 | I9: =G9*(1+H9) -> 0
A10: Land-related costs, subtotal | D10: =SUM(D7:D9) -> 0 | E10: ='3cluster_artery'!E10 -> 0 | F10: ='3cluster_artery'!F10 -> 0.05 | G10: =D10*(1+E10)*(1+F10) -> 0 | H10: 0.1 | I10: =G10*(1+H10) -> 0
A11: Semi-private (collective) network | B11: 500 | C11: =Q!D46 -> 0 | D11: =B11*C11 -> 0 | E11: =E12 -> 0.1 | F11: =F12 -> 0.12 | G11: =D11*(1+E11)*(1+F11) -> 0 | H11: =H10 -> 0.1 | I11: =G11*(1+H11) -> 0
A12: Connections to individual subpartitions (lots) | B12: 180 | C12: =Q!X27 -> 0 | D12: =B12*C12 -> 0 | E12: =E13 -> 0.1 | F12: =F13 -> 0.12 | G12: =D12*(1+E12)*(1+F12) -> 0 | H12: =H10 -> 0.1 | I12: =G12*(1+H12) -> 0
A13: Semi-private (collective) open spaces | B13: 15 | C13: =Q!I46 -> 0 | D13: =B13*C13 -> 0 | E13: =E14 -> 0.1 | F13: =F14 -> 0.12 | G13: =D13*(1+E13)*(1+F13) -> 0 | H13: =H10 -> 0.1 | I13: =G13*(1+H13) -> 0
A14: Semi-private (collective) amenities | C14: e.g. community hall | D14: 0 | E14: =E15 -> 0.1 | F14: =F15 -> 0.12 | G14: =D14*(1+E14)*(1+F14) -> 0 | H14: =H10 -> 0.1 | I14: =G14*(1+H14) -> 0
A15: Other semi-private (collective) items, if any | D15: 0 | E15: =E16 -> 0.1 | F15: =F16 -> 0.12 | G15: =D15*(1+E15)*(1+F15) -> 0 | H15: =H10 -> 0.1 | I15: =G15*(1+H15) -> 0
A16: Semi-private (collective) development, subtotal | D16: =SUM(D11:D15) -> 0 | E16: ='3cluster_artery'!E16 -> 0.1 | F16: ='3cluster_artery'!F16 -> 0.12 | G16: =D16*(1+E16)*(1+F16) -> 0 | H16: =H10 -> 0.1 | I16: =G16*(1+H16) -> 0
A17: Cost, total | D17: =D16+D10 -> 0 | G17: =G16+G10 -> 0 | I17: =I16+I10 -> 0
A19: Revenues, by location (in color code) | B19: area (a) | C19: typical land uses | F19: FAR | G19: differential price | H19: differential profit (c) | I19: revenue
A20: Single-level cluster…
A21: semi-private (collective) spaces (a) | B21: =Q!H46+Q!I46 -> 0 | C21: shared circulation, open spaces, and amenities
A22: =IF(B23=0,0,I17/B23) -> 0
A23: revenue generating private lots (a) | B23: =C9-B21 -> 0 | C23: ='2neighborhood'!C67 -> MSME manufacturing | F23: =Q!AM27 -> 0 | G23: 48 | H23: =IF(B23=0,0,IF(I17=0,0,G23/(I17/B23)-1)) -> 0 | I23: =G23*B23 -> 0
A24: Semi-private (collective) amenities | C24: e.g. from community facilities | I24: 0
A25: Other, if any | C25: e.g. from community facilities | I25: 0
A26: Revenue, total | D26: =D23+D15 -> 0 | H26: =H23 -> 0 | I26: =SUM(I21:I25) -> 0
A28: Base-year surplus (loss) | H28: revenues from (or 'value of') serviced land less cost for land, infrastructure and services | I28: =I26-I17 -> 0
H29: Financial efficiency | I29: =IF(I17=0,0,I28/I17) -> 0
A33: Notes
A34: user input in the financial model
A35: (2) pricing from the neighborhood scale model
A36: (a) from the spatial model
A37: (c) profit margin over base year cost
A38: (x) costs may be shared with on-grid lots in case of duplicate use, such as entrances that also serve the back of the on-grid lot or that allow a bridge building on top of a gate, or access paths that only consume setbacks / side margins between on-grid buildings.
A40: ="@Matt, question is whether the access area of the on-grid partition needs to be charged to the off-grid. Presumably not (fully) if it also services the backside of the on-grid and/or serves as distance between on-grid buildings..." -> @Matt, question is whether the access area of the on-grid partition needs to be charged to the off-grid. Presumably not (fully) if it also services the backside of the on-grid and/or serves as distance between on-grid buildings...
A41: ="@Daniel, Hide sheet if value in B3 is zero." -> @Daniel, Hide sheet if value in B3 is zero.
A69: Notes
A70: user input in the financial model
A71: (a) from the spatial model
A72: (2) pricing from the neighborhood scale model
A73: (x) costs may be shared with adjacent on-grid lots, e.g. in case of double use, such as entrances that also serve the back of the on-grid lot or that allow a bridge building on top of a gate, or access paths that only consume setbacks / side margins between on-grid buildings.
A75: ="@Matt, question is whether the access area of the on-grid partition needs to be charged to the off-grid. Presumably not (fully) if it also services the backside of the on-grid and/or serves as distance between on-grid buildings..." -> @Matt, question is whether the access area of the on-grid partition needs to be charged to the off-grid. Presumably not (fully) if it also services the backside of the on-grid and/or serves as distance between on-grid buildings...
A78: Revenues from individual serviced lots in off-grid clusters. | J78: imputed value for calibration (x)
A84: Notes
A85: user input in the financial model
A86: column H: profit input is Retorn on Investment (ROI)
A87: (a) from the spatial model
A88: (b) from the spot costing model
A89: (x) after phasing, price contingencies and cost of finance (preview of budget results, with current settings)
A91: ="@Matt, for FAR use permitted vs. viable FAR calculated from the spatial model? Only consider private lands for this calculation to calibrate opportunity costs of public lands..." -> @Matt, for FAR use permitted vs. viable FAR calculated from the spatial model? Only consider private lands for this calculation to calibrate opportunity costs of public lands...

Sheet 3lcluster_local
A1: Off-grid clusters on local roads: development of semi-private / collective lands
A3: Single-level clusters on local roads… | B3: =Q!C47 -> 0
A5: Costs, land & site development | B5: unit cost | C5: quantity (a) | D5: hard cost | E5: physical contingency | F5: design & management | G5: base-year cost before interest | H5: interest cost | I5: total cost (base year)
A6: Single-level cluster…
A7: On-grid frontage/access path (2) | B7: ='2neighborhood'!F62 -> 50 | C7: =Q!G47 -> 0 | D7: =B7*C7 -> 0 | E7: =E8 -> 0 | F7: =F8 -> 0 | G7: =D7*(1+E7)*(1+F7) -> 0 | H7: =H10 -> 0.1 | I7: =G7*(1+H7) -> 0
A8: less cost shared with on-grid lots (x) | B8: ='3lcluster_local_2level'!B8 -> 0.5 | D8: =-D7*B8 -> 0 | E8: =E9 -> 0 | F8: =F9 -> 0 | G8: =D8*(1+E8)*(1+F8) -> 0 | H8: =H10 -> 0.1 | I8: =G8*(1+H8) -> 0
A9: Off-grid partitions, 1st (2) | B9: ='2neighborhood'!F68 -> 15 | C9: =Q!O28 -> 0 | D9: =B9*C9 -> 0 | E9: =E10 -> 0 | F9: =F10 -> 0 | G9: =D9*(1+E9)*(1+F9) -> 0 | H9: =H10 -> 0.1 | I9: =G9*(1+H9) -> 0
A10: Land-related costs, subtotal | D10: =SUM(D7:D9) -> 0 | E10: ='3lcluster_local_2level'!E10 -> 0 | F10: ='3lcluster_local_2level'!F10 -> 0 | G10: =D10*(1+E10)*(1+F10) -> 0 | H10: 0.1 | I10: =G10*(1+H10) -> 0
A11: Semi-private (collective) network | B11: ='3lcluster_local_2level'!B11 -> 150 | C11: =Q!D47 -> 0 | D11: =B11*C11 -> 0 | E11: =E12 -> 0.05 | F11: =F12 -> 0.1 | G11: =D11*(1+E11)*(1+F11) -> 0 | H11: =H10 -> 0.1 | I11: =G11*(1+H11) -> 0
A12: Connections to individual subpartitions (lots) | B12: ='3lcluster_local_2level'!B12 -> 300 | C12: =Q!X28 -> 0 | D12: =B12*C12 -> 0 | E12: =E13 -> 0.05 | F12: =F13 -> 0.1 | G12: =D12*(1+E12)*(1+F12) -> 0 | H12: =H10 -> 0.1 | I12: =G12*(1+H12) -> 0
A13: Semi-private (collective) open spaces | B13: ='3lcluster_local_2level'!B13 -> 20 | C13: =Q!I47 -> 0 | D13: =B13*C13 -> 0 | E13: =E14 -> 0.05 | F13: =F14 -> 0.1 | G13: =D13*(1+E13)*(1+F13) -> 0 | H13: =H10 -> 0.1 | I13: =G13*(1+H13) -> 0
A14: Semi-private (collective) amenities | C14: e.g. community hall | D14: ='3lcluster_local_2level'!D14 -> 0 | E14: =E15 -> 0.05 | F14: =F15 -> 0.1 | G14: =D14*(1+E14)*(1+F14) -> 0 | H14: =H10 -> 0.1 | I14: =G14*(1+H14) -> 0
A15: Other semi-private (collective) items, if any | D15: ='3lcluster_local_2level'!D15 -> 0 | E15: =E16 -> 0.05 | F15: =F16 -> 0.1 | G15: =D15*(1+E15)*(1+F15) -> 0 | H15: =H10 -> 0.1 | I15: =G15*(1+H15) -> 0
A16: Semi-private (collective) development, subtotal | D16: =SUM(D11:D15) -> 0 | E16: ='3lcluster_local_2level'!E16 -> 0.05 | F16: ='3lcluster_local_2level'!F16 -> 0.1 | G16: =D16*(1+E16)*(1+F16) -> 0 | H16: =H10 -> 0.1 | I16: =G16*(1+H16) -> 0
A17: Cost, total | 1 cluster | D17: =D16+D10 -> 0 | G17: =G16+G10 -> 0 | I17: =I16+I10 -> 0
A19: Revenues, by location (in color code) | B19: area (a) | C19: typical land uses | F19: FAR | G19: differential price | H19: profit (c) | I19: revenue
A20: Single-level cluster…
A21: semi-private (collective) spaces (a) | B21: =(Q!H47+Q!I47) -> 0 | C21: Shared circulation, open spaces, and amenities
A22: =IF(B23=0,0,I17/B23) -> 0
A23: revenue generating private lots (a) | B23: =C9-B21 -> 0 | C23: ='2neighborhood'!C68 -> Small-scale livelihoods, residential | F23: =Q!AM28 -> 0 | G23: 45 | H23: =IF(B23=0,0,IF(I17=0,0,G23/(I17/B23)-1)) -> 0 | I23: =G23*B23 -> 0
A24: Semi-private (collective) amenities | C24: e.g. from community facilities | I24: ='3lcluster_local_2level'!I38 -> 0
A25: Other, if any | I25: ='3lcluster_local_2level'!I39 -> 0
A26: Revenue, total | 1 cluster | D26: =D23+D15 -> 0 | H26: =H23 -> 0 | I26: =SUM(I21:I25) -> 0
A28: Base-year surplus (loss), 1 cluster | H28: revenues from (or 'value of') serviced land less cost for land, infrastructure and services | I28: =I26-I17 -> 0
H29: Financial efficiency | I29: =IF(I17=0,0,I28/I17) -> 0
A32: Notes
A33: user input in the financial model
A34: (a) from the spatial model
A35: (b) from the spot costing model
A36: (c) profit margin: market value relative to base year cost (Retorn on Investment (ROI))
A37: (x) after phasing, price contingencies and cost of finance (preview of budget results, with current settings)
A39: ="@Matt, for FAR use permitted vs. viable FAR calculated from the spatial model? Only consider private lands for this calculation to calibrate opportunity costs of public lands..." -> @Matt, for FAR use permitted vs. viable FAR calculated from the spatial model? Only consider private lands for this calculation to calibrate opportunity costs of public lands...

Sheet 3lcluster_local_2level
A1: Off-grid clusters on local roads: development of semi-private / collective lands
A3: Multi-level clusters on local roads | B3: =Q!C48 -> 0
A5: Costs, land & site development | B5: unit cost | C5: quantity (a) | D5: hard cost | E5: physical contingency | F5: design & management | G5: base-year cost before interest | H5: interest cost | I5: total cost (base year)
A6: 2-level cluster: 1st level (light blue)…
A7: On-grid frontage/access path (2) | B7: ='2neighborhood'!F62 -> 50 | C7: =Q!G48 -> 0 | D7: =B7*C7 -> 0 | E7: =E8 -> 0 | F7: =F8 -> 0 | G7: =D7*(1+E7)*(1+F7) -> 0 | H7: =H10 -> 0.1 | I7: =G7*(1+H7) -> 0
A8: less cost shared with on-grid lots (x) | B8: 0.5 | D8: =-D7*B8 -> 0 | E8: =E9 -> 0 | F8: =F9 -> 0 | G8: =D8*(1+E8)*(1+F8) -> 0 | H8: =H10 -> 0.1 | I8: =G8*(1+H8) -> 0
A9: Off-grid partitions, 1st level (2) | B9: ='2neighborhood'!F68 -> 15 | C9: =Q!O29 -> 0 | D9: =B9*C9 -> 0 | E9: =E10 -> 0 | F9: =F10 -> 0 | G9: =D9*(1+E9)*(1+F9) -> 0 | H9: =H10 -> 0.1 | I9: =G9*(1+H9) -> 0
A10: 1st level cluster: land-related costs, subtotal | D10: =SUM(D7:D9) -> 0 | E10: 0 | F10: 0 | G10: =D10*(1+E10)*(1+F10) -> 0 | H10: 0.1 | I10: =G10*(1+H10) -> 0
A11: Semi-private (collective) network | B11: 150 | C11: =Q!D48 -> 0 | D11: =B11*C11 -> 0 | E11: =E12 -> 0.05 | F11: =F12 -> 0.1 | G11: =D11*(1+E11)*(1+F11) -> 0 | H11: =H10 -> 0.1 | I11: =G11*(1+H11) -> 0
A12: Connections to individual subpartitions (lots) | B12: 300 | C12: =Q!X29 -> 0 | D12: =B12*C12 -> 0 | E12: =E13 -> 0.05 | F12: =F13 -> 0.1 | G12: =D12*(1+E12)*(1+F12) -> 0 | H12: =H10 -> 0.1 | I12: =G12*(1+H12) -> 0
A13: Semi-private (collective) open spaces | B13: 20 | C13: =Q!I48 -> 0 | D13: =B13*C13 -> 0 | E13: =E14 -> 0.05 | F13: =F14 -> 0.1 | G13: =D13*(1+E13)*(1+F13) -> 0 | H13: =H10 -> 0.1 | I13: =G13*(1+H13) -> 0
A14: Semi-private (collective) amenities | C14: e.g. community hall | D14: 0 | E14: =E15 -> 0.05 | F14: =F15 -> 0.1 | G14: =D14*(1+E14)*(1+F14) -> 0 | H14: =H10 -> 0.1 | I14: =G14*(1+H14) -> 0
A15: Other semi-private (collective) items, if any | D15: 0 | E15: =E16 -> 0.05 | F15: =F16 -> 0.1 | G15: =D15*(1+E15)*(1+F15) -> 0 | H15: =H10 -> 0.1 | I15: =G15*(1+H15) -> 0
A16: Semi-private (collective) development, subtotal | D16: =SUM(D11:D15) -> 0 | E16: 0.05 | F16: 0.1 | G16: =D16*(1+E16)*(1+F16) -> 0 | H16: =H10 -> 0.1 | I16: =G16*(1+H16) -> 0
A17: 1st level cluster: costs, subtotal | D17: =D16+D9 -> 0 | G17: =G16+G10 -> 0 | I17: =I16+I10 -> 0
A19: 2-level cluster: 2nd level (dark blue)…
A20: Off-grid partitions, 2nd level (2) | B20: ='2neighborhood'!F70 -> 10 | C20: =Q!O30 -> 0 | D20: =B20*C20 -> 0 | E20: =E21 -> 0 | F20: =F21 -> 0 | G20: =D20*(1+E20)*(1+F20) -> 0 | H20: =H10 -> 0.1 | I20: =G20*(1+H20) -> 0
A21: Connections to 1st level off-grid cluster | B21: 0 | C21: =Q!C49 -> 0 | D21: =B21*C21 -> 0 | E21: =E22 -> 0 | F21: =F22 -> 0 | G21: =D21*(1+E21)*(1+F21) -> 0 | H21: =H10 -> 0.1 | I21: =G21*(1+H21) -> 0
A22: 2nd level cluster: land-related costs, subtotal | D22: =SUM(D20:D21) -> 0 | E22: 0 | F22: 0 | G22: =D22*(1+E22)*(1+F22) -> 0 | H22: =H10 -> 0.1 | I22: =G22*(1+H22) -> 0
A23: Semi-private (collective) network | B23: 150 | C23: =Q!D49 -> 0 | D23: =B23*C23 -> 0 | E23: =E24 -> 0.05 | F23: =F24 -> 0.1 | G23: =D23*(1+E23)*(1+F23) -> 0 | H23: =H10 -> 0.1 | I23: =G23*(1+H23) -> 0
A24: Connections to individual subpartitions (lots) | B24: 150 | C24: =Q!X30 -> 0 | D24: =B24*C24 -> 0 | E24: =E25 -> 0.05 | F24: =F25 -> 0.1 | G24: =D24*(1+E24)*(1+F24) -> 0 | H24: =H10 -> 0.1 | I24: =G24*(1+H24) -> 0
A25: Semi-private (collective) open spaces | B25: 20 | C25: =Q!I49 -> 0 | D25: =B25*C25 -> 0 | E25: =E26 -> 0.05 | F25: =F26 -> 0.1 | G25: =D25*(1+E25)*(1+F25) -> 0 | H25: =H10 -> 0.1 | I25: =G25*(1+H25) -> 0
A26: Semi-private (collective) amenities | C26: e.g. community hall | D26: 0 | E26: =E27 -> 0.05 | F26: =F27 -> 0.1 | G26: =D26*(1+E26)*(1+F26) -> 0 | H26: =H10 -> 0.1 | I26: =G26*(1+H26) -> 0
A27: Other semi-private (collective) items, if any | D27: 0 | E27: =E28 -> 0.05 | F27: =F28 -> 0.1 | G27: =D27*(1+E27)*(1+F27) -> 0 | H27: =H10 -> 0.1 | I27: =G27*(1+H27) -> 0
A28: Semi-private (collective) development, subtotal | D28: =SUM(D23:D27) -> 0 | E28: 0.05 | F28: 0.1 | G28: =D28*(1+E28)*(1+F28) -> 0 | H28: =H10 -> 0.1 | I28: =G28*(1+H28) -> 0
A29: 2nd level cluster: costs, subtotal | D29: =D28+D22 -> 0 | G29: =G28+G22 -> 0 | I29: =I28+I22 -> 0
A31: total cost | D31: =D29+D17 -> 0 | G31: =G29+G17 -> 0 | I31: =I29+I17 -> 0
A33: Private land by location (in color code) | B33: area | C33: typical land uses | F33: FAR | G33: differential price | H33: differential profit | I33: revenue
A34: 2-level cluster: 1st level (light blue)…
A35: semi-private (collective) spaces, 1st level (a) | B35: =Q!H48+Q!I48 -> 0 | C35: shared circulation, open spaces, and amenities
A36: =IF(B37=0,0,I17/B37) -> 0
A37: revenue generating private lots, 1st level (a) | B37: =C9-'3lcluster_local_2level'!B35 -> 0 | C37: ='2neighborhood'!C68 -> Small-scale livelihoods, residential | F37: =Q!AM29 -> 0 | G37: 40 | H37: =IF(B37=0,0,IF(I17=0,0,G37/(I17/B37)-1)) -> 0 | I37: =G37*B37 -> 0
A38: Semi-private (collective) amenities | C38: e.g. from community facilities | I38: 0
A39: Other, if any | I39: 0
A41: 2-level cluster: 2nd level (dark blue)…
A42: semi-private (collective) spaces, 2nd level (a) | B42: =Q!H49+Q!I49 -> 0 | C42: shared circulation, open spaces, and amenities
A43: =IF(B44=0,0,I29/B44) -> 0
A44: revenue generating private lots, 2nd level (a) | B44: =C20-B42 -> 0 | C44: ='2neighborhood'!C70 -> Small-scale livelihoods, residential | F44: =Q!AM30 -> 0 | G44: 25 | H44: =IF(B44=0,0,IF(I29=0,0,G44/(I29/B44)-1)) -> 0 | I44: =G44*B44 -> 0
A45: Semi-private (collective) amenities | C45: e.g. from community facilities | I45: 0
A46: Other, if any | I46: 0
A47: Totals | B47: =SUM(B37:B44) -> 0 | D47: =D44+D27 -> 0 | H47: =IF(I31=0,0,I47/I31-1) -> 0 | I47: =SUM(I35:I46) -> 0
A49: Base-year surplus (loss) | H49: revenues from (or 'value of') serviced land less cost for land, infrastructure and services | I49: =I47-I29-I17 -> 0
H50: Financial efficiency | I50: =IF(I31=0,0,I49/I31) -> 0
A54: Notes
A55: user input in the financial model
A56: (a) from the spatial model
A57: (2) pricing from the neighborhood scale model
A58: (x) costs may be shared with on-grid lots in case of duplicate use, such as entrances that also serve the back of the on-grid lot or that allow a bridge building on top of a gate, or access paths that only consume setbacks / side margins between on-grid buildings.
A60: ="@Matt, question is whether the access area of the on-grid partition needs to be charged to the off-grid. Presumably not (fully) if it also services the backside of the on-grid and/or serves as distance between on-grid buildings..." -> @Matt, question is whether the access area of the on-grid partition needs to be charged to the off-grid. Presumably not (fully) if it also services the backside of the on-grid and/or serves as distance between on-grid buildings...

Sheet 4buildings
A1: Starter building model
A2: Location, by color code | B2: Artery x artery (corner) | C2: Artery x secondary (corner) | D2: Artery x tertiary (corner) | E2: Artery (regular) | F2: Artery (cluster access) | G2: Off-grid cluster (on arteries) | H2: Secondary x secondary (corner) | I2: Secondary x tertiary (corner) | J2: Secondary (regular) | K2: Secondary (cluster access) | L2: Off-grid cluster (secondaries) | M2: Tertiary x tertiary (corner) | N2: Tertiary (regular) | O2: Tertiary (cluster access) | P2: Off-grid cluster (simple) | Q2: 2-level cluster (1st level) | R2: 2-level cluster (2nd level)
A3: COSTS
A4: Lot definition & land cost…
A5: Total private area (for all lots), by location | B5: =Q!O14 -> 0 | C5: =Q!O15 -> 0 | D5: =Q!O16 -> 0 | E5: =IF(SUM(Q!X17:X18)=0,0,Q!O17*Q!X17/SUM(Q!X17:X18)) -> 0 | F5: =IF(SUM(Q!X17:X18)=0,0,Q!O17*Q!X18/SUM(Q!X17:X18)) -> 0 | G5: ='3cluster_artery'!B23 -> 0 | H5: =Q!O19 -> 0 | I5: =Q!O20 -> 0 | J5: =IF(SUM(Q!X21:X22)=0,0,Q!O21*Q!X21/SUM(Q!X21:X22)) -> 0 | K5: =IF(SUM(Q!X21:X22)=0,0,Q!O21*Q!X22/SUM(Q!X21:X22)) -> 0 | L5: ='3cluster_secondary'!B23 -> 0 | M5: =Q!O23 -> 0 | N5: =IF(SUM(Q!X24:X25)=0,0,Q!O24*Q!X24/SUM(Q!X24:X25)) -> 0 | O5: =IF(SUM(Q!X24:X25)=0,0,Q!O24*Q!X25/SUM(Q!X24:X25)) -> 0 | P5: ='3lcluster_local'!B23 -> 0 | Q5: ='3lcluster_local_2level'!B37 -> 0 | R5: ='3lcluster_local_2level'!B44 -> 0
A6: Land price | F6: =E13 -> 90 | K6: =J13 -> 65 | O6: =N13 -> 50
A7: Total land price, by location | F7: =F6*F5 -> 0 | K7: =K6*K5 -> 0 | O7: =O6*O5 -> 0
A8: less cost sharing with off-grid | F8: =-SUM('3cluster_artery'!D7:D8) -> 0 | K8: =-SUM('3cluster_secondary'!D7:D8) -> 0 | O8: =-SUM('3lcluster_local'!D7:D8)*'3lcluster_local'!B3 -> 0
A9: Land cost (adjusted for cluster's contribution, if applicable) | F9: =SUM(F7:F8) -> 0 | K9: =SUM(K7:K8) -> 0 | O9: =SUM(O7:O8) -> 0
A10: Number of lots (a) | B10: =Q!X14 -> 0 | C10: =Q!X15 -> 0 | D10: =Q!X16 -> 0 | E10: =Q!X17 -> 0 | F10: =Q!X18 -> 0 | G10: =Q!X26 -> 0 | H10: =Q!X19 -> 0 | I10: =Q!X20 -> 0 | J10: =Q!X21 -> 0 | K10: =Q!X22 -> 0 | L10: =Q!X27 -> 0 | M10: =Q!X23 -> 0 | N10: =Q!X24 -> 0 | O10: =Q!X25 -> 0 | P10: =Q!X28 -> 0 | Q10: =Q!X29 -> 0 | R10: =Q!X30 -> 0
A11: Average lot size (a) | B11: =IF(B10=0,0,B5/B10) -> 0 | C11: =IF(C10=0,0,C5/C10) -> 0 | D11: =IF(D10=0,0,D5/D10) -> 0 | E11: =IF(E10=0,0,E5/E10) -> 0 | F11: =IF(F10=0,0,F5/F10) -> 0 | G11: =IF(G10=0,0,G5/G10) -> 0 | H11: =IF(H10=0,0,H5/H10) -> 0 | I11: =IF(I10=0,0,I5/I10) -> 0 | ... R11: =IF(R10=0,0,R5/R10) -> 0
A12: Idealized lot size | B12: =Q!AA14 -> 0 | C12: =Q!AA15 -> 0 | D12: =Q!AA16 -> 0 | E12: =Q!AA17 -> 0 | F12: =Q!AA18 -> 0 | G12: =Q!AA26 -> 0 | H12: =Q!AA19 -> 0 | I12: =Q!AA20 -> 0 | J12: =Q!AA21 -> 0 | K12: =Q!AA22 -> 0 | L12: =Q!AA27 -> 0 | M12: =Q!AA23 -> 0 | N12: =Q!AA24 -> 0 | O12: =Q!AA25 -> 0 | P12: =Q!AA28 -> 0 | Q12: =Q!AA29 -> 0 | R12: =Q!AA30 -> 0
A13: Land cost | B13: ='2neighborhood'!F52 -> 125 | C13: ='2neighborhood'!F53 -> 110 | D13: ='2neighborhood'!F54 -> 100 | E13: ='2neighborhood'!F55 -> 90 | F13: =IF(F5=0,0,F9/F5) -> 0 | G13: ='3cluster_artery'!G23 -> 60 | H13: ='2neighborhood'!F57 -> 85 | I13: ='2neighborhood'!F58 -> 75 | J13: ='2neighborhood'!F59 -> 65 | K13: =IF(K5=0,0,K9/K5) -> 0 | L13: ='3cluster_secondary'!G23 -> 48 | M13: ='2neighborhood'!F61 -> 60 | N13: ='2neighborhood'!F62 -> 50 | O13: =IF(O5=0,0,O9/O5) -> 0 | P13: ='3lcluster_local'!G23 -> 45 | Q13: ='3lcluster_local_2level'!G37 -> 40 | R13: ='3lcluster_local_2level'!G44 -> 25
A14: Land acquisition cost, per lot | B14: =B12*B13 -> 0 | C14: =C12*C13 -> 0 | D14: =D12*D13 -> 0 | E14: =E12*E13 -> 0 | F14: =F12*F13 -> 0 | G14: =G12*G13 -> 0 | H14: =H12*H13 -> 0 | I14: =I12*I13 -> 0 | ... R14: =R12*R13 -> 0
A15: Physical contingency | B15: 0 | C15: =B15 -> 0 | D15: =B15 -> 0 | E15: =B15 -> 0 | F15: =B15 -> 0 | G15: 0 | H15: 0 | I15: =H15 -> 0 | J15: =H15 -> 0 | K15: =H15 -> 0 | L15: 0 | M15: 0 | N15: =M15 -> 0 | O15: =M15 -> 0 | P15: 0 | Q15: =P15 -> 0 | R15: =P15 -> 0
A16: Design and management | B16: 0 | C16: =B16 -> 0 | D16: =B16 -> 0 | E16: =B16 -> 0 | F16: =B16 -> 0 | G16: 0 | H16: 0 | I16: =H16 -> 0 | J16: =H16 -> 0 | K16: =H16 -> 0 | L16: 0.01 | M16: 0.02 | N16: =M16 -> 0.02 | O16: =M16 -> 0.02 | P16: 0 | Q16: =P16 -> 0 | R16: =P16 -> 0
A17: Land cost, base-year before interest | B17: =B14*(1+B15)*(1+B16) -> 0 | C17: =C14*(1+C15)*(1+C16) -> 0 | D17: =D14*(1+D15)*(1+D16) -> 0 | E17: =E14*(1+E15)*(1+E16) -> 0 | F17: =F14*(1+F15)*(1+F16) -> 0 | G17: =G14*(1+G15)*(1+G16) -> 0 | H17: =H14*(1+H15)*(1+H16) -> 0 | I17: =I14*(1+I15)*(1+I16) -> 0 | ... R17: =R14*(1+R15)*(1+R16) -> 0
A19: Starter building definition & cost…
A20: Starter type | B20: ='4buildings'!C20 -> lot only | C20: lot only | D20: lot only | E20: mixed-use building | F20: =E20 -> mixed-use building | G20: lot only | H20: lot only | I20: lot only | J20: mixed-use building | K20: =J20 -> mixed-use building | L20: lot only | M20: apartments | N20: shell | O20: =N20 -> shell | P20: core | Q20: core | R20: roof
A21: Starter description | M21: 4-story aparment building with ground floor commercial and 4 units on each of the 3 upper floors | N21: 2-story shell (loft) without interior walls and slabs: open space for user-driven infill, foundation for up to 3 floors | O21: same, as left | P21: 1-story core home, basic 1 room initially, incl. utility/wet core, for horizontal and vertical expansion (in back yard and up to 3 floors) | Q21: 1-story core home, 2.5 rooms initially, incl. utility/wet core, for horizontal and vertical expansion (in back yard and up to 3 floors) | R21: starter roof: only foundation, frame, roof slab, utility/wet core; for 1 "room", initially. Can be expanded as much the core. Difference: no walls, windows, etc – which are all done by the user…
A22: Idealized starter building floor area, if any (a) | B22: =IF(B5=0,0,Q!AU14) -> 0 | C22: =IF(C5=0,0,Q!AU15) -> 0 | D22: =IF(D5=0,0,Q!AU16) -> 0 | E22: =IF(E5=0,0,Q!AU17) -> 0 | F22: =IF(F5=0,0,Q!AU18) -> 0 | G22: =IF(G5=0,0,Q!AU26) -> 0 | H22: =IF(H5=0,0,Q!AU19) -> 0 | I22: =IF(I5=0,0,Q!AU20) -> 0 | J22: =IF(J5=0,0,Q!AU21) -> 0 | K22: =IF(K5=0,0,Q!AU22) -> 0 | L22: =IF(L5=0,0,Q!AU27) -> 0 | M22: =IF(M5=0,0,Q!AU23) -> 0 | N22: =IF(N5=0,0,Q!AU24) -> 0 | O22: =IF(O5=0,0,Q!AU25) -> 0 | P22: =IF(P5=0,0,Q!AU28) -> 0 | Q22: =IF(Q5=0,0,Q!AU29) -> 0 | R22: =IF(R5=0,0,Q!AU30) -> 0
A23: portion of floor space to be selfbuilt by household (infill of slab in case of shells, only) | B23: 0 | C23: 0 | D23: 0 | E23: 0 | F23: 0 | G23: 0 | H23: 0 | I23: 0 | J23: 0 | K23: 0 | L23: 0 | M23: 0 | N23: 0.5 | O23: 0.5 | P23: 0 | Q23: 0 | R23: 0
A24: Assumed starter building floor area, if any (a) | B24: =B22*(1-B23) -> 0 | C24: =C22*(1-C23) -> 0 | D24: =D22*(1-D23) -> 0 | E24: =E22*(1-E23) -> 0 | F24: =F22*(1-F23) -> 0 | G24: =G22*(1-G23) -> 0 | H24: =H22*(1-H23) -> 0 | I24: =I22*(1-I23) -> 0 | ... R24: =R22*(1-R23) -> 0
A25: Construction unit cost, charged by builder as per above specifications | B25: 0 | C25: 300 | D25: 250 | E25: 200 | F25: 200 | G25: 150 | H25: 225 | I25: 200 | J25: 180 | K25: 180 | L25: 120 | M25: 280 | N25: 240 | O25: 240 | P25: 200 | Q25: 200 | R25: 150
A26: Construction hard cost, subtotal | B26: =B24*B25 -> 0 | C26: =C24*C25 -> 0 | D26: =D24*D25 -> 0 | E26: =E24*E25 -> 0 | F26: =F24*F25 -> 0 | G26: =G24*G25 -> 0 | H26: =H24*H25 -> 0 | I26: =I24*I25 -> 0 | ... R26: =R24*R25 -> 0
A27: Physical contingency | B27: 0.05 | C27: =B27 -> 0.05 | D27: =B27 -> 0.05 | E27: =B27 -> 0.05 | F27: =B27 -> 0.05 | G27: 0.05 | H27: =G27 -> 0.05 | I27: =H27 -> 0.05 | J27: =H27 -> 0.05 | K27: =H27 -> 0.05 | L27: 0.05 | M27: =L27 -> 0.05 | N27: =M27 -> 0.05 | O27: =M27 -> 0.05 | P27: 0.05 | Q27: =P27 -> 0.05 | R27: =Q27 -> 0.05
A28: Design and management | B28: 0.1 | C28: =B28 -> 0.1 | D28: =B28 -> 0.1 | E28: =B28 -> 0.1 | F28: =B28 -> 0.1 | G28: =M28 -> 0.1 | H28: 0.1 | I28: =H28 -> 0.1 | J28: =H28 -> 0.1 | K28: =H28 -> 0.1 | L28: =M28 -> 0.1 | M28: 0.1 | N28: =M28 -> 0.1 | O28: =M28 -> 0.1 | P28: 0.1 | Q28: =P28 -> 0.1 | R28: =P28 -> 0.1
A29: Construction cost, base-year before interest | B29: =B26*(1+B27)*(1+B28) -> 0 | C29: =C26*(1+C27)*(1+C28) -> 0 | D29: =D26*(1+D27)*(1+D28) -> 0 | E29: =E26*(1+E27)*(1+E28) -> 0 | F29: =F26*(1+F27)*(1+F28) -> 0 | G29: =G26*(1+G27)*(1+G28) -> 0 | H29: =H26*(1+H27)*(1+H28) -> 0 | I29: =I26*(1+I27)*(1+I28) -> 0 | ... R29: =R26*(1+R27)*(1+R28) -> 0
A31: Total cost (serviced land & starter building), base-year before interest | B31: =B29+B17 -> 0 | C31: =C29+C17 -> 0 | D31: =D29+D17 -> 0 | E31: =E29+E17 -> 0 | F31: =F29+F17 -> 0 | G31: =G29+G17 -> 0 | H31: =H29+H17 -> 0 | I31: =I29+I17 -> 0 | ... R31: =R29+R17 -> 0
A32: Interest margin during construction | B32: 0.05 | C32: =B32 -> 0.05 | D32: =B32 -> 0.05 | E32: =B32 -> 0.05 | F32: =B32 -> 0.05 | G32: 0.05 | H32: 0.05 | I32: =H32 -> 0.05 | J32: =H32 -> 0.05 | K32: =H32 -> 0.05 | L32: 0.05 | M32: 0.05 | N32: =M32 -> 0.05 | O32: =M32 -> 0.05 | P32: 0.05 | Q32: =P32 -> 0.05 | R32: =P32 -> 0.05
A33: Total cost (serviced land & starter building), base-year including interest | B33: =B31*(1+B32) -> 0 | C33: =C31*(1+C32) -> 0 | D33: =D31*(1+D32) -> 0 | E33: =E31*(1+E32) -> 0 | F33: =F31*(1+F32) -> 0 | G33: =G31*(1+G32) -> 0 | H33: =H31*(1+H32) -> 0 | I33: =I31*(1+I32) -> 0 | ... R33: =R31*(1+R32) -> 0
A34: Profit margin | B34: 0.15 | C34: =B34 -> 0.15 | D34: =B34 -> 0.15 | E34: =B34 -> 0.15 | F34: =B34 -> 0.15 | G34: 0.15 | H34: 0.15 | I34: =H34 -> 0.15 | J34: =H34 -> 0.15 | K34: =H34 -> 0.15 | L34: 0.15 | M34: 0.15 | N34: =M34 -> 0.15 | O34: =M34 -> 0.15 | P34: 0 | Q34: =P34 -> 0 | R34: =P34 -> 0
A35: Total cost (serviced land & starter building), base-year | B35: =B33*(1+B34) -> 0 | C35: =C33*(1+C34) -> 0 | D35: =D33*(1+D34) -> 0 | E35: =E33*(1+E34) -> 0 | F35: =F33*(1+F34) -> 0 | G35: =G33*(1+G34) -> 0 | H35: =H33*(1+H34) -> 0 | I35: =I33*(1+I34) -> 0 | ... R35: =R33*(1+R34) -> 0
A37: REVENUES
A38: Differenting commercial and residential floor space, as applicable…
A39: total floor area | B39: =B24 -> 0 | C39: =C24 -> 0 | D39: =D24 -> 0 | E39: =E24 -> 0 | F39: =F24 -> 0 | G39: =G24 -> 0 | H39: =H24 -> 0 | I39: =I24 -> 0 | ... R39: =R24 -> 0
A40: less non-revenue-generating floor area (e.g. shared staircases, corridors) | B40: 0.25 | C40: 0.25 | D40: 0.25 | E40: 0.25 | F40: 0.25 | G40: 0 | H40: 0.25 | I40: 0.25 | J40: 0.25 | K40: 0.25 | L40: 0 | M40: 0.25 | N40: 0 | O40: 0 | P40: 0 | Q40: 0 | R40: 0
A41: non-revenue-generating floor space | B41: =B39*B40 -> 0 | C41: =C39*C40 -> 0 | D41: =D39*D40 -> 0 | E41: =E39*E40 -> 0 | F41: =F39*F40 -> 0 | G41: =G39*G40 -> 0 | H41: =H39*H40 -> 0 | I41: =I39*I40 -> 0 | ... R41: =R39*R40 -> 0
A42: revenue-generating floor area | B42: =B39-B41 -> 0 | C42: =C39-C41 -> 0 | D42: =D39-D41 -> 0 | E42: =E39-E41 -> 0 | F42: =F39-F41 -> 0 | G42: =G39-G41 -> 0 | H42: =H39-H41 -> 0 | I42: =I39-I41 -> 0 | ... R42: =R39-R41 -> 0
A43: non-residential as share of revenue generating floor area (e.g. ground floor commercial), if any | B43: 1 | C43: 0.5 | D43: 0.3 | E43: 0.2 | F43: =E43 -> 0.2 | G43: 0 | H43: 0.25 | I43: 0.25 | J43: 0.25 | K43: 0.25 | L43: 0 | M43: 0.25 | N43: 0 | O43: 0 | P43: 0 | Q43: 0 | R43: 0
A44: non-residential revenue-generating floor space | B44: =B42*B43 -> 0 | C44: =C42*C43 -> 0 | D44: =D42*D43 -> 0 | E44: =E42*E43 -> 0 | F44: =F42*F43 -> 0 | G44: =G42*G43 -> 0 | H44: =H42*H43 -> 0 | I44: =I42*I43 -> 0 | ... R44: =R42*R43 -> 0
A45: revenue from non-residential (e.g. ground floor commercial), if any | B45: 1500 | C45: 1200 | D45: 1000 | E45: 900 | F45: =E45 -> 900 | G45: 700 | H45: 1000 | I45: 800 | J45: 700 | K45: 700 | L45: 600 | M45: 700 | N45: 600 | O45: 600 | P45: 450 | Q45: 450 | R45: 400
A46: non-residential revenue (e.g. commercial) | B46: =B45*B44 -> 0 | C46: =C45*C44 -> 0 | D46: =D45*D44 -> 0 | E46: =E45*E44 -> 0 | F46: =F45*F44 -> 0 | G46: =G45*G44 -> 0 | H46: =H45*H44 -> 0 | I46: =I45*I44 -> 0 | ... R46: =R45*R44 -> 0
A48: required revenue from residential, remaining | B48: =IF(B39=0,0,B35-B46) -> 0 | C48: =IF(C39=0,0,C35-C46) -> 0 | D48: =IF(D39=0,0,D35-D46) -> 0 | E48: =IF(E39=0,0,E35-E46) -> 0 | F48: =IF(F39=0,0,F35-F46) -> 0 | G48: =IF(G39=0,0,G35-G46) -> 0 | H48: =IF(H39=0,0,H35-H46) -> 0 | I48: =IF(I39=0,0,I35-I46) -> 0 | ... R48: =IF(R39=0,0,R35-R46) -> 0
A49: residential floor area | B49: =B42-B44 -> 0 | C49: =C42-C44 -> 0 | D49: =D42-D44 -> 0 | E49: =E42-E44 -> 0 | F49: =F42-F44 -> 0 | G49: =G42-G44 -> 0 | H49: =H42-H44 -> 0 | I49: =I42-I44 -> 0 | ... R49: =R42-R44 -> 0
A50: starter dwellings, price per residential floor area | B50: =IF(B49=0,0,B48/B49) -> 0 | C50: =IF(C49=0,0,C48/C49) -> 0 | D50: =IF(D49=0,0,D48/D49) -> 0 | E50: =IF(E49=0,0,E48/E49) -> 0 | F50: =IF(F49=0,0,F48/F49) -> 0 | G50: =IF(G49=0,0,G48/G49) -> 0 | H50: =IF(H49=0,0,H48/H49) -> 0 | I50: =IF(I49=0,0,I48/I49) -> 0 | ... R50: =IF(R49=0,0,R48/R49) -> 0
A52: Notes
A53: (a) from the spatial model

Sheet 5dwellings
A1: Starter dwellings model
A2: Location, by color code | B2: Artery x artery (corner) | C2: Artery x secondary (corner) | D2: Artery x tertiary (corner) | E2: Artery (regular) | F2: Artery (cluster access) | G2: Off-grid cluster (on arteries) | H2: Secondary x secondary (corner) | I2: Secondary x tertiary (corner) | J2: Secondary (regular) | K2: Secondary (cluster access) | L2: Off-grid cluster (secondaries) | M2: Tertiary x tertiary (corner) | N2: Tertiary (regular) | O2: Tertiary (cluster access) | P2: Off-grid cluster (simple) | Q2: 2-level cluster (1st level) | R2: 2-level cluster (2nd level)
A3: ='4buildings'!A20 -> Starter type | B3: ='4buildings'!B20 -> lot only | C3: ='4buildings'!C20 -> lot only | D3: ='4buildings'!D20 -> lot only | E3: ='4buildings'!E20 -> mixed-use building | F3: ='4buildings'!F20 -> mixed-use building | G3: ='4buildings'!G20 -> lot only | H3: ='4buildings'!H20 -> lot only | ... R3: ='4buildings'!R20 -> roof
A4: ='4buildings'!A21 -> Starter description | B4: ='4buildings'!B21 -> 0 | C4: ='4buildings'!C21 -> 0 | D4: ='4buildings'!D21 -> 0 | E4: ='4buildings'!E21 -> 0 | F4: ='4buildings'!F21 -> 0 | G4: ='4buildings'!G21 -> 0 | H4: ='4buildings'!H21 -> 0 | ... R4: ='4buildings'!R21 -> starter roof: only foundation, frame, roof slab, utility/wet core; for 1 "room", initially. Can be expanded as much the core. Difference: no walls, windows, etc – which are all done by the user…
A5: Idealized lot size | B5: ='4buildings'!B12 -> 0 | C5: ='4buildings'!C12 -> 0 | D5: ='4buildings'!D12 -> 0 | E5: ='4buildings'!E12 -> 0 | F5: ='4buildings'!F12 -> 0 | G5: ='4buildings'!G12 -> 0 | H5: ='4buildings'!H12 -> 0 | I5: ='4buildings'!I12 -> 0 | ... R5: ='4buildings'!R12 -> 0
A6: ='4buildings'!A20 -> Starter type | B6: ='4buildings'!B20 -> lot only | C6: ='4buildings'!C20 -> lot only | D6: ='4buildings'!D20 -> lot only | E6: ='4buildings'!E20 -> mixed-use building | F6: ='4buildings'!F20 -> mixed-use building | G6: ='4buildings'!G20 -> lot only | H6: ='4buildings'!H20 -> lot only | ... R6: ='4buildings'!R20 -> roof
A7: ='4buildings'!A22 -> Idealized starter building floor area, if any (a) | B7: ='4buildings'!B24 -> 0 | C7: ='4buildings'!C24 -> 0 | D7: ='4buildings'!D24 -> 0 | E7: ='4buildings'!E24 -> 0 | F7: ='4buildings'!F24 -> 0 | G7: ='4buildings'!G24 -> 0 | H7: ='4buildings'!H24 -> 0 | I7: ='4buildings'!I24 -> 0 | ... R7: ='4buildings'!R24 -> 0
A8: thereof, revenue-generating residential floor space | B8: ='4buildings'!B49 -> 0 | C8: ='4buildings'!C49 -> 0 | D8: ='4buildings'!D49 -> 0 | E8: ='4buildings'!E49 -> 0 | F8: ='4buildings'!F49 -> 0 | G8: ='4buildings'!G49 -> 0 | H8: ='4buildings'!H49 -> 0 | I8: ='4buildings'!I49 -> 0 | ... R8: ='4buildings'!R49 -> 0
A10: residential units: main dwellings (owned) per lot, initial | B10: =ROUND(B7/50,0) -> 0 | C10: =ROUND(C7/50,0) -> 0 | D10: =ROUND(D7/50,0) -> 0 | E10: =ROUND(E7/50,0) -> 0 | F10: =E10 -> 0 | G10: 0 | H10: =ROUND(H7/40,0) -> 0 | I10: =ROUND(I7/40,0) -> 0 | J10: =ROUND(J7/40,0) -> 0 | K10: =J10 -> 0 | L10: 0 | M10: 12 | N10: 1 | O10: 1 | P10: 1 | Q10: 1 | R10: 1
A11: starter dwelling main units (owned), average gross area | B11: =IF(B10=0,0,B8/B10) -> 0 | C11: =IF(C10=0,0,C8/C10) -> 0 | D11: =IF(D10=0,0,D8/D10) -> 0 | E11: =IF(E10=0,0,E8/E10) -> 0 | F11: =IF(F10=0,0,F8/F10) -> 0 | G11: =IF(G10=0,0,G8/G10) -> 0 | H11: =IF(H10=0,0,H8/H10) -> 0 | I11: =IF(I10=0,0,I8/I10) -> 0 | ... R11: =IF(R10=0,0,R8/R10) -> 0
A12: starter dwelling main unit, average price | B12: =IF(B10=0,0,'4buildings'!B48/B10) -> 0 | C12: =IF(C10=0,0,'4buildings'!C48/C10) -> 0 | D12: =IF(D10=0,0,'4buildings'!D48/D10) -> 0 | E12: =IF(E10=0,0,'4buildings'!E48/E10) -> 0 | F12: =IF(F10=0,0,'4buildings'!F48/F10) -> 0 | G12: =IF(G10=0,0,'4buildings'!G48/G10) -> 0 | H12: =IF(H10=0,0,'4buildings'!H48/H10) -> 0 | I12: =IF(I10=0,0,'4buildings'!I48/I10) -> 0 | ... R12: =IF(R10=0,0,'4buildings'!R48/R10) -> 0
A14: Carving out small-scale private rental (sublets), as applicable – potential win-win for income generation and provision of most affordable dwelling units…
A15: sublet 1, if any (per main dwelling) | B15: 0 | C15: 0 | D15: 0 | E15: 0 | F15: 0 | G15: 0 | H15: 0 | I15: 0 | J15: 0 | K15: 0 | L15: 20 | M15: 0 | N15: 40 | O15: 30 | P15: 9 | Q15: 12 | R15: 6
A16: sublet 2, if any (per main dwelling) | B16: 0 | C16: 0 | D16: 0 | E16: 0 | F16: 0 | G16: 0 | H16: 0 | I16: 0 | J16: 0 | K16: 0 | L16: 0 | M16: 0 | N16: 0 | O16: 24 | P16: 0 | Q16: 0 | R16: 0
A17: remaining area of main dwelling (owned, self-occupied) | B17: =IF(B11=0,0,B11-B15-B16) -> 0 | C17: =IF(C11=0,0,C11-C15-C16) -> 0 | D17: =IF(D11=0,0,D11-D15-D16) -> 0 | E17: =IF(E11=0,0,E11-E15-E16) -> 0 | F17: =IF(F11=0,0,F11-F15-F16) -> 0 | G17: =IF(G11=0,0,G11-G15-G16) -> 0 | H17: =IF(H11=0,0,H11-H15-H16) -> 0 | I17: =IF(I11=0,0,I11-I15-I16) -> 0 | ... R17: =IF(R11=0,0,R11-R15-R16) -> 0
A19: sublet units, per main units | B19: =IF(B11=0,0,COUNTIF(B15:B16,">0")) -> 0 | C19: =IF(C11=0,0,COUNTIF(C15:C16,">0")) -> 0 | D19: =IF(D11=0,0,COUNTIF(D15:D16,">0")) -> 0 | E19: =IF(E11=0,0,COUNTIF(E15:E16,">0")) -> 0 | F19: =IF(F11=0,0,COUNTIF(F15:F16,">0")) -> 0 | G19: =IF(G11=0,0,COUNTIF(G15:G16,">0")) -> 0 | H19: =IF(H11=0,0,COUNTIF(H15:H16,">0")) -> 0 | I19: =IF(I11=0,0,COUNTIF(I15:I16,">0")) -> 0 | ... R19: =IF(R11=0,0,COUNTIF(R15:R16,">0")) -> 0
A20: total number of dwelling units per lot, initial | B20: =B10*(1+B19) -> 0 | C20: =C10*(1+C19) -> 0 | D20: =D10*(1+D19) -> 0 | E20: =E10*(1+E19) -> 0 | F20: =F10*(1+F19) -> 0 | G20: =G10*(1+G19) -> 0 | H20: =H10*(1+H19) -> 0 | I20: =I10*(1+I19) -> 0 | ... R20: =R10*(1+R19) -> 1
A22: Notes
A23: (a) from the spatial model
A25: ="@Matt: include legal and tax costs" -> @Matt: include legal and tax costs

Sheet 5finance
A1: Financing of demand model (part 1/2: ownership)
A2: Location, by color code | B2: Artery x artery (corner) | C2: Artery x secondary (corner) | D2: Artery x tertiary (corner) | E2: Artery (regular) | F2: Artery (cluster access) | G2: Off-grid cluster (on arteries) | H2: Secondary x secondary (corner) | I2: Secondary x tertiary (corner) | J2: Secondary (regular) | K2: Secondary (cluster access) | L2: Off-grid cluster (secondaries) | M2: Tertiary x tertiary (corner) | N2: Tertiary (regular) | O2: Tertiary (cluster access) | P2: Off-grid cluster (simple) | Q2: 2-level cluster (1st level) | R2: 2-level cluster (2nd level)
A3: ='4buildings'!A20 -> Starter type | B3: ='4buildings'!B20 -> lot only | C3: ='4buildings'!C20 -> lot only | D3: ='4buildings'!D20 -> lot only | E3: ='4buildings'!E20 -> mixed-use building | F3: ='4buildings'!F20 -> mixed-use building | G3: ='4buildings'!G20 -> lot only | H3: ='4buildings'!H20 -> lot only | ... R3: ='4buildings'!R20 -> roof
A4: ='5dwellings'!A11 -> starter dwelling main units (owned), average gross area | M4: ='5dwellings'!M11 -> 0 | N4: ='5dwellings'!N11 -> 0 | O4: ='5dwellings'!O11 -> 0 | P4: ='5dwellings'!P11 -> 0 | Q4: ='5dwellings'!Q11 -> 0 | R4: ='5dwellings'!R11 -> 0
A5: Land cost, attributed to 1 main dwelling unit | B5: =IF('4buildings'!B35=0,0,'4buildings'!B17*'5dwellings'!B12/'4buildings'!B35) -> 0 | C5: =IF('4buildings'!C35=0,0,'4buildings'!C17*'5dwellings'!C12/'4buildings'!C35) -> 0 | D5: =IF('4buildings'!D35=0,0,'4buildings'!D17*'5dwellings'!D12/'4buildings'!D35) -> 0 | E5: =IF('4buildings'!E35=0,0,'4buildings'!E17*'5dwellings'!E12/'4buildings'!E35) -> 0 | F5: =IF('4buildings'!F35=0,0,'4buildings'!F17*'5dwellings'!F12/'4buildings'!F35) -> 0 | G5: =IF('4buildings'!G35=0,0,'4buildings'!G17*'5dwellings'!G12/'4buildings'!G35) -> 0 | H5: =IF('4buildings'!H35=0,0,'4buildings'!H17*'5dwellings'!H12/'4buildings'!H35) -> 0 | I5: =IF('4buildings'!I35=0,0,'4buildings'!I17*'5dwellings'!I12/'4buildings'!I35) -> 0 | ... R5: =IF('4buildings'!R35=0,0,'4buildings'!R17*'5dwellings'!R12/'4buildings'!R35) -> 0
A6: Starter unit cost, attributed to 1 main dwelling unit | M6: ='5dwellings'!M12-M5 -> 0 | N6: ='5dwellings'!N12-N5 -> 0 | O6: ='5dwellings'!O12-O5 -> 0 | P6: ='5dwellings'!P12-P5 -> 0 | Q6: ='5dwellings'!Q12-Q5 -> 0 | R6: ='5dwellings'!R12-R5 -> 0
A7: Additional household investment, before move in (if any) | M7: 0 | N7: 0 | O7: 0 | P7: 0 | Q7: 0 | R7: 2000
A8: Total cost, to be financed | M8: =IF(M4=0,0,SUM(M5:M7)) -> 0 | N8: =IF(N4=0,0,SUM(N5:N7)) -> 0 | O8: =IF(O4=0,0,SUM(O5:O7)) -> 0 | P8: =IF(P4=0,0,SUM(P5:P7)) -> 0 | Q8: =IF(Q4=0,0,SUM(Q5:Q7)) -> 0 | R8: =IF(R4=0,0,SUM(R5:R7)) -> 0
A9: Note: dwelling costs to make a starter livable: e.g. to complete any unit with finishings, a shell with internal partition walls/slabs, or a starter roof with perimeter walls.
A10: Note: additional household investment is optional - with labor and materials possibly procured on the informal / second-hand market… In case of potential raw units, it makes the dwelling livable.
A12: Demand-side finance, required for taking units off the balance sheets of developers and builders
A13: Optional: this box allows financing the land with a different instrument (e.g. mortgage, long-term lease) than the construction.
A14: Finance land separately (1=Yes, 0=No) | M14: 0 | N14: 1 | O14: 1 | P14: 1 | Q14: 1 | R14: 1
A15: Land cost to be financed (amount) | M15: =M5*M14 -> 0 | N15: =N5*N14 -> 0 | O15: =O5*O14 -> 0 | P15: =P5*P14 -> 0 | Q15: =Q5*Q14 -> 0 | R15: =R5*R14 -> 0
A16: Financing period, months | M16: 300 | N16: =M16 -> 300 | O16: =M16 -> 300 | P16: =M16 -> 300 | Q16: =M16 -> 300 | R16: =M16 -> 300
A17: nominal interest rate | M17: 0.1 | N17: =M17 -> 0.1 | O17: =M17 -> 0.1 | P17: =M17 -> 0.1 | Q17: =M17 -> 0.1 | R17: =M17 -> 0.1
A18: Note: as land does not depreciate it may be indexed to inflation, possibly. If so, this can be done with the following line.
A19: indexation to inflation / payment growth | M19: 0.025 | N19: =M19 -> 0.025 | O19: =M19 -> 0.025 | P19: =M19 -> 0.025 | Q19: =M19 -> 0.025 | R19: =M19 -> 0.025
A20: real interest rate applied | M20: =M17-M19 -> 0.075 | N20: =N17-N19 -> 0.075 | O20: =O17-O19 -> 0.075 | P20: =P17-P19 -> 0.075 | Q20: =Q17-Q19 -> 0.075 | R20: =R17-R19 -> 0.075
A21: Note: land indexed to inflation may also be financed as a perpetual lease. If so, the following line allows setting the future value to 100% meaning that only interest is paid but no amortization.
A22: amount remaining at the end of the financing period (balloon) | M22: 0 | N22: =M22 -> 0 | O22: =M22 -> 0 | P22: =M22 -> 0 | Q22: =M22 -> 0 | R22: =M22 -> 0
A23: Monthly payment for land (initial) | M23: =-PMT(M20/12,M16,M15,-M22*M15) -> 0 | N23: =-PMT(N20/12,N16,N15,-N22*N15) -> 0 | O23: =-PMT(O20/12,O16,O15,-O22*O15) -> 0 | P23: =-PMT(P20/12,P16,P15,-P22*P15) -> 0 | Q23: =-PMT(Q20/12,Q16,Q15,-Q22*Q15) -> 0 | R23: =-PMT(R20/12,R16,R15,-R22*R15) -> 0
A24: Note: here, the downpayment should be assumed to be zero, given that any downpayment should be allocated to higher-interest instruments (e.g. microloans) to save on interest payments, below.
A25: Note: balloons reduce amortization but require refinancing; to avoid traps, automatically roll over at the end of the period. For a perpetual lease, set the future value to 100% or to financing period to high number of years.
A27: Financial instrument 2: To finance a professionally built and durable structure. This second box allows to use longer-term and lower-interest financial instruments, such as mortgages or leases.
A28: Finance starter dwelling separately (1=Yes, 0=No) | M28: 0 | N28: 0 | O28: 0 | P28: 0 | Q28: 0 | R28: 0
A29: Starter dwelling (support) cost to be financed (amount) | M29: =M6*M28 -> 0 | N29: =N6*N28 -> 0 | O29: =O6*O28 -> 0 | P29: =P6*P28 -> 0 | Q29: =Q6*Q28 -> 0 | R29: =R6*R28 -> 0 | U29: ="@Daniel, if all entries are zero, hide rows marked with a red filling." -> @Daniel, if all entries are zero, hide rows marked with a red filling.
A30: Downpayment, share | M30: 0 | N30: 0 | O30: 0 | P30: 0 | Q30: 0 | R30: 0
A31: …, amount | M31: =M29*M30 -> 0 | N31: =N29*N30 -> 0 | O31: =O29*O30 -> 0 | P31: =P29*P30 -> 0 | Q31: =Q29*Q30 -> 0 | R31: =R29*R30 -> 0
A32: Downpayment/cash subsidy | M32: 0 | N32: 0 | O32: 0 | P32: 0 | Q32: 0 | R32: 0
A33: Amount to be financed | M33: =M29-M31-M32 -> 0 | N33: =N29-N31-N32 -> 0 | O33: =O29-O31-O32 -> 0 | P33: =P29-P31-P32 -> 0 | Q33: =Q29-Q31-Q32 -> 0 | R33: =R29-R31-R32 -> 0
A34: Financing period, months | M34: 240 | N34: 240 | O34: 240 | P34: 120 | Q34: 120 | R34: 120
A35: nominal interest rate charged | M35: 0.12 | N35: 0.12 | O35: 0.12 | P35: 0.12 | Q35: 0.12 | R35: 0.12
A36: indexation to inflation / payment growth | M36: 0 | N36: 0 | O36: 0 | P36: 0 | Q36: 0 | R36: 0
A37: real interst rate applied | M37: =M35-M36 -> 0.12 | N37: =N35-N36 -> 0.12 | O37: =O35-O36 -> 0.12 | P37: =P35-P36 -> 0.12 | Q37: =Q35-Q36 -> 0.12 | R37: =R35-R36 -> 0.12
A38: Monthly payment for starter dwelling, only (initial) | M38: =-PMT(M35/12,M34,M33) -> 0 | N38: =-PMT(N35/12,N34,N33) -> 0 | O38: =-PMT(O35/12,O34,O33) -> 0 | P38: =-PMT(P35/12,P34,P33) -> 0 | Q38: =-PMT(Q35/12,Q34,Q33) -> 0 | R38: =-PMT(R35/12,R34,R33) -> 0
A39: Note: again, the downpayment should be small; instead, downpayments should be allocated to higher-interest instruments (e.g. microloans) to save on interest payments, below.
A40: Note: again, also the subsidy should be small; instead, downpayments should be allocated to higher-interest instruments (e.g. microloans) to save on interest payments, below.
A42: The following box allows using the full range of financial instruments (e.g. long-term mortgages or leases vs. housing microfinance, vs. regular microfinance). Differentiate interest rate and amortization period, depending on loan size, asset durability, perceivd risk – ranging from shorter term and higher rate for microfinance to longer term and lower rate for mortgages and leases...
A43: Remaining cost to be financed (loan amount) | M43: =IF(M4=0,0,M8-M15-M29) -> 0 | N43: =IF(N4=0,0,N8-N15-N29) -> 0 | O43: =IF(O4=0,0,O8-O15-O29) -> 0 | P43: =IF(P4=0,0,P8-P15-P29) -> 0 | Q43: =IF(Q4=0,0,Q8-Q15-Q29) -> 0 | R43: =IF(R4=0,0,R8-R15-R29) -> 0
A44: Downpayment, share | M44: 0.15 | N44: 0.15 | O44: 0.15 | P44: 0.1 | Q44: 0.1 | R44: 0.1
A45: …, amount | M45: =M43*M44 -> 0 | N45: =N43*N44 -> 0 | O45: =O43*O44 -> 0 | P45: =P43*P44 -> 0 | Q45: =Q43*Q44 -> 0 | R45: =R43*R44 -> 0
A46: Downpayment/cash subsidy | M46: 2000 | N46: 2000 | O46: 2000 | P46: 2000 | Q46: 2000 | R46: 2000
A47: Amount to be financed | M47: =M43-M45-M46 -> -2000 | N47: =N43-N45-N46 -> -2000 | O47: =O43-O45-O46 -> -2000 | P47: =P43-P45-P46 -> -2000 | Q47: =Q43-Q45-Q46 -> -2000 | R47: =R43-R45-R46 -> -2000
A48: Financing period, months | M48: 240 | N48: 180 | O48: 180 | P48: 120 | Q48: 120 | R48: 120
A49: nominal interest rate charged | M49: 0.1 | N49: 0.15 | O49: 0.15 | P49: 0.2 | Q49: 0.2 | R49: 0.25
A50: indexation to inflation / payment growth | M50: 0 | N50: 0 | O50: 0 | P50: 0 | Q50: 0 | R50: 0
A51: real interst rate applied | M51: =M49-M50 -> 0.1 | N51: =N49-N50 -> 0.15 | O51: =O49-O50 -> 0.15 | P51: =P49-P50 -> 0.2 | Q51: =Q49-Q50 -> 0.2 | R51: =R49-R50 -> 0.25
A52: Monthly payment for starter dwelling, only (initial) | M52: =IF(M4=0,0,-PMT(M51/12,M48,M47)) -> 0 | N52: =IF(N4=0,0,-PMT(N51/12,N48,N47)) -> 0 | O52: =IF(O4=0,0,-PMT(O51/12,O48,O47)) -> 0 | P52: =IF(P4=0,0,-PMT(P51/12,P48,P47)) -> 0 | Q52: =IF(Q4=0,0,-PMT(Q51/12,Q48,Q47)) -> 0 | R52: =IF(R4=0,0,-PMT(R51/12,R48,R47)) -> 0
A53: Note: here, the downpayment should be LARGE to save on interest payments.
A54: Note: also the subsidy, if any, should be allocated here, mostly - in order to save on interest payments.
A56: Aggregated payments required for off-take…
A57: Financing of land separately, if applicable | M57: =M23 -> 0 | N57: =N23 -> 0 | O57: =O23 -> 0 | P57: =P23 -> 0 | Q57: =Q23 -> 0 | R57: =R23 -> 0
A58: Instrument 2: structure only | M58: =M38 -> 0 | N58: =N38 -> 0 | O58: =O38 -> 0 | P58: =P38 -> 0 | Q58: =Q38 -> 0 | R58: =R38 -> 0
A59: Remaining amount to be financed | M59: =M52 -> 0 | N59: =N52 -> 0 | O59: =O52 -> 0 | P59: =P52 -> 0 | Q59: =Q52 -> 0 | R59: =R52 -> 0
A60: Total monthly payment required, initially | M60: =M23+M38+M52 -> 0 | N60: =N23+N38+N52 -> 0 | O60: =O23+O38+O52 -> 0 | P60: =P23+P38+P52 -> 0 | Q60: =Q23+Q38+Q52 -> 0 | R60: =R23+R38+R52 -> 0
A62: Note: this payment growth (relative to initial total) should be moderate: i.e. never higher than the lower of expected inflation or expected nominal wage growth.
A64: Note: subsidies should favor lower-income households, e.g. be focused in the bottom 40 percent (as per SDG10).
A65: The relative share should be significantly higher for lower-income households, and the absolute amount should NOT increase with income.
A66: Otherwise, it is difficult to phase out the subsidy for higher-middle-income households (who would have an incentive to capture larger subsidies intended for lower-middle-income households.)
A67: As higher income households receive (at least) relatively lower subsidies, there downpayments need to be relatively higher - which they can typically better afford.
A68: Nevertheless, the affordability check (to follow) needs to assess whether monthly payments as well as downpayments are affordable across income groups.

Sheet 5rental
A1: Financing of demand model (part 2/2: rental sublets)
A2: Location, by color code | B2: Artery x artery (corner) | C2: Artery x secondary (corner) | D2: Artery x tertiary (corner) | E2: Artery (regular) | F2: Artery (cluster access) | G2: Off-grid cluster (on arteries) | H2: Secondary x secondary (corner) | I2: Secondary x tertiary (corner) | J2: Secondary (regular) | K2: Secondary (cluster access) | L2: Off-grid cluster (secondaries) | M2: Tertiary x tertiary (corner) | N2: Tertiary (regular) | O2: Tertiary (cluster access) | P2: Off-grid cluster (simple) | Q2: 2-level cluster (1st level) | R2: 2-level cluster (2nd level)
A3: ='4buildings'!A20 -> Starter type | B3: ='4buildings'!B20 -> lot only | C3: ='4buildings'!C20 -> lot only | D3: ='4buildings'!D20 -> lot only | E3: ='4buildings'!E20 -> mixed-use building | F3: ='4buildings'!F20 -> mixed-use building | G3: ='4buildings'!G20 -> lot only | H3: ='4buildings'!H20 -> lot only | ... R3: ='4buildings'!R20 -> roof
A4: ='5dwellings'!A11 -> starter dwelling main units (owned), average gross area | M4: ='5dwellings'!M11 -> 0 | N4: ='5dwellings'!N11 -> 0 | O4: ='5dwellings'!O11 -> 0 | P4: ='5dwellings'!P11 -> 0 | Q4: ='5dwellings'!Q11 -> 0 | R4: ='5dwellings'!R11 -> 0
A5: Total monthly payment required, initially | M5: ='5finance'!M60 -> 0 | N5: ='5finance'!N60 -> 0 | O5: ='5finance'!O60 -> 0 | P5: ='5finance'!P60 -> 0 | Q5: ='5finance'!Q60 -> 0 | R5: ='5finance'!R60 -> 0
A6: …per m2 | M6: =IF(M4=0,0,'5finance'!M60/'5finance'!M4) -> 0 | N6: =IF(N4=0,0,'5finance'!N60/'5finance'!N4) -> 0 | O6: =IF(O4=0,0,'5finance'!O60/'5finance'!O4) -> 0 | P6: =IF(P4=0,0,'5finance'!P60/'5finance'!P4) -> 0 | Q6: =IF(Q4=0,0,'5finance'!Q60/'5finance'!Q4) -> 0 | R6: =IF(R4=0,0,'5finance'!R60/'5finance'!R4) -> 0
A7: Note: this payment growth (relative to initial total) should be moderate: i.e. never higher than the lower of expected inflation or expected nominal wage growth.
A9: less rental income, from sublet units (where applicable)…
A10: aggregated rental sublet area | M10: ='5dwellings'!M11-'5dwellings'!M17 -> 0 | N10: ='5dwellings'!N11-'5dwellings'!N17 -> 0 | O10: ='5dwellings'!O11-'5dwellings'!O17 -> 0 | P10: ='5dwellings'!P11-'5dwellings'!P17 -> 0 | Q10: ='5dwellings'!Q11-'5dwellings'!Q17 -> 0 | R10: ='5dwellings'!R11-'5dwellings'!R17 -> 0
A11: monthly net rent per m2, excl. utilities, etc. (initial) | M11: 5 | N11: 5 | O11: 5 | P11: 4 | Q11: 4 | R11: 4
A12: monthly rent collection (initial), maximum | M12: =M11*M10 -> 0 | N12: =N11*N10 -> 0 | O12: =O11*O10 -> 0 | P12: =P11*P10 -> 0 | Q12: =Q11*Q10 -> 0 | R12: =R11*R10 -> 0
A13: less cushion to hedge against loss of rental income | M13: 0.3 | N13: =M13 -> 0.3 | O13: =N13 -> 0.3 | P13: =O13 -> 0.3 | Q13: =P13 -> 0.3 | R13: =Q13 -> 0.3
A14: monthly rent collection (initial), assumed | M14: =M12*(1-M13) -> 0 | N14: =N12*(1-N13) -> 0 | O14: =O12*(1-O13) -> 0 | P14: =P12*(1-P13) -> 0 | Q14: =Q12*(1-Q13) -> 0 | R14: =R12*(1-R13) -> 0
A15: rent: annual growth / inflation | M15: 0.04 | N15: =M15 -> 0.04 | O15: =N15 -> 0.04 | P15: =O15 -> 0.04 | Q15: =P15 -> 0.04 | R15: =Q15 -> 0.04
A17: Effective contribution required from owner-household | M17: ='5finance'!M60-M14 -> 0 | N17: ='5finance'!N60-N14 -> 0 | O17: ='5finance'!O60-O14 -> 0 | P17: ='5finance'!P60-P14 -> 0 | Q17: ='5finance'!Q60-Q14 -> 0 | R17: ='5finance'!R60-R14 -> 0
A18: ...plus rental income used to cover financial obligations | M18: =M14 -> 0 | N18: =N14 -> 0 | O18: =O14 -> 0 | P18: =P14 -> 0 | Q18: =Q14 -> 0 | R18: =R14 -> 0
A19: Total downpayment, by household | M19: =IF(M4=0,0,'5finance'!M31+'5finance'!M45) -> 0 | N19: ='5finance'!N31+'5finance'!N45 -> 0 | O19: ='5finance'!O31+'5finance'!O45 -> 0 | P19: ='5finance'!P31+'5finance'!P45 -> 0 | Q19: ='5finance'!Q31+'5finance'!Q45 -> 0 | R19: ='5finance'!R31+'5finance'!R45 -> 0
A20: downpayment as a share of total cost | M20: =IF('5finance'!M8=0,0,M19/'5finance'!M8) -> 0 | N20: =IF('5finance'!N8=0,0,N19/'5finance'!N8) -> 0 | O20: =IF('5finance'!O8=0,0,O19/'5finance'!O8) -> 0 | P20: =IF('5finance'!P8=0,0,P19/'5finance'!P8) -> 0 | Q20: =IF('5finance'!Q8=0,0,Q19/'5finance'!Q8) -> 0 | R20: =IF('5finance'!R8=0,0,R19/'5finance'!R8) -> 0
A21: Total downpayment subsidy (cash support) | M21: =IF(M4=0,0,'5finance'!M32+'5finance'!M46) -> 0 | N21: =IF(N4=0,0,'5finance'!N32+'5finance'!N46) -> 0 | O21: =IF(O4=0,0,'5finance'!O32+'5finance'!O46) -> 0 | P21: =IF(P4=0,0,'5finance'!P32+'5finance'!P46) -> 0 | Q21: =IF(Q4=0,0,'5finance'!Q32+'5finance'!Q46) -> 0 | R21: =IF(R4=0,0,'5finance'!R32+'5finance'!R46) -> 0
A22: subsidy as a share of total cost | M22: =IF('5finance'!M8=0,0,M21/'5finance'!M8) -> 0 | N22: =IF('5finance'!N8=0,0,N21/'5finance'!N8) -> 0 | O22: =IF('5finance'!O8=0,0,O21/'5finance'!O8) -> 0 | P22: =IF('5finance'!P8=0,0,P21/'5finance'!P8) -> 0 | Q22: =IF('5finance'!Q8=0,0,Q21/'5finance'!Q8) -> 0 | R22: =IF('5finance'!R8=0,0,R21/'5finance'!R8) -> 0
A23: De-risking: aggregated loan-to-value ratio (LTV) | M23: =1-(M19+M21)/'5finance'!M8 -> #DIV/0! | N23: =1-(N19+N21)/'5finance'!N8 -> #DIV/0! | O23: =1-(O19+O21)/'5finance'!O8 -> #DIV/0! | P23: =1-(P19+P21)/'5finance'!P8 -> #DIV/0! | Q23: =1-(Q19+Q21)/'5finance'!Q8 -> #DIV/0! | R23: =1-(R19+R21)/'5finance'!R8 -> #DIV/0!
A25: Note: subsidies should favor lower-income households, e.g. be focused in the bottom 40 percent (as per SDG10).
A26: The relative share should be significantly higher for lower-income households, and the absolute amount should NOT increase with income.
A27: Otherwise, it is difficult to phase out the subsidy for higher-middle-income households (who would have an incentive to capture larger subsidies intended for lower-middle-income households.)
A28: As higher income households receive (at least) relatively lower subsidies, there downpayments need to be relatively higher - which they can typically better afford.
A29: Nevertheless, the affordability check (to follow) needs to assess whether monthly payments as well as downpayments are affordable across income groups.

Sheet 5affordability
A1: Affordability model — assessing households' payment capacity vs. required contributions
A3: PART 1. Affordability assessment for OWNERSHIP. Comparing payment capacity w/ required monthly payment & downpayment. | H3: Artery x artery (corner) | I3: Artery x secondary (corner) | J3: Artery x tertiary (corner) | K3: Artery (regular) | L3: Artery (cluster access) | M3: Off-grid cluster (on arteries) | N3: Secondary x secondary (corner) | O3: Secondary x tertiary (corner) | P3: Secondary (regular) | Q3: Secondary (cluster access) | R3: Off-grid cluster (secondaries) | S3: Tertiary x tertiary (corner) | T3: Tertiary (regular) | U3: Tertiary (cluster access) | V3: Off-grid cluster (simple) | W3: 2-level cluster (1st level) | X3: 2-level cluster (2nd level)
G4: ='5finance'!A3 -> Starter type | H4: ='5finance'!B3 -> lot only | I4: ='5finance'!C3 -> lot only | J4: ='5finance'!D3 -> lot only | K4: ='5finance'!E3 -> mixed-use building | L4: ='5finance'!F3 -> mixed-use building | M4: ='5finance'!G3 -> lot only | N4: ='5finance'!H3 -> lot only | ... X4: ='5finance'!R3 -> roof
G5: ='5dwellings'!A11 -> starter dwelling main units (owned), average gross area | H5: ='5dwellings'!B17 -> 0 | I5: ='5dwellings'!C17 -> 0 | J5: ='5dwellings'!D17 -> 0 | K5: ='5dwellings'!E17 -> 0 | L5: ='5dwellings'!F17 -> 0 | M5: ='5dwellings'!G17 -> 0 | N5: ='5dwellings'!H17 -> 0 | O5: ='5dwellings'!I17 -> 0 | ... X5: ='5dwellings'!R17 -> 0
G6: Monthly payment capacity required | S6: ='5rental'!M17 -> 0 | T6: ='5rental'!N17 -> 0 | U6: ='5rental'!O17 -> 0 | V6: ='5rental'!P17 -> 0 | W6: ='5rental'!Q17 -> 0 | X6: ='5rental'!R17 -> 0
G7: Downpayment capacity required | S7: ='5rental'!M19 -> 0 | T7: ='5rental'!N19 -> 0 | U7: ='5rental'!O19 -> 0 | V7: ='5rental'!P19 -> 0 | W7: ='5rental'!Q19 -> 0 | X7: ='5rental'!R19 -> 0
C9: income group | D9: Monthly household income | E9: Residual income disposable for housing (safe payment capacity) | G9: affordable down-payment | S9: Affordability assessment - OWNERSHIP (Comparison of payment capacity and required payment) | Y9: Included?
A10: typical market | B10: high income (e.g. quintile 5) | C10: decile 10 | D10: 1542.9535 | E10: 0.35 | F10: =E10*D10 -> 540.03371 | G10: =D10*12 -> 18515.442 | S10: =IF(S5=0,"No",IF(AND(F10>S6,G10>S7), "Yes",IF(AND(F10>S6,G10<S7), "Downpayment",IF(AND(F10<S6,G10>S7), "Installment","No")))) -> No | T10: =IF(T5=0,"No",IF(AND(F10>T6,G10>T7), "Yes",IF(AND(F10>T6,G10<T7), "Downpayment",IF(AND(F10<T6,G10>T7), "Installment","No")))) -> No | U10: =IF(U5=0,"No",IF(AND(F10>U6,G10>U7), "Yes",IF(AND(F10>U6,G10<U7), "Downpayment",IF(AND(F10<U6,G10>U7), "Installment","No")))) -> No | V10: =IF(V5=0,"No",IF(AND(F10>V6,G10>V7), "Yes",IF(AND(F10>V6,G10<V7), "Downpayment",IF(AND(F10<V6,G10>V7), "Installment","No")))) -> No | W10: =IF(W5=0,"No",IF(AND(F10>W6,G10>W7), "Yes",IF(AND(F10>W6,G10<W7), "Downpayment",IF(AND(F10<W6,G10>W7), "Installment","No")))) -> No | X10: =IF(X5=0,"No",IF(AND(F10>X6,G10>X7), "Yes",IF(AND(F10>X6,G10<X7), "Downpayment",IF(AND(F10<X6,G10>X7), "Installment","No")))) -> No | Y10: =IF(COUNTIF(S10:X10,"Yes")>0,"Yes","No") -> No | Z10: =C10 -> decile 10 | AB10: =IF(S10="Yes",0.1,0) -> 0 | AC10: =IF(T10="Yes",0.1,0) -> 0 | AD10: =IF(U10="Yes",0.1,0) -> 0 | AE10: =IF(V10="Yes",0.1,0) -> 0 | AF10: =IF(W10="Yes",0.1,0) -> 0 | AG10: =IF(X10="Yes",0.1,0) -> 0
C11: decile 9 | D11: 847.11171 | E11: 0.325 | F11: =E11*D11 -> 275.3113 | G11: =D11*9 -> 7624.0054 | S11: =IF(S5=0,"No",IF(AND(F11>S6,G11>S7), "Yes",IF(AND(F11>S6,G11<S7), "Downpayment",IF(AND(F11<S6,G11>S7), "Installment","No")))) -> No | T11: =IF(T5=0,"No",IF(AND(F11>T6,G11>T7), "Yes",IF(AND(F11>T6,G11<T7), "Downpayment",IF(AND(F11<T6,G11>T7), "Installment","No")))) -> No | U11: =IF(U5=0,"No",IF(AND(F11>U6,G11>U7), "Yes",IF(AND(F11>U6,G11<U7), "Downpayment",IF(AND(F11<U6,G11>U7), "Installment","No")))) -> No | V11: =IF(V5=0,"No",IF(AND(F11>V6,G11>V7), "Yes",IF(AND(F11>V6,G11<V7), "Downpayment",IF(AND(F11<V6,G11>V7), "Installment","No")))) -> No | W11: =IF(W5=0,"No",IF(AND(F11>W6,G11>W7), "Yes",IF(AND(F11>W6,G11<W7), "Downpayment",IF(AND(F11<W6,G11>W7), "Installment","No")))) -> No | X11: =IF(X5=0,"No",IF(AND(F11>X6,G11>X7), "Yes",IF(AND(F11>X6,G11<X7), "Downpayment",IF(AND(F11<X6,G11>X7), "Installment","No")))) -> No | Y11: =IF(COUNTIF(S11:X11,"Yes")>0,"Yes","No") -> No | Z11: =C11 -> decile 9 | AB11: =IF(S11="Yes",0.1,0) -> 0 | AC11: =IF(T11="Yes",0.1,0) -> 0 | AD11: =IF(U11="Yes",0.1,0) -> 0 | AE11: =IF(V11="Yes",0.1,0) -> 0 | AF11: =IF(W11="Yes",0.1,0) -> 0 | AG11: =IF(X11="Yes",0.1,0) -> 0
A12: just below market frontier: middle 40% | B12: higher middle income (e.g. quintile 4) | C12: decile 8 | D12: 658.46918 | E12: 0.3 | F12: =E12*D12 -> 197.54076 | G12: =D12*6 -> 3950.8151 | S12: =IF(S5=0,"No",IF(AND(F12>S6,G12>S7), "Yes",IF(AND(F12>S6,G12<S7), "Downpayment",IF(AND(F12<S6,G12>S7), "Installment","No")))) -> No | T12: =IF(T5=0,"No",IF(AND(F12>T6,G12>T7), "Yes",IF(AND(F12>T6,G12<T7), "Downpayment",IF(AND(F12<T6,G12>T7), "Installment","No")))) -> No | U12: =IF(U5=0,"No",IF(AND(F12>U6,G12>U7), "Yes",IF(AND(F12>U6,G12<U7), "Downpayment",IF(AND(F12<U6,G12>U7), "Installment","No")))) -> No | V12: =IF(V5=0,"No",IF(AND(F12>V6,G12>V7), "Yes",IF(AND(F12>V6,G12<V7), "Downpayment",IF(AND(F12<V6,G12>V7), "Installment","No")))) -> No | W12: =IF(W5=0,"No",IF(AND(F12>W6,G12>W7), "Yes",IF(AND(F12>W6,G12<W7), "Downpayment",IF(AND(F12<W6,G12>W7), "Installment","No")))) -> No | X12: =IF(X5=0,"No",IF(AND(F12>X6,G12>X7), "Yes",IF(AND(F12>X6,G12<X7), "Downpayment",IF(AND(F12<X6,G12>X7), "Installment","No")))) -> No | Y12: =IF(COUNTIF(S12:X12,"Yes")>0,"Yes","No") -> No | Z12: =C12 -> decile 8 | AB12: =IF(S12="Yes",0.1,0) -> 0 | AC12: =IF(T12="Yes",0.1,0) -> 0 | AD12: =IF(U12="Yes",0.1,0) -> 0 | AE12: =IF(V12="Yes",0.1,0) -> 0 | AF12: =IF(W12="Yes",0.1,0) -> 0 | AG12: =IF(X12="Yes",0.1,0) -> 0
C13: decile 7 | D13: 549.91075 | E13: 0.275 | F13: =E13*D13 -> 151.22546 | G13: =D13*5 -> 2749.5538 | S13: =IF(S5=0,"No",IF(AND(F13>S6,G13>S7), "Yes",IF(AND(F13>S6,G13<S7), "Downpayment",IF(AND(F13<S6,G13>S7), "Installment","No")))) -> No | T13: =IF(T5=0,"No",IF(AND(F13>T6,G13>T7), "Yes",IF(AND(F13>T6,G13<T7), "Downpayment",IF(AND(F13<T6,G13>T7), "Installment","No")))) -> No | U13: =IF(U5=0,"No",IF(AND(F13>U6,G13>U7), "Yes",IF(AND(F13>U6,G13<U7), "Downpayment",IF(AND(F13<U6,G13>U7), "Installment","No")))) -> No | V13: =IF(V5=0,"No",IF(AND(F13>V6,G13>V7), "Yes",IF(AND(F13>V6,G13<V7), "Downpayment",IF(AND(F13<V6,G13>V7), "Installment","No")))) -> No | W13: =IF(W5=0,"No",IF(AND(F13>W6,G13>W7), "Yes",IF(AND(F13>W6,G13<W7), "Downpayment",IF(AND(F13<W6,G13>W7), "Installment","No")))) -> No | X13: =IF(X5=0,"No",IF(AND(F13>X6,G13>X7), "Yes",IF(AND(F13>X6,G13<X7), "Downpayment",IF(AND(F13<X6,G13>X7), "Installment","No")))) -> No | Y13: =IF(COUNTIF(S13:X13,"Yes")>0,"Yes","No") -> No | Z13: =C13 -> decile 7 | AB13: =IF(S13="Yes",0.1,0) -> 0 | AC13: =IF(T13="Yes",0.1,0) -> 0 | AD13: =IF(U13="Yes",0.1,0) -> 0 | AE13: =IF(V13="Yes",0.1,0) -> 0 | AF13: =IF(W13="Yes",0.1,0) -> 0 | AG13: =IF(X13="Yes",0.1,0) -> 0
B14: lower middle income (e.g. quintile 3) | C14: decile 6 | D14: 468.04701 | E14: 0.25 | F14: =E14*D14 -> 117.01175 | G14: =D14*4 -> 1872.1881 | S14: =IF(S5=0,"No",IF(AND(F14>S6,G14>S7), "Yes",IF(AND(F14>S6,G14<S7), "Downpayment",IF(AND(F14<S6,G14>S7), "Installment","No")))) -> No | T14: =IF(T5=0,"No",IF(AND(F14>T6,G14>T7), "Yes",IF(AND(F14>T6,G14<T7), "Downpayment",IF(AND(F14<T6,G14>T7), "Installment","No")))) -> No | U14: =IF(U5=0,"No",IF(AND(F14>U6,G14>U7), "Yes",IF(AND(F14>U6,G14<U7), "Downpayment",IF(AND(F14<U6,G14>U7), "Installment","No")))) -> No | V14: =IF(V5=0,"No",IF(AND(F14>V6,G14>V7), "Yes",IF(AND(F14>V6,G14<V7), "Downpayment",IF(AND(F14<V6,G14>V7), "Installment","No")))) -> No | W14: =IF(W5=0,"No",IF(AND(F14>W6,G14>W7), "Yes",IF(AND(F14>W6,G14<W7), "Downpayment",IF(AND(F14<W6,G14>W7), "Installment","No")))) -> No | X14: =IF(X5=0,"No",IF(AND(F14>X6,G14>X7), "Yes",IF(AND(F14>X6,G14<X7), "Downpayment",IF(AND(F14<X6,G14>X7), "Installment","No")))) -> No | Y14: =IF(COUNTIF(S14:X14,"Yes")>0,"Yes","No") -> No | Z14: =C14 -> decile 6 | AB14: =IF(S14="Yes",0.1,0) -> 0 | AC14: =IF(T14="Yes",0.1,0) -> 0 | AD14: =IF(U14="Yes",0.1,0) -> 0 | AE14: =IF(V14="Yes",0.1,0) -> 0 | AF14: =IF(W14="Yes",0.1,0) -> 0 | AG14: =IF(X14="Yes",0.1,0) -> 0
C15: decile 5 | D15: 400.42045 | E15: 0.225 | F15: =E15*D15 -> 90.094601 | G15: =D15*3 -> 1201.2613 | S15: =IF(S5=0,"No",IF(AND(F15>S6,G15>S7), "Yes",IF(AND(F15>S6,G15<S7), "Downpayment",IF(AND(F15<S6,G15>S7), "Installment","No")))) -> No | T15: =IF(T5=0,"No",IF(AND(F15>T6,G15>T7), "Yes",IF(AND(F15>T6,G15<T7), "Downpayment",IF(AND(F15<T6,G15>T7), "Installment","No")))) -> No | U15: =IF(U5=0,"No",IF(AND(F15>U6,G15>U7), "Yes",IF(AND(F15>U6,G15<U7), "Downpayment",IF(AND(F15<U6,G15>U7), "Installment","No")))) -> No | V15: =IF(V5=0,"No",IF(AND(F15>V6,G15>V7), "Yes",IF(AND(F15>V6,G15<V7), "Downpayment",IF(AND(F15<V6,G15>V7), "Installment","No")))) -> No | W15: =IF(W5=0,"No",IF(AND(F15>W6,G15>W7), "Yes",IF(AND(F15>W6,G15<W7), "Downpayment",IF(AND(F15<W6,G15>W7), "Installment","No")))) -> No | X15: =IF(X5=0,"No",IF(AND(F15>X6,G15>X7), "Yes",IF(AND(F15>X6,G15<X7), "Downpayment",IF(AND(F15<X6,G15>X7), "Installment","No")))) -> No | Y15: =IF(COUNTIF(S15:X15,"Yes")>0,"Yes","No") -> No | Z15: =C15 -> decile 5 | AB15: =IF(S15="Yes",0.1,0) -> 0 | AC15: =IF(T15="Yes",0.1,0) -> 0 | AD15: =IF(U15="Yes",0.1,0) -> 0 | AE15: =IF(V15="Yes",0.1,0) -> 0 | AF15: =IF(W15="Yes",0.1,0) -> 0 | AG15: =IF(X15="Yes",0.1,0) -> 0
A16: SDG focus: bottom 40% | B16: low income (e.g. quintile 2) | C16: decile 4 | D16: 350.59035 | E16: 0.2 | F16: =E16*D16 -> 70.11807 | G16: =D16*2 -> 701.1807 | S16: =IF(S5=0,"No",IF(AND(F16>S6,G16>S7), "Yes",IF(AND(F16>S6,G16<S7), "Downpayment",IF(AND(F16<S6,G16>S7), "Installment","No")))) -> No | T16: =IF(T5=0,"No",IF(AND(F16>T6,G16>T7), "Yes",IF(AND(F16>T6,G16<T7), "Downpayment",IF(AND(F16<T6,G16>T7), "Installment","No")))) -> No | U16: =IF(U5=0,"No",IF(AND(F16>U6,G16>U7), "Yes",IF(AND(F16>U6,G16<U7), "Downpayment",IF(AND(F16<U6,G16>U7), "Installment","No")))) -> No | V16: =IF(V5=0,"No",IF(AND(F16>V6,G16>V7), "Yes",IF(AND(F16>V6,G16<V7), "Downpayment",IF(AND(F16<V6,G16>V7), "Installment","No")))) -> No | W16: =IF(W5=0,"No",IF(AND(F16>W6,G16>W7), "Yes",IF(AND(F16>W6,G16<W7), "Downpayment",IF(AND(F16<W6,G16>W7), "Installment","No")))) -> No | X16: =IF(X5=0,"No",IF(AND(F16>X6,G16>X7), "Yes",IF(AND(F16>X6,G16<X7), "Downpayment",IF(AND(F16<X6,G16>X7), "Installment","No")))) -> No | Y16: =IF(COUNTIF(S16:X16,"Yes")>0,"Yes","No") -> No | Z16: =C16 -> decile 4 | AB16: =IF(S16="Yes",0.1,0) -> 0 | AC16: =IF(T16="Yes",0.1,0) -> 0 | AD16: =IF(U16="Yes",0.1,0) -> 0 | AE16: =IF(V16="Yes",0.1,0) -> 0 | AF16: =IF(W16="Yes",0.1,0) -> 0 | AG16: =IF(X16="Yes",0.1,0) -> 0
C17: decile 3 | D17: 298.9806 | E17: 0.175 | F17: =E17*D17 -> 52.321605 | G17: =D17*2 -> 597.9612 | S17: =IF(S5=0,"No",IF(AND(F17>S6,G17>S7), "Yes",IF(AND(F17>S6,G17<S7), "Downpayment",IF(AND(F17<S6,G17>S7), "Installment","No")))) -> No | T17: =IF(T5=0,"No",IF(AND(F17>T6,G17>T7), "Yes",IF(AND(F17>T6,G17<T7), "Downpayment",IF(AND(F17<T6,G17>T7), "Installment","No")))) -> No | U17: =IF(U5=0,"No",IF(AND(F17>U6,G17>U7), "Yes",IF(AND(F17>U6,G17<U7), "Downpayment",IF(AND(F17<U6,G17>U7), "Installment","No")))) -> No | V17: =IF(V5=0,"No",IF(AND(F17>V6,G17>V7), "Yes",IF(AND(F17>V6,G17<V7), "Downpayment",IF(AND(F17<V6,G17>V7), "Installment","No")))) -> No | W17: =IF(W5=0,"No",IF(AND(F17>W6,G17>W7), "Yes",IF(AND(F17>W6,G17<W7), "Downpayment",IF(AND(F17<W6,G17>W7), "Installment","No")))) -> No | X17: =IF(X5=0,"No",IF(AND(F17>X6,G17>X7), "Yes",IF(AND(F17>X6,G17<X7), "Downpayment",IF(AND(F17<X6,G17>X7), "Installment","No")))) -> No | Y17: =IF(COUNTIF(S17:X17,"Yes")>0,"Yes","No") -> No | Z17: =C17 -> decile 3 | AB17: =IF(S17="Yes",0.1,0) -> 0 | AC17: =IF(T17="Yes",0.1,0) -> 0 | AD17: =IF(U17="Yes",0.1,0) -> 0 | AE17: =IF(V17="Yes",0.1,0) -> 0 | AF17: =IF(W17="Yes",0.1,0) -> 0 | AG17: =IF(X17="Yes",0.1,0) -> 0
B18: poor (e.g. quintile 1) | C18: decile 2 | D18: 256.26909 | E18: 0.15 | F18: =E18*D18 -> 38.440363 | G18: =D18*1 -> 256.26909 | S18: =IF(S5=0,"No",IF(AND(F18>S6,G18>S7), "Yes",IF(AND(F18>S6,G18<S7), "Downpayment",IF(AND(F18<S6,G18>S7), "Installment","No")))) -> No | T18: =IF(T5=0,"No",IF(AND(F18>T6,G18>T7), "Yes",IF(AND(F18>T6,G18<T7), "Downpayment",IF(AND(F18<T6,G18>T7), "Installment","No")))) -> No | U18: =IF(U5=0,"No",IF(AND(F18>U6,G18>U7), "Yes",IF(AND(F18>U6,G18<U7), "Downpayment",IF(AND(F18<U6,G18>U7), "Installment","No")))) -> No | V18: =IF(V5=0,"No",IF(AND(F18>V6,G18>V7), "Yes",IF(AND(F18>V6,G18<V7), "Downpayment",IF(AND(F18<V6,G18>V7), "Installment","No")))) -> No | W18: =IF(W5=0,"No",IF(AND(F18>W6,G18>W7), "Yes",IF(AND(F18>W6,G18<W7), "Downpayment",IF(AND(F18<W6,G18>W7), "Installment","No")))) -> No | X18: =IF(X5=0,"No",IF(AND(F18>X6,G18>X7), "Yes",IF(AND(F18>X6,G18<X7), "Downpayment",IF(AND(F18<X6,G18>X7), "Installment","No")))) -> No | Y18: =IF(COUNTIF(S18:X18,"Yes")>0,"Yes","No") -> No | Z18: =C18 -> decile 2 | AB18: =IF(S18="Yes",0.1,0) -> 0 | AC18: =IF(T18="Yes",0.1,0) -> 0 | AD18: =IF(U18="Yes",0.1,0) -> 0 | AE18: =IF(V18="Yes",0.1,0) -> 0 | AF18: =IF(W18="Yes",0.1,0) -> 0 | AG18: =IF(X18="Yes",0.1,0) -> 0
C19: decile 1 | D19: 201.10005 | E19: 0.125 | F19: =E19*D19 -> 25.137506 | G19: =D19*1 -> 201.10005 | S19: =IF(S5=0,"No",IF(AND(F19>S6,G19>S7), "Yes",IF(AND(F19>S6,G19<S7), "Downpayment",IF(AND(F19<S6,G19>S7), "Installment","No")))) -> No | T19: =IF(T5=0,"No",IF(AND(F19>T6,G19>T7), "Yes",IF(AND(F19>T6,G19<T7), "Downpayment",IF(AND(F19<T6,G19>T7), "Installment","No")))) -> No | U19: =IF(U5=0,"No",IF(AND(F19>U6,G19>U7), "Yes",IF(AND(F19>U6,G19<U7), "Downpayment",IF(AND(F19<U6,G19>U7), "Installment","No")))) -> No | V19: =IF(V5=0,"No",IF(AND(F19>V6,G19>V7), "Yes",IF(AND(F19>V6,G19<V7), "Downpayment",IF(AND(F19<V6,G19>V7), "Installment","No")))) -> No | W19: =IF(W5=0,"No",IF(AND(F19>W6,G19>W7), "Yes",IF(AND(F19>W6,G19<W7), "Downpayment",IF(AND(F19<W6,G19>W7), "Installment","No")))) -> No | X19: =IF(X5=0,"No",IF(AND(F19>X6,G19>X7), "Yes",IF(AND(F19>X6,G19<X7), "Downpayment",IF(AND(F19<X6,G19>X7), "Installment","No")))) -> No | Y19: =IF(COUNTIF(S19:X19,"Yes")>0,"Yes","No") -> No | Z19: =C19 -> decile 1 | AB19: =IF(S19="Yes",0.1,0) -> 0 | AC19: =IF(T19="Yes",0.1,0) -> 0 | AD19: =IF(U19="Yes",0.1,0) -> 0 | AE19: =IF(V19="Yes",0.1,0) -> 0 | AF19: =IF(W19="Yes",0.1,0) -> 0 | AG19: =IF(X19="Yes",0.1,0) -> 0
A21: Affordability of ownership | F21: Included | S21: =AB21 -> 0 | T21: =AC21 -> 0 | U21: =AD21 -> 0 | V21: =AE21 -> 0 | W21: =AF21 -> 0 | X21: =AG21 -> 0 | Y21: =MAX(S21:X21) -> 0 | AB21: =SUM(AB10:AB19) -> 0 | AC21: =SUM(AC10:AC19) -> 0 | AD21: =SUM(AD10:AD19) -> 0 | AE21: =SUM(AE10:AE19) -> 0 | AF21: =SUM(AF10:AF19) -> 0 | AG21: =SUM(AG10:AG19) -> 0
F22: Excluded | S22: =AB22 -> 1 | T22: =AC22 -> 1 | U22: =AD22 -> 1 | V22: =AE22 -> 1 | W22: =AF22 -> 1 | X22: =AG22 -> 1 | Y22: =1-Y21 -> 1 | AB22: =1-AB21 -> 1 | AC22: =1-AC21 -> 1 | AD22: =1-AD21 -> 1 | AE22: =1-AE21 -> 1 | AF22: =1-AF21 -> 1 | AG22: =1-AG21 -> 1
A26: PART 2. Affordability assessment for small-scale private RENTAL. Comparing payment capacity with required rent. | S26: Tertiary x tertiary (corner) | T26: Tertiary (regular) | U26: Tertiary (cluster access) | V26: Off-grid cluster (simple) | W26: 2-level cluster (1st level) | X26: 2-level cluster (2nd level)
G27: Smallest rental sublet (possibly a tiny room for a poor single person migrant household) | S27: =IF('5dwellings'!M19=0,0,IF('5dwellings'!M15>0,IF('5dwellings'!M16>0,MIN('5dwellings'!M15:M16),'5dwellings'!M15),'5dwellings'!M16)) -> 0 | T27: =IF('5dwellings'!N19=0,0,IF('5dwellings'!N15>0,IF('5dwellings'!N16>0,MIN('5dwellings'!N15:N16),'5dwellings'!N15),'5dwellings'!N16)) -> 0 | U27: =IF('5dwellings'!O19=0,0,IF('5dwellings'!O15>0,IF('5dwellings'!O16>0,MIN('5dwellings'!O15:O16),'5dwellings'!O15),'5dwellings'!O16)) -> 0 | V27: =IF('5dwellings'!P19=0,0,IF('5dwellings'!P15>0,IF('5dwellings'!P16>0,MIN('5dwellings'!P15:P16),'5dwellings'!P15),'5dwellings'!P16)) -> 0 | W27: =IF('5dwellings'!Q19=0,0,IF('5dwellings'!Q15>0,IF('5dwellings'!Q16>0,MIN('5dwellings'!Q15:Q16),'5dwellings'!Q15),'5dwellings'!Q16)) -> 0 | X27: =IF('5dwellings'!R19=0,0,IF('5dwellings'!R15>0,IF('5dwellings'!R16>0,MIN('5dwellings'!R15:R16),'5dwellings'!R15),'5dwellings'!R16)) -> 0
G28: lowest rent | S28: =IF(S27=0,"n/a",S27*'5rental'!M11) -> n/a | T28: =IF(T27=0,"n/a",T27*'5rental'!N11) -> n/a | U28: =IF(U27=0,"n/a",U27*'5rental'!O11) -> n/a | V28: =IF(V27=0,"n/a",V27*'5rental'!P11) -> n/a | W28: =IF(W27=0,"n/a",W27*'5rental'!Q11) -> n/a | X28: =IF(X27=0,"n/a",X27*'5rental'!R11) -> n/a
C30: income group | D30: Monthly household income | E30: Residual income disposable for housing (safe payment capacity) | G30: available savings | S30: Affordability assessment - OWNERSHIP (Comparison of payment capacity and required payment) | Y30: Included?
A31: just below market frontier | B31: =B14 -> lower middle income (e.g. quintile 3) | C31: =C14 -> decile 6 | D31: =D14 -> 468.04701 | E31: 0.25 | F31: =E31*D31 -> 117.01175 | G31: n/a | S31: =IF(S27=0,"No",IF(S28=0,"No",IF(S28<F31,"Yes","No"))) -> No | T31: =IF(T27=0,"No",IF(T28=0,"No",IF(T28<F31,"Yes","No"))) -> No | U31: =IF(U27=0,"No",IF(U28=0,"No",IF(U28<F31,"Yes","No"))) -> No | V31: =IF(V27=0,"No",IF(V28=0,"No",IF(V28<F31,"Yes","No"))) -> No | W31: =IF(W27=0,"No",IF(W28=0,"No",IF(W28<F31,"Yes","No"))) -> No | X31: =IF(X27=0,"No",IF(X28=0,"No",IF(X28<F31,"Yes","No"))) -> No | Y31: =IF(COUNTIF(S31:X31,"Yes")>0,"Yes","No") -> No | Z31: =C31 -> decile 6 | AB31: =IF(S31="Yes",0.1,0) -> 0 | AC31: =IF(T31="Yes",0.1,0) -> 0 | AD31: =IF(U31="Yes",0.1,0) -> 0 | AE31: =IF(V31="Yes",0.1,0) -> 0 | AF31: =IF(W31="Yes",0.1,0) -> 0 | AG31: =IF(X31="Yes",0.1,0) -> 0
C32: =C15 -> decile 5 | D32: =D15 -> 400.42045 | E32: 0.225 | F32: =E32*D32 -> 90.094601 | G32: n/a | S32: =IF(S27=0,"No",IF(S28=0,"No",IF(S28<F32,"Yes","No"))) -> No | T32: =IF(T27=0,"No",IF(T28=0,"No",IF(T28<F32,"Yes","No"))) -> No | U32: =IF(U27=0,"No",IF(U28=0,"No",IF(U28<F32,"Yes","No"))) -> No | V32: =IF(V27=0,"No",IF(V28=0,"No",IF(V28<F32,"Yes","No"))) -> No | W32: =IF(W27=0,"No",IF(W28=0,"No",IF(W28<F32,"Yes","No"))) -> No | X32: =IF(X27=0,"No",IF(X28=0,"No",IF(X28<F32,"Yes","No"))) -> No | Y32: =IF(COUNTIF(S32:X32,"Yes")>0,"Yes","No") -> No | Z32: =C32 -> decile 5 | AB32: =IF(S32="Yes",0.1,0) -> 0 | AC32: =IF(T32="Yes",0.1,0) -> 0 | AD32: =IF(U32="Yes",0.1,0) -> 0 | AE32: =IF(V32="Yes",0.1,0) -> 0 | AF32: =IF(W32="Yes",0.1,0) -> 0 | AG32: =IF(X32="Yes",0.1,0) -> 0
A33: SDG focus: bottom 40% | B33: low income (e.g. quintile 2) | C33: decile 4 | D33: 400 | E33: 0.2 | F33: =E33*D33 -> 80 | G33: n/a | S33: =IF(S27=0,"No",IF(S28=0,"No",IF(S28<F33,"Yes","No"))) -> No | T33: =IF(T27=0,"No",IF(T28=0,"No",IF(T28<F33,"Yes","No"))) -> No | U33: =IF(U27=0,"No",IF(U28=0,"No",IF(U28<F33,"Yes","No"))) -> No | V33: =IF(V27=0,"No",IF(V28=0,"No",IF(V28<F33,"Yes","No"))) -> No | W33: =IF(W27=0,"No",IF(W28=0,"No",IF(W28<F33,"Yes","No"))) -> No | X33: =IF(X27=0,"No",IF(X28=0,"No",IF(X28<F33,"Yes","No"))) -> No | Y33: =IF(COUNTIF(S33:X33,"Yes")>0,"Yes","No") -> No | Z33: =C33 -> decile 4 | AB33: =IF(S33="Yes",0.1,0) -> 0 | AC33: =IF(T33="Yes",0.1,0) -> 0 | AD33: =IF(U33="Yes",0.1,0) -> 0 | AE33: =IF(V33="Yes",0.1,0) -> 0 | AF33: =IF(W33="Yes",0.1,0) -> 0 | AG33: =IF(X33="Yes",0.1,0) -> 0
C34: decile 3 | D34: 300 | E34: 0.175 | F34: =E34*D34 -> 52.5 | G34: n/a | S34: =IF(S27=0,"No",IF(S28=0,"No",IF(S28<F34,"Yes","No"))) -> No | T34: =IF(T27=0,"No",IF(T28=0,"No",IF(T28<F34,"Yes","No"))) -> No | U34: =IF(U27=0,"No",IF(U28=0,"No",IF(U28<F34,"Yes","No"))) -> No | V34: =IF(V27=0,"No",IF(V28=0,"No",IF(V28<F34,"Yes","No"))) -> No | W34: =IF(W27=0,"No",IF(W28=0,"No",IF(W28<F34,"Yes","No"))) -> No | X34: =IF(X27=0,"No",IF(X28=0,"No",IF(X28<F34,"Yes","No"))) -> No | Y34: =IF(COUNTIF(S34:X34,"Yes")>0,"Yes","No") -> No | Z34: =C34 -> decile 3 | AB34: =IF(S34="Yes",0.1,0) -> 0 | AC34: =IF(T34="Yes",0.1,0) -> 0 | AD34: =IF(U34="Yes",0.1,0) -> 0 | AE34: =IF(V34="Yes",0.1,0) -> 0 | AF34: =IF(W34="Yes",0.1,0) -> 0 | AG34: =IF(X34="Yes",0.1,0) -> 0
B35: poor (e.g. quintile 1) | C35: decile 2 | D35: 250 | E35: 0.15 | F35: =E35*D35 -> 37.5 | G35: n/a | S35: =IF(S27=0,"No",IF(S28=0,"No",IF(S28<F35,"Yes","No"))) -> No | T35: =IF(T27=0,"No",IF(T28=0,"No",IF(T28<F35,"Yes","No"))) -> No | U35: =IF(U27=0,"No",IF(U28=0,"No",IF(U28<F35,"Yes","No"))) -> No | V35: =IF(V27=0,"No",IF(V28=0,"No",IF(V28<F35,"Yes","No"))) -> No | W35: =IF(W27=0,"No",IF(W28=0,"No",IF(W28<F35,"Yes","No"))) -> No | X35: =IF(X27=0,"No",IF(X28=0,"No",IF(X28<F35,"Yes","No"))) -> No | Y35: =IF(COUNTIF(S35:X35,"Yes")>0,"Yes","No") -> No | Z35: =C35 -> decile 2 | AB35: =IF(S35="Yes",0.1,0) -> 0 | AC35: =IF(T35="Yes",0.1,0) -> 0 | AD35: =IF(U35="Yes",0.1,0) -> 0 | AE35: =IF(V35="Yes",0.1,0) -> 0 | AF35: =IF(W35="Yes",0.1,0) -> 0 | AG35: =IF(X35="Yes",0.1,0) -> 0
C36: decile 1 | D36: 200 | E36: 0.125 | F36: =E36*D36 -> 25 | G36: n/a | S36: =IF(S27=0,"No",IF(S28=0,"No",IF(S28<F36,"Yes","No"))) -> No | T36: =IF(T27=0,"No",IF(T28=0,"No",IF(T28<F36,"Yes","No"))) -> No | U36: =IF(U27=0,"No",IF(U28=0,"No",IF(U28<F36,"Yes","No"))) -> No | V36: =IF(V27=0,"No",IF(V28=0,"No",IF(V28<F36,"Yes","No"))) -> No | W36: =IF(W27=0,"No",IF(W28=0,"No",IF(W28<F36,"Yes","No"))) -> No | X36: =IF(X27=0,"No",IF(X28=0,"No",IF(X28<F36,"Yes","No"))) -> No | Y36: =IF(COUNTIF(S36:X36,"Yes")>0,"Yes","No") -> No | Z36: =C36 -> decile 1 | AB36: =IF(S36="Yes",0.1,0) -> 0 | AC36: =IF(T36="Yes",0.1,0) -> 0 | AD36: =IF(U36="Yes",0.1,0) -> 0 | AE36: =IF(V36="Yes",0.1,0) -> 0 | AF36: =IF(W36="Yes",0.1,0) -> 0 | AG36: =IF(X36="Yes",0.1,0) -> 0
A38: Affordability of rental sublets | F38: Included | S38: =IF(AB38=0.4,"n/a",AB38) -> n/a | T38: =IF(AC38=0.4,"n/a",AC38) -> n/a | U38: =IF(AD38=0.4,"n/a",AD38) -> n/a | V38: =IF(AE38=0.4,"n/a",AE38) -> n/a | W38: =IF(AF38=0.4,"n/a",AF38) -> n/a | X38: =IF(AG38=0.4,"n/a",AG38) -> n/a | Y38: =MAX(S38:X38) -> 0 | AB38: =SUM(AB31:AB36)+0.4 -> 0.4 | AC38: =SUM(AC31:AC36)+0.4 -> 0.4 | AD38: =SUM(AD31:AD36)+0.4 -> 0.4 | AE38: =SUM(AE31:AE36)+0.4 -> 0.4 | AF38: =SUM(AF31:AF36)+0.4 -> 0.4 | AG38: =SUM(AG31:AG36)+0.4 -> 0.4
F39: Excluded | S39: =IF(AB39=0.6,"n/a",AB39) -> n/a | T39: =IF(AC39=0.6,"n/a",AC39) -> n/a | U39: =IF(AD39=0.6,"n/a",AD39) -> n/a | V39: =IF(AE39=0.6,"n/a",AE39) -> n/a | W39: =IF(AF39=0.6,"n/a",AF39) -> n/a | X39: =IF(AG39=0.6,"n/a",AG39) -> n/a | Y39: =1-Y38 -> 1 | AB39: =1-AB38 -> 0.6 | AC39: =1-AC38 -> 0.6 | AD39: =1-AD38 -> 0.6 | AE39: =1-AE38 -> 0.6 | AF39: =1-AF38 -> 0.6 | AG39: =1-AG38 -> 0.6
A41: Note: for those still excluded, consider a rental voucher or other supply-side support (e.g. subsidizing the landlord)?

Sheet 6demographics
A1: Demographic projections
A2: Location, by color code | B2: Artery x artery (corner) | C2: Artery x secondary (corner) | D2: Artery x tertiary (corner) | E2: Artery (regular) | F2: Artery (cluster access) | G2: Off-grid cluster (on arteries) | H2: Secondary x secondary (corner) | I2: Secondary x tertiary (corner) | J2: Secondary (regular) | K2: Secondary (cluster access) | L2: Off-grid cluster (secondaries) | M2: Tertiary x tertiary (corner) | N2: Tertiary (regular) | O2: Tertiary (cluster access) | P2: Off-grid cluster (simple) | Q2: 2-level cluster (1st level) | R2: 2-level cluster (2nd level) | S2: Total
A3: dwelling units per lot, initial | B3: ='5dwellings'!B20 -> 0 | C3: ='5dwellings'!C20 -> 0 | D3: ='5dwellings'!D20 -> 0 | E3: ='5dwellings'!E20 -> 0 | F3: ='5dwellings'!F20 -> 0 | G3: ='5dwellings'!G20 -> 0 | H3: ='5dwellings'!H20 -> 0 | I3: ='5dwellings'!I20 -> 0 | ... R3: ='5dwellings'!R20 -> 1
A4: dwelling units per lot, consolidated | B4: 0 | C4: 0 | D4: 0 | E4: 28 | F4: 28 | G4: 0 | H4: 0 | I4: 0 | J4: 12 | K4: 12 | L4: 0 | M4: 12 | N4: 3 | O4: 4.5 | P4: 3 | Q4: 3 | R4: 3 | S4: initial | T4: consolidated
A5: dwelling units, initial | B5: =B3*'4buildings'!B10 -> 0 | C5: =C3*'4buildings'!C10 -> 0 | D5: =D3*'4buildings'!D10 -> 0 | E5: =E3*'4buildings'!E10 -> 0 | F5: =F3*'4buildings'!F10 -> 0 | G5: =G3*'4buildings'!G10 -> 0 | H5: =H3*'4buildings'!H10 -> 0 | I5: =I3*'4buildings'!I10 -> 0 | ... R5: =R3*'4buildings'!R10 -> 0 | S5: =SUM(B5:R5) -> 0
A6: dwelling units, consolidated | B6: =B4*'4buildings'!B10 -> 0 | C6: =C4*'4buildings'!C10 -> 0 | D6: =D4*'4buildings'!D10 -> 0 | E6: =E4*'4buildings'!E10 -> 0 | F6: =F4*'4buildings'!F10 -> 0 | G6: =G4*'4buildings'!G10 -> 0 | H6: =H4*'4buildings'!H10 -> 0 | I6: =I4*'4buildings'!I10 -> 0 | ... R6: =R4*'4buildings'!R10 -> 0 | T6: =SUM(B6:R6) -> 0
A7: household size | S7: 2.5 | T7: 4
A8: total population size | S8: =S5*S7 -> 0 | T8: =T6*T7 -> 0
A9: gross density (people per total area) | R9: over the total site: | S9: =IF(Q!Q37=0,0,S8/Q!Q37*10000) -> 0 | T9: =IF(Q!Q37=0,0,T8/Q!Q37*10000) -> 0
A10: net density (people per private land) | R10: over the private land, excl. streets, public open spaces and public amenities, but including semi-private shared spaces in clusters: | S10: =IF(Q!O32=0,0,S8/Q!O32*10000) -> 0 | T10: =IF(Q!O32=0,0,T8/Q!O32*10000) -> 0
A12: (a) from the spatial model
